Workbook

Sheet DRS
A1: Category | B1: Description | C1: Size | D1: Plant No. | E1: Flooring | F1: Walls | G1: Ceiling | H1: Fittings | I1: Mirror | J1: Washbasin | K1: Toilet | L1: Door | M1: Door keys | N1: Shower | O1: Lights | P1: Windows | Q1: Interior paint | R1: Exterior paint | S1: ACs | T1: Comments
A2: Cabins | B2: Toilet Shower | C2: 32' | D2: DR.2.T.32.3 | E2: TRUE | F2: TRUE | G2: TRUE | H2: TRUE | I2: TRUE | J2: TRUE | K2: TRUE | L2: TRUE | M2: TRUE | N2: TRUE | O2: TRUE | P2: TRUE | Q2: TRUE | R2: TRUE | S2: TRUE | T2: [2026-05-15] Revising/ Checked by Calo | By: Calo
A3: Cabins | B3: Toilet | C3: 32' | D3: DR.2.T.32.8 | E3: TRUE | F3: TRUE | G3: TRUE | H3: TRUE | I3: TRUE | J3: TRUE | K3: TRUE | L3: TRUE | M3: TRUE | N3: TRUE | O3: TRUE | P3: TRUE | Q3: TRUE | R3: TRUE | S3: TRUE | T3: [2026-05-15] Revising/ Checked by Calo - testing archive feature | By: Calo
A4: Cabins | B4: Toilet | C4: 32' | D4: DR.2.T.32.9 | E4: TRUE | F4: TRUE | G4: TRUE | H4: TRUE | I4: TRUE | J4: TRUE | K4: TRUE | L4: TRUE | M4: TRUE | N4: TRUE | O4: TRUE | P4: TRUE | Q4: TRUE | R4: TRUE | S4: TRUE | T4: [2026-05-15] Revising/ Checked by Calo - testing archive feature | By: Calo
A5: Cabins | B5: Toilet Shower | C5: 32' | D5: DR.2.TS.32.1 | E5: TRUE | F5: TRUE | G5: TRUE | H5: TRUE | I5: TRUE | J5: TRUE | K5: TRUE | L5: TRUE | M5: TRUE | N5: TRUE | O5: TRUE | P5: TRUE | Q5: TRUE | R5: TRUE | S5: TRUE | T5: [2026-05-15] Revising/ Checked by Calo - testing archive feature | By: Calo
A6: Cabins | B6: Toilet Shower | C6: 32' | D6: DR.2.TS.32.2 | E6: FALSE | F6: FALSE | G6: FALSE | H6: FALSE | I6: FALSE | J6: FALSE | K6: FALSE | L6: FALSE | M6: FALSE | N6: FALSE | O6: FALSE | P6: FALSE | Q6: FALSE | R6: FALSE | S6: FALSE | T6: No inspection
A7: Cabins | B7: Toilet Shower | C7: 32' | D7: DR.2.TS.32.3 | E7: TRUE | F7: TRUE | G7: TRUE | H7: TRUE | I7: TRUE | J7: TRUE | K7: TRUE | L7: TRUE | M7: TRUE | N7: TRUE | O7: TRUE | P7: TRUE | Q7: TRUE | R7: TRUE | S7: TRUE | T7: [2026-05-15] Revising/ Checked by Calo - testing archive feature | By: Calo
A8: Cabins | B8: Toilet Shower | C8: 32' | D8: DR.2.TS.32.4 | E8: TRUE | F8: TRUE | G8: TRUE | H8: TRUE | I8: TRUE | J8: TRUE | K8: TRUE | L8: TRUE | M8: TRUE | N8: TRUE | O8: TRUE | P8: TRUE | Q8: TRUE | R8: TRUE | S8: TRUE | T8: [2026-04-16] We remove the Branding plate . Before Deliver time we fix Before deliver we fix Barinding plate | By: calo.lategan@allaith.com
A9: Cabins | B9: Toilet Shower | C9: 32' | D9: DR.2.TS.32.5 | E9: TRUE | F9: TRUE | G9: TRUE | H9: TRUE | I9: TRUE | J9: TRUE | K9: TRUE | L9: TRUE | M9: TRUE | N9: TRUE | O9: TRUE | P9: TRUE | Q9: TRUE | R9: TRUE | S9: TRUE | T9: [2026-05-15] Revising/ Checked by Calo - testing archive feature | By: Calo
A10: Cabins | B10: Toilet Shower | C10: 32' | D10: DR.2.TS.32.6 | E10: TRUE | F10: TRUE | G10: TRUE | H10: TRUE | I10: TRUE | J10: TRUE | K10: TRUE | L10: TRUE | M10: TRUE | N10: TRUE | O10: TRUE | P10: TRUE | Q10: TRUE | R10: TRUE | S10: TRUE | T10: [2026-05-15] Revising/ Checked by Calo - testing archive feature | By: Calo
A11: Cabins | B11: Toilet | C11: 40' | D11: DR.2T.40.01 | E11: TRUE | F11: TRUE | G11: TRUE | H11: TRUE | I11: TRUE | J11: TRUE | K11: TRUE | L11: TRUE | M11: TRUE | N11: TRUE | O11: TRUE | P11: TRUE | Q11: TRUE | R11: FALSE | S11: TRUE | T11: [2026-04-07] Before sent we will paint work finished within a day Extrior painting work before we will finished | By: calo.lategan@allaith.com | Defects: Exterior paint
A12: Cabins | B12: Toilet | C12: 40' | D12: DR.2T.40.02 | E12: TRUE | F12: TRUE | G12: TRUE | H12: TRUE | I12: TRUE | J12: TRUE | K12: TRUE | L12: TRUE | M12: TRUE | N12: TRUE | O12: TRUE | P12: N/A | Q12: TRUE | R12: FALSE | S12: TRUE | T12: [2026-05-15] Before sent we will paint within a day Extrior painting | By: calo.lategan@allaith.com | Defects: Exterior paint
A13: Cabins | B13: Toilet | C13: 40' | D13: DR.2.40.1 | E13: TRUE | F13: TRUE | G13: TRUE | H13: N/A | I13: N/A | J13: N/A | K13: N/A | L13: FALSE | M13: TRUE | N13: N/A | O13: TRUE | P13: N/A | Q13: TRUE | R13: FALSE | S13: TRUE | T13: [2026-04-16] Before deliver we will paint / branding we will fix before deliver door inside plywood need to change door inside plywood need to change 18/04 | By: calo.lategan@allaith.com | Defects: Door, Exterior paint

Sheet Shower unit
A1: Category | B1: Description | C1: Size | D1: Plant No. | E1: Flooring | F1: Walls | G1: Ceiling | H1: Fittings | I1: Mirror | J1: Washbasin | K1: Lights | L1: Shower | M1: Shower Curtain | N1: AC | O1: Door | P1: Electrical | Q1: WC | R1: Intrior paint | S1: exterior paint | T1: STATUS
A2: Cabins | B2: Shower | C2: 20' | D2: SHC.F.20.1 | E2: FALSE | F2: FALSE | G2: FALSE | H2: FALSE | I2: FALSE | J2: FALSE | K2: FALSE | L2: FALSE | M2: FALSE | N2: FALSE | O2: FALSE | P2: FALSE | Q2: FALSE | R2: FALSE | S2: FALSE | T2: No inspection
A3: Cabins | B3: Shower | C3: 20' | D3: SHC.M.20..1 | E3: FALSE | F3: FALSE | G3: FALSE | H3: FALSE | I3: FALSE | J3: FALSE | K3: FALSE | L3: FALSE | M3: FALSE | N3: FALSE | O3: FALSE | P3: FALSE | Q3: FALSE | R3: FALSE | S3: FALSE | T3: Top
A4: Cabins | B4: Shower | C4: 20' | D4: SHC.20.3 | E4: FALSE | F4: FALSE | G4: FALSE | H4: FALSE | I4: FALSE | J4: FALSE | K4: FALSE | L4: FALSE | M4: FALSE | N4: FALSE | O4: FALSE | P4: FALSE | Q4: FALSE | R4: FALSE | S4: FALSE | T4: No inspection
A5: Cabins | B5: Shower | C5: 20' | D5: SHC.20.4 | E5: FALSE | F5: FALSE | G5: FALSE | H5: FALSE | I5: FALSE | J5: FALSE | K5: FALSE | L5: FALSE | M5: FALSE | N5: FALSE | O5: FALSE | P5: FALSE | Q5: FALSE | R5: FALSE | S5: FALSE | T5: Top
A6: Cabins | B6: Shower | C6: 20' | D6: SHC.20.5 | E6: FALSE | F6: FALSE | G6: FALSE | H6: FALSE | I6: FALSE | J6: FALSE | K6: FALSE | L6: FALSE | M6: FALSE | N6: FALSE | O6: FALSE | P6: FALSE | Q6: FALSE | R6: FALSE | S6: FALSE | T6: No inspection

Sheet Ablution
A1: Category | B1: Description | C1: Size | D1: Plant No. | E1: Flooring | F1: Walls | G1: Ceiling | H1: Window | I1: WC | J1: Urinal | K1: Interior paint | L1: exterior paint | M1: Mirror | N1: Washbasin | O1: Lights | P1: Exhaust Fan | Q1: Door | R1: Door keys | S1: Comments
A2: Ablution | B2: VIP | C2: 32' | D2: VIPABLM-F.32.1 | E2: TRUE | F2: TRUE | G2: TRUE | H2: N/A | I2: TRUE | J2: TRUE | K2: TRUE | L2: TRUE | M2: TRUE | N2: TRUE | O2: TRUE | P2: TRUE | Q2: TRUE | R2: TRUE | S2: [2026-05-20] Inspection Done By ANTO | By: ANTO
A3: Ablution | B3: VIP | C3: 32' | D3: VIPABLM-F.32.2 | E3: TRUE | F3: TRUE | G3: TRUE | H3: N/A | I3: TRUE | J3: TRUE | K3: TRUE | L3: TRUE | M3: TRUE | N3: TRUE | O3: TRUE | P3: TRUE | Q3: TRUE | R3: TRUE | S3: [2026-05-20] Inspection Done By ANTO | By: ANTO
A4: Ablution | B4: POD | C4: 10' | D4: D.ABL.10.2 | E4: FALSE | F4: FALSE | G4: FALSE | H4: FALSE | I4: FALSE | J4: FALSE | K4: FALSE | L4: FALSE | M4: FALSE | N4: FALSE | O4: FALSE | P4: FALSE | Q4: FALSE | R4: FALSE | S4: No inspection
A5: Ablution | B5: POD | C5: 10' | D5: D.ABL.10.5 | E5: FALSE | F5: FALSE | G5: FALSE | H5: FALSE | I5: FALSE | J5: FALSE | K5: FALSE | L5: FALSE | M5: FALSE | N5: FALSE | O5: FALSE | P5: FALSE | Q5: FALSE | R5: FALSE | S5: No inspection
A6: Ablution | B6: POD VIP | C6: 10' | D6: D.ABL.10.3 | E6: FALSE | F6: FALSE | G6: FALSE | H6: FALSE | I6: FALSE | J6: FALSE | K6: FALSE | L6: FALSE | M6: FALSE | N6: FALSE | O6: FALSE | P6: FALSE | Q6: FALSE | R6: FALSE | S6: No inspection
A7: Ablution | B7: 4 Door VIP | C7: 16' | D7: 4DR.ABL.16.1 | E7: FALSE | F7: FALSE | G7: FALSE | H7: FALSE | I7: FALSE | J7: FALSE | K7: FALSE | L7: FALSE | M7: FALSE | N7: FALSE | O7: FALSE | P7: FALSE | Q7: FALSE | R7: FALSE | S7: No inspection
A8: Ablution | B8: 4 Door VIP | C8: 16' | D8: 4DR.ABL.16.2 | E8: FALSE | F8: FALSE | G8: FALSE | H8: FALSE | I8: FALSE | J8: FALSE | K8: FALSE | L8: FALSE | M8: FALSE | N8: FALSE | O8: FALSE | P8: FALSE | Q8: FALSE | R8: FALSE | S8: No inspection
A9: Ablution | B9: 4 Door VIP | C9: 16' | D9: 4DR.ABL.16.3 | E9: FALSE | F9: FALSE | G9: FALSE | H9: FALSE | I9: FALSE | J9: FALSE | K9: FALSE | L9: FALSE | M9: FALSE | N9: FALSE | O9: FALSE | P9: FALSE | Q9: FALSE | R9: FALSE | S9: No inspection
A10: Ablution | B10: 4 Door | C10: 20' | D10: 4DR.ABL.20.1 | E10: FALSE | F10: FALSE | G10: FALSE | H10: FALSE | I10: FALSE | J10: FALSE | K10: FALSE | L10: FALSE | M10: FALSE | N10: FALSE | O10: FALSE | P10: FALSE | Q10: FALSE | R10: FALSE | S10: No inspection
A11: Ablution | B11: 4 Door | C11: 20' | D11: 4DR.ABL.20.2 | E11: FALSE | F11: FALSE | G11: FALSE | H11: FALSE | I11: FALSE | J11: FALSE | K11: FALSE | L11: FALSE | M11: FALSE | N11: FALSE | O11: FALSE | P11: FALSE | Q11: FALSE | R11: FALSE | S11: No inspection
A12: Ablution | B12: 4 Door | C12: 20' | D12: 4DR.ABL.20.3 | E12: FALSE | F12: FALSE | G12: FALSE | H12: FALSE | I12: FALSE | J12: FALSE | K12: FALSE | L12: FALSE | M12: FALSE | N12: FALSE | O12: FALSE | P12: FALSE | Q12: FALSE | R12: FALSE | S12: No inspection
A13: Ablution | B13: 1+1 door | C13: 10'' | D13: ABL.10.2 | E13: FALSE | F13: FALSE | G13: FALSE | H13: FALSE | I13: FALSE | J13: FALSE | K13: FALSE | L13: FALSE | M13: FALSE | N13: FALSE | O13: FALSE | P13: FALSE | Q13: FALSE | R13: FALSE | S13: No inspection
A14: Ablution | B14: Female | C14: 20' | D14: ABL.F.20.11 | E14: FALSE | F14: FALSE | G14: FALSE | H14: FALSE | I14: FALSE | J14: FALSE | K14: FALSE | L14: FALSE | M14: FALSE | N14: FALSE | O14: FALSE | P14: FALSE | Q14: FALSE | R14: FALSE | S14: No inspection
A15: Ablution | B15: Female | C15: 20' | D15: ABL.F.20.3 | E15: FALSE | F15: FALSE | G15: FALSE | H15: FALSE | I15: FALSE | J15: FALSE | K15: FALSE | L15: FALSE | M15: FALSE | N15: FALSE | O15: FALSE | P15: FALSE | Q15: FALSE | R15: FALSE | S15: No inspection
... A29: Ablution | B29: Mixed | C29: 20' | D29: ABL.M-F.20.12 | E29: FALSE | F29: FALSE | G29: FALSE | H29: FALSE | I29: FALSE | J29: FALSE | K29: FALSE | L29: FALSE | M29: FALSE | N29: FALSE | O29: FALSE | P29: FALSE | Q29: FALSE | R29: FALSE | S29: No inspection
A30: Ablution | B30: Mixed | C30: 20' | D30: ABL.M-F.20.13 | E30: FALSE | F30: FALSE | G30: FALSE | H30: x | I30: FALSE | J30: FALSE | K30: FALSE | L30: FALSE | M30: FALSE | N30: FALSE | O30: FALSE | P30: FALSE | Q30: FALSE | R30: FALSE | S30: Scrap
A31: Ablution | B31: Mixed | C31: 20' | D31: ABL.M-F.20.18 | E31: FALSE | F31: FALSE | G31: FALSE | H31: FALSE | I31: FALSE | J31: FALSE | K31: FALSE | L31: FALSE | M31: FALSE | N31: FALSE | O31: FALSE | P31: FALSE | Q31: FALSE | R31: FALSE | S31: No inspection
A32: Ablution | B32: Mixed | C32: 20' | D32: ABL.M-F.20.2 | E32: FALSE | F32: FALSE | G32: FALSE | H32: FALSE | I32: FALSE | J32: FALSE | K32: FALSE | L32: FALSE | M32: FALSE | N32: FALSE | O32: FALSE | P32: FALSE | Q32: FALSE | R32: FALSE | S32: No inspection
A33: Ablution | B33: Mixed | C33: 20' | D33: ABL.M-F.20.3 | E33: FALSE | F33: FALSE | G33: FALSE | H33: FALSE | I33: FALSE | J33: FALSE | K33: FALSE | L33: FALSE | M33: FALSE | N33: FALSE | O33: FALSE | P33: FALSE | Q33: FALSE | R33: FALSE | S33: No inspection
A34: Ablution | B34: Mixed | C34: 20' | D34: ABL.M-F.20.5 | E34: FALSE | F34: FALSE | G34: FALSE | H34: FALSE | I34: FALSE | J34: FALSE | K34: FALSE | L34: FALSE | M34: FALSE | N34: FALSE | O34: FALSE | P34: FALSE | Q34: FALSE | R34: FALSE | S34: No inspection
A35: Ablution | B35: Mixed | C35: 20' | D35: ABL.M-F.20.4 | E35: FALSE | F35: FALSE | G35: FALSE | H35: FALSE | I35: FALSE | J35: FALSE | K35: FALSE | L35: FALSE | M35: FALSE | N35: FALSE | O35: FALSE | P35: FALSE | Q35: FALSE | R35: FALSE | S35: No inspection
A36: Ablution | B36: Mixed | C36: 20' | D36: ABL.M-F.20.6 | E36: FALSE | F36: FALSE | G36: FALSE | H36: FALSE | I36: FALSE | J36: FALSE | K36: FALSE | L36: FALSE | M36: FALSE | N36: FALSE | O36: FALSE | P36: FALSE | Q36: FALSE | R36: FALSE | S36: No inspection
A37: Ablution | B37: Mixed | C37: 20' | D37: ABL.M-F.20.7 | E37: FALSE | F37: FALSE | G37: FALSE | H37: FALSE | I37: FALSE | J37: FALSE | K37: FALSE | L37: FALSE | M37: FALSE | N37: FALSE | O37: FALSE | P37: FALSE | Q37: FALSE | R37: FALSE | S37: No inspection
A38: Ablution | B38: Mixed | C38: 20' | D38: ABL.M-F.20.8 | E38: FALSE | F38: FALSE | G38: FALSE | H38: FALSE | I38: FALSE | J38: FALSE | K38: FALSE | L38: FALSE | M38: FALSE | N38: FALSE | O38: FALSE | P38: FALSE | Q38: FALSE | R38: FALSE | S38: No inspection
A39: Ablution | B39: Mixed VIP | C39: 20' | D39: ABL.M-F.20.16 | E39: TRUE | F39: TRUE | G39: TRUE | H39: N/A | I39: TRUE | J39: TRUE | K39: TRUE | L39: TRUE | M39: TRUE | N39: TRUE | O39: TRUE | P39: TRUE | Q39: TRUE | R39: TRUE | S39: [2026-04-18] Inspection done by Anto | By: Anto
A40: Ablution | B40: Mixed VIP | C40: 20' | D40: ABL.M-F.20.14 | E40: FALSE | F40: FALSE | G40: FALSE | H40: FALSE | I40: FALSE | J40: FALSE | K40: FALSE | L40: FALSE | M40: FALSE | N40: FALSE | O40: FALSE | P40: FALSE | Q40: FALSE | R40: FALSE | S40: No inspection
A41: Ablution | B41: Female | C41: 40' | D41: ABL.F.40.01 | E41: TRUE | F41: TRUE | G41: TRUE | H41: N/A | I41: TRUE | J41: N/A | K41: TRUE | L41: TRUE | M41: TRUE | N41: TRUE | O41: TRUE | P41: TRUE | Q41: TRUE | R41: TRUE | S41: [2026-05-15] Inspection done by ANTO | By: ANTO
A42: Ablution | B42: Female | C42: 40' | D42: ABL.F.40.02 | E42: TRUE | F42: TRUE | G42: TRUE | H42: N/A | I42: TRUE | J42: N/A | K42: TRUE | L42: TRUE | M42: TRUE | N42: TRUE | O42: TRUE | P42: TRUE | Q42: TRUE | R42: TRUE | S42: [2026-05-15] Inspection done by ANTO | By: ANTO
A43: Ablution | B43: Female | C43: 40' | D43: ABL.F.40.03 | E43: TRUE | F43: TRUE | G43: TRUE | H43: N/A | I43: TRUE | J43: N/A | K43: TRUE | L43: TRUE | M43: TRUE | N43: TRUE | O43: TRUE | P43: TRUE | Q43: TRUE | R43: TRUE | S43: [2026-05-15] Inspection done by ANTO | By: ANTO
A44: Ablution | B44: Female | C44: 40' | D44: ABL.F.40.04 | E44: FALSE | F44: FALSE | G44: FALSE | H44: FALSE | I44: FALSE | J44: FALSE | K44: FALSE | L44: FALSE | M44: FALSE | N44: FALSE | O44: FALSE | P44: FALSE | Q44: FALSE | R44: FALSE | S44: No inspection
A45: Ablution | B45: Female | C45: 40' | D45: ABL.F.40.05 | E45: FALSE | F45: FALSE | G45: FALSE | H45: FALSE | I45: FALSE | J45: FALSE | K45: FALSE | L45: FALSE | M45: FALSE | N45: FALSE | O45: FALSE | P45: FALSE | Q45: FALSE | R45: FALSE | S45: No inspection
A46: Ablution | B46: Female | C46: 40' | D46: ABL.F.40.06 | E46: FALSE | F46: FALSE | G46: FALSE | H46: FALSE | I46: FALSE | J46: FALSE | K46: FALSE | L46: FALSE | M46: FALSE | N46: FALSE | O46: FALSE | P46: FALSE | Q46: FALSE | R46: FALSE | S46: No inspection
A47: Ablution | B47: Female | C47: 40' | D47: ABL.F.40.07 | E47: FALSE | F47: FALSE | G47: FALSE | H47: FALSE | I47: FALSE | J47: FALSE | K47: FALSE | L47: FALSE | M47: FALSE | N47: FALSE | O47: FALSE | P47: FALSE | Q47: FALSE | R47: FALSE | S47: No inspection
A48: Ablution | B48: Male | C48: 40' | D48: ABL.M.40.01 | E48: TRUE | F48: TRUE | G48: TRUE | H48: N/A | I48: TRUE | J48: TRUE | K48: TRUE | L48: TRUE | M48: TRUE | N48: TRUE | O48: TRUE | P48: TRUE | Q48: TRUE | R48: TRUE | S48: [2026-05-16] Inspection done by ANTO | By: ANTO
A49: Ablution | B49: Male | C49: 40' | D49: ABL.M.40.02 | E49: TRUE | F49: TRUE | G49: TRUE | H49: N/A | I49: TRUE | J49: TRUE | K49: TRUE | L49: TRUE | M49: TRUE | N49: TRUE | O49: TRUE | P49: TRUE | Q49: TRUE | R49: TRUE | S49: [2026-05-16] Inspection done by ANTO | By: ANTO
A50: Ablution | B50: Mixed | C50: 40' | D50: ABL.M.40.03 | E50: FALSE | F50: FALSE | G50: FALSE | H50: FALSE | I50: FALSE | J50: FALSE | K50: FALSE | L50: FALSE | M50: FALSE | N50: FALSE | O50: FALSE | P50: FALSE | Q50: FALSE | R50: FALSE | S50: No inspection
A51: Ablution | B51: Male | C51: 40' | D51: ABL.M.40.04 | E51: FALSE | F51: FALSE | G51: FALSE | H51: FALSE | I51: FALSE | J51: FALSE | K51: FALSE | L51: FALSE | M51: FALSE | N51: FALSE | O51: FALSE | P51: FALSE | Q51: FALSE | R51: FALSE | S51: No inspection
A52: Ablution | B52: Male | C52: 40' | D52: ABL.M.40.05 | E52: FALSE | F52: FALSE | G52: FALSE | H52: FALSE | I52: FALSE | J52: FALSE | K52: FALSE | L52: FALSE | M52: FALSE | N52: FALSE | O52: FALSE | P52: FALSE | Q52: FALSE | R52: FALSE | S52: No inspection
A53: Ablution | B53: Male | C53: 40' | D53: ABL.M.40.06 | E53: FALSE | F53: FALSE | G53: FALSE | H53: FALSE | I53: FALSE | J53: FALSE | K53: FALSE | L53: FALSE | M53: FALSE | N53: FALSE | O53: FALSE | P53: FALSE | Q53: FALSE | R53: FALSE | S53: No inspection
A54: Ablution | B54: Male | C54: 40' | D54: ABL.M-F.40.01 | E54: FALSE | F54: FALSE | G54: FALSE | H54: FALSE | I54: FALSE | J54: FALSE | K54: FALSE | L54: FALSE | M54: FALSE | N54: FALSE | O54: FALSE | P54: FALSE | Q54: FALSE | R54: FALSE | S54: No inspection
A55: Ablution | B55: Mixed | C55: 40' | D55: ABL.M-F.40.10 | E55: TRUE | F55: TRUE | G55: TRUE | H55: N/A | I55: TRUE | J55: TRUE | K55: TRUE | L55: TRUE | M55: TRUE | N55: TRUE | O55: TRUE | P55: TRUE | Q55: TRUE | R55: TRUE | S55: [2026-05-16] Inspection done by ANTO | By: ANTO
A56: Ablution | B56: Mixed | C56: 40' | D56: ABL.M-F.40.3 | E56: FALSE | F56: FALSE | G56: FALSE | H56: FALSE | I56: FALSE | J56: FALSE | K56: FALSE | L56: FALSE | M56: FALSE | N56: FALSE | O56: FALSE | P56: FALSE | Q56: FALSE | R56: FALSE | S56: No inspection
A57: Ablution | B57: Mixed | C57: 40' | D57: ABL.M-F.40.6 | E57: TRUE | F57: TRUE | G57: TRUE | H57: N/A | I57: TRUE | J57: TRUE | K57: TRUE | L57: TRUE | M57: TRUE | N57: TRUE | O57: TRUE | P57: TRUE | Q57: TRUE | R57: TRUE | S57: [2026-05-15] Inspection done by ANTO | By: ANTO
A58: Ablution | B58: Mixed | C58: 40' | D58: ABL.M-F.40.9 | E58: TRUE | F58: TRUE | G58: TRUE | H58: N/A | I58: TRUE | J58: TRUE | K58: TRUE | L58: TRUE | M58: TRUE | N58: TRUE | O58: TRUE | P58: TRUE | Q58: TRUE | R58: TRUE | S58: [2026-05-16] Inpection done by ANTO | By: ANTO
A59: Ablution | B59: Mixed VIP | C59: 40' | D59: ABL.M-F.40.2 | E59: FALSE | F59: FALSE | G59: FALSE | H59: FALSE | I59: FALSE | J59: FALSE | K59: FALSE | L59: FALSE | M59: FALSE | N59: FALSE | O59: FALSE | P59: FALSE | Q59: FALSE | R59: FALSE | S59: No inspection
A60: Ablution | B60: Mixed VIP | C60: 40' | D60: ABL.M-F.40.4 | E60: FALSE | F60: FALSE | G60: FALSE | H60: FALSE | I60: FALSE | J60: FALSE | K60: FALSE | L60: FALSE | M60: FALSE | N60: FALSE | O60: FALSE | P60: FALSE | Q60: FALSE | R60: FALSE | S60: No inspection
A61: Ablution | B61: Mixed VIP | C61: 40' | D61: ABL.M-F.40.5 | E61: TRUE | F61: TRUE | G61: TRUE | H61: N/A | I61: TRUE | J61: TRUE | K61: TRUE | L61: TRUE | M61: TRUE | N61: TRUE | O61: TRUE | P61: TRUE | Q61: TRUE | R61: TRUE | S61: [2026-05-15] Inspection done by ANTO | By: ANTO
A62: Ablution | B62: Mixed VIP | C62: 40' | D62: ABL.M-F.40.8 | E62: FALSE | F62: FALSE | G62: FALSE | H62: FALSE | I62: FALSE | J62: FALSE | K62: FALSE | L62: FALSE | M62: FALSE | N62: FALSE | O62: FALSE | P62: FALSE | Q62: FALSE | R62: FALSE | S62: No inspection
A63: Toilet trailer | B63: Mixed 4 door | D63: ABL.T.4D.01 | E63: TRUE | F63: TRUE | G63: TRUE | H63: TRUE | I63: TRUE | J63: N/A | K63: TRUE | L63: TRUE | M63: TRUE | N63: TRUE | O63: TRUE | P63: N/A | Q63: TRUE | R63: TRUE | S63: [2026-05-20] Inspection Done By ANTO | By: ANTO
A64: Toilet trailer | B64: Mixed 4 door | D64: ABL.T.4D.02 | E64: TRUE | F64: TRUE | G64: TRUE | H64: TRUE | I64: TRUE | J64: N/A | K64: TRUE | L64: TRUE | M64: TRUE | N64: TRUE | O64: TRUE | P64: TRUE | Q64: TRUE | R64: TRUE | S64: [2026-05-20] Inspection Done By ANTO | By: ANTO
A65: Toilet trailer | B65: Mixed 4 door | D65: ABL.T.4D.03 | E65: TRUE | F65: TRUE | G65: TRUE | H65: TRUE | I65: TRUE | J65: N/A | K65: TRUE | L65: TRUE | M65: TRUE | N65: TRUE | O65: TRUE | P65: TRUE | Q65: TRUE | R65: TRUE | S65: [2026-05-20] Inspection Done By ANTO | By: ANTO
A66: Toilet trailer | B66: Mixed 4 door | D66: ABL.T.4D.04 | E66: TRUE | F66: TRUE | G66: TRUE | H66: TRUE | I66: TRUE | J66: N/A | K66: TRUE | L66: TRUE | M66: TRUE | N66: TRUE | O66: TRUE | P66: N/A | Q66: TRUE | R66: TRUE | S66: [2026-05-20] Inspection Done By ANTO | By: ANTO

Sheet _QCMirror
A1: SourceFileId | B1: SourceName | C1: MirrorFileId | D1: MirroredAt
A2: 1pmW6kVOF1gXwCMWSnFvjVsXc1wwtR7IJ | B2: DR.2T.40.01-260407 POST PDI.pdf | C2: 17yTBpApEObof039H1tDZKcMS9-WfAPgr | D2: 46120.576
A3: 1Ut_AKnRQHNzAg6oAEIhA7eEUm5T8msdZ | B3: DR.2.T.32.9-260407 POST PDI.pdf | C3: 1Edbln0dwIXOBPHLI-raySZh7SyjV3p8i | D3: 46120.576
A4: 10wgtWMM71YsZ2p-FdXzgCYDL6bVftOTJ | B4: ABL.F.40.01-260404 POST PDI.pdf | C4: 1Fzj5QWQdmc2UFetNfEC4ZyrHJOvAmDvT | D4: 46120.576
A5: 1lF8OUdmtYZ3Y5XomuCeWN0wcg_OGWeEg | B5: ABL.F.40.02-260404 POST PDI.pdf | C5: 1KMWMvXfPTYBB0qtkgX1qMu1SUA_h-8x1 | D5: 46120.576
A6: 12uezddCyChgWSN_4n9R54WbompodJrk6 | B6: DR.2.T.32.8-260404 POST PDI.pdf | C6: 1U7rrsmLh1EFqcUmOWCNDJkc_r2grL5tr | D6: 46120.576
A7: 1gf3oXR9214Qe4ZYHhNdtvdvmRZk349iw | B7: DR.2.T.32.3-260404 POST PDI.pdf | C7: 1vR6LpsFoanefFjBP6QgmdpMRdIjiUEDk | D7: 46120.576
A8: 1OrXNyANh70KCiuF8VR9BM4qJeuNIjM-p | B8: DR.2.TS.32.5-260404 POST PDI.pdf | C8: 18SMskUTkk-_RP2RL0yUU97TgudhwOXa6 | D8: 46120.576
A9: 12LP-HWNGxpxyeJVa5RbyMZMVYDnfQpDs | B9: DR.2.TS.32.6-260404 POST PDI.pdf | C9: 1BChRoLxwLSQhwEP3VAJSMjoofNZ0G-3q | D9: 46120.576
A10: 1sGUUG2GoG8McUIRzfUnRlkYw4wo9uZid | B10: PB-260403 POST PDI.pdf | C10: 1gz3TOp5jB3h10IQm6S6AfxEUNRwhiDYh | D10: 46120.576
A11: 1DsuGxHP4eDAaNRiv-ovtOI3EAp1PXcT4 | B11: STC.20.6-260331 POST PDI.pdf | C11: 1eLmqgojPmO8SPULZU9EVcby6iupd65F6 | D11: 46120.576
A12: 1dkP3ucjSBVqqxmnTp8dH_-i0C_yNjcLr | B12: STC.40.8-260331 POST PDI.pdf | C12: 1L0zaXAqQpRmk_T08IqhsfADzi-762ldc | D12: 46120.576
A13: 15q3LWUL0_xWx_pqsqRQ2HZz14WLI10rT | B13: STC.20.5-260331 POST PDI.pdf | C13: 1X8AMBe_IarLAvAGLydLKiFCN6OYbcUlD | D13: 46120.576
... A23: 1lKl9AVG9aIRVOUxLA3pz_bUQqJfLvr1o | B23: PL.59-260330 POST PDI.pdf | C23: 1KS8fgnpFVIus_JyIG-Cn7L_EiR-NYF0q | D23: 46120.577

Sheet Messhall
A1: Category | B1: Description | C1: Size | D1: Plant No. | E1: Flooring | F1: Walls | G1: Ceiling | H1: Fittings | I1: AC | J1: Window Tint | K1: Roof | L1: Lights | M1: Door | N1: Comments
A2: Cabins | B2: Mess | C2: 40' | D2: MH.40.1-E | E2: FALSE | F2: FALSE | G2: FALSE | H2: FALSE | I2: FALSE | J2: FALSE | K2: FALSE | L2: FALSE | M2: FALSE | N2: No inspection
A3: Cabins | B3: Mess | C3: 40' | D3: MH.40.4 | E3: FALSE | F3: FALSE | G3: FALSE | H3: FALSE | I3: FALSE | J3: FALSE | K3: FALSE | L3: FALSE | M3: FALSE | N3: No inspection
A4: Cabins | B4: Mess | C4: 40' | D4: MH.40.5 | E4: FALSE | F4: FALSE | G4: FALSE | H4: FALSE | I4: FALSE | J4: FALSE | K4: FALSE | L4: FALSE | M4: FALSE | N4: No inspection
A5: Cabins | B5: Mess | C5: 40' | D5: MH.40.10-E | E5: FALSE | F5: FALSE | G5: FALSE | H5: FALSE | I5: FALSE | J5: FALSE | K5: FALSE | L5: FALSE | M5: FALSE | N5: No inspection
A6: Cabins | B6: Mess | C6: 40' | D6: MH.40.11-E | E6: FALSE | F6: FALSE | G6: FALSE | H6: FALSE | I6: FALSE | J6: FALSE | K6: FALSE | L6: FALSE | M6: FALSE | N6: No inspection
A7: Cabins | B7: Mess | C7: 40' | D7: MH.40.12-E | E7: FALSE | F7: FALSE | G7: FALSE | H7: FALSE | I7: FALSE | J7: FALSE | K7: FALSE | L7: FALSE | M7: FALSE | N7: No inspection
A8: Cabins | B8: Mess | C8: 40' | D8: MH.40.16-E | E8: FALSE | F8: FALSE | G8: FALSE | H8: FALSE | I8: FALSE | J8: FALSE | K8: FALSE | L8: FALSE | M8: FALSE | N8: No inspection
A9: Cabins | B9: Mess | C9: 40' | D9: MH.40.22-E | E9: FALSE | F9: FALSE | G9: FALSE | H9: FALSE | I9: FALSE | J9: FALSE | K9: FALSE | L9: FALSE | M9: FALSE | N9: No inspection
A10: Cabins | B10: Mess | C10: 40' | D10: MH.40.27-E | E10: FALSE | F10: FALSE | G10: FALSE | H10: FALSE | I10: FALSE | J10: FALSE | K10: FALSE | L10: FALSE | M10: FALSE | N10: No inspection
A11: Cabins | B11: Mess | C11: 40' | D11: MH.40.28-E | E11: FALSE | F11: FALSE | G11: FALSE | H11: FALSE | I11: FALSE | J11: FALSE | K11: FALSE | L11: FALSE | M11: FALSE | N11: No inspection

Sheet Cabins
A1: Category | B1: Description | C1: Size | D1: Plant No. | E1: Flooring | F1: Walls | G1: Ceiling | H1: Interior paint | I1: Exterior paint | J1: AC | K1: Window | L1: Blinds | M1: Lights | N1: Door | O1: Door keys | P1: Comments
A2: Cabins | B2: Ticket | C2: 8' | D2: TB.10.10 | E2: FALSE | F2: FALSE | G2: FALSE | H2: FALSE | I2: FALSE | J2: FALSE | K2: FALSE | L2: FALSE | M2: FALSE | N2: FALSE | O2: FALSE | P2: No inspection
A3: Cabins | B3: Ticket | C3: 8' | D3: TB.10.11 | E3: FALSE | F3: FALSE | G3: FALSE | H3: FALSE | I3: FALSE | J3: FALSE | K3: FALSE | L3: FALSE | M3: FALSE | N3: FALSE | O3: FALSE | P3: No inspection
A4: Cabins | B4: Ticket | C4: 8' | D4: TB.10.12 | E4: FALSE | F4: FALSE | G4: FALSE | H4: FALSE | I4: FALSE | J4: FALSE | K4: FALSE | L4: FALSE | M4: FALSE | N4: FALSE | O4: FALSE | P4: No inspection
A5: Cabins | B5: Ticket | C5: 8' | D5: TB.10.13 | E5: FALSE | F5: FALSE | G5: FALSE | H5: FALSE | I5: FALSE | J5: FALSE | K5: FALSE | L5: FALSE | M5: FALSE | N5: FALSE | O5: FALSE | P5: No inspection
A6: Cabins | B6: Ticket | C6: 8' | D6: TB.10.4 | E6: FALSE | F6: FALSE | G6: FALSE | H6: FALSE | I6: FALSE | J6: FALSE | K6: FALSE | L6: FALSE | M6: FALSE | N6: FALSE | O6: FALSE | P6: No inspection
A7: Cabins | B7: Ticket | C7: 8' | D7: TB.10.5 | E7: FALSE | F7: FALSE | G7: FALSE | H7: FALSE | I7: FALSE | J7: FALSE | K7: FALSE | L7: FALSE | M7: FALSE | N7: FALSE | O7: FALSE | P7: No inspection
A8: Cabins | B8: Ticket | C8: 8' | D8: TB.10.6 | E8: FALSE | F8: FALSE | G8: FALSE | H8: FALSE | I8: FALSE | J8: FALSE | K8: FALSE | L8: FALSE | M8: FALSE | N8: FALSE | O8: FALSE | P8: No inspection
A9: Cabins | B9: Ticket | C9: 8' | D9: TB.10.7 | E9: FALSE | F9: FALSE | G9: FALSE | H9: FALSE | I9: FALSE | J9: FALSE | K9: FALSE | L9: FALSE | M9: FALSE | N9: FALSE | O9: FALSE | P9: No inspection
A10: Cabins | B10: Ticket | C10: 8' | D10: TB.10.8 | E10: FALSE | F10: FALSE | G10: FALSE | H10: FALSE | I10: FALSE | J10: FALSE | K10: FALSE | L10: FALSE | M10: FALSE | N10: FALSE | O10: FALSE | P10: No inspection
A11: Cabins | B11: Ticket | C11: 8' | D11: TB.10.9 | E11: FALSE | F11: FALSE | G11: FALSE | H11: FALSE | I11: FALSE | J11: FALSE | K11: FALSE | L11: FALSE | M11: FALSE | N11: FALSE | O11: FALSE | P11: No inspection
A12: Cabins | B12: Ticket | C12: 10' | D12: TB.10.1 | E12: FALSE | F12: FALSE | G12: FALSE | H12: FALSE | I12: FALSE | J12: FALSE | K12: FALSE | L12: FALSE | M12: FALSE | N12: FALSE | O12: FALSE | P12: No inspection
A13: Cabins | B13: Ticket | C13: 10' | D13: TB.10.2 | E13: FALSE | F13: FALSE | G13: FALSE | H13: FALSE | I13: FALSE | J13: FALSE | K13: FALSE | L13: FALSE | M13: FALSE | N13: FALSE | O13: FALSE | P13: No inspection
... A17: Cabins | B17: OPO | C17: 20' | D17: STC.20.4 | E17: FALSE | F17: FALSE | G17: FALSE | H17: FALSE | I17: FALSE | J17: FALSE | K17: FALSE | L17: FALSE | M17: FALSE | N17: FALSE | O17: FALSE | P17: No inspection
A18: Cabins | B18: Storage | C18: 20' | D18: STC.20.5 | E18: TRUE | F18: TRUE | G18: TRUE | H18: TRUE | I18: TRUE | J18: N/A | K18: N/A | L18: FALSE | M18: N/A | N18: TRUE | O18: FALSE | P18: [2026-03-31] Inspection done by khaild | By: khaild
A19: Cabins | B19: Storage | C19: 20' | D19: STC.20.6 | E19: TRUE | F19: TRUE | G19: TRUE | H19: TRUE | I19: TRUE | J19: N/A | K19: N/A | L19: FALSE | M19: N/A | N19: TRUE | O19: FALSE | P19: [2026-03-31] Inspection done by khalid | By: khalid
A20: Cabins | B20: OPO | C20: 20' | D20: OPO.20.16 | E20: FALSE | F20: FALSE | G20: FALSE | H20: FALSE | I20: FALSE | J20: FALSE | K20: FALSE | L20: FALSE | M20: FALSE | N20: FALSE | O20: FALSE | P20: No inspection
A21: Cabins | B21: OPO | C21: 20' | D21: OPO.20.01 | E21: FALSE | F21: FALSE | G21: FALSE | H21: FALSE | I21: FALSE | J21: FALSE | K21: FALSE | L21: FALSE | M21: FALSE | N21: FALSE | O21: FALSE | P21: No inspection
A22: Cabins | B22: OPO | C22: 20' | D22: OPO.20.10 | E22: FALSE | F22: FALSE | G22: FALSE | H22: FALSE | I22: FALSE | J22: FALSE | K22: FALSE | L22: FALSE | M22: FALSE | N22: FALSE | O22: FALSE | P22: No inspection
A23: Cabins | B23: OPO | C23: 20' | D23: OPO.20.11 | E23: FALSE | F23: FALSE | G23: FALSE | H23: FALSE | I23: FALSE | J23: FALSE | K23: FALSE | L23: FALSE | M23: FALSE | N23: FALSE | O23: FALSE | P23: No inspection
A24: Cabins | B24: OPO | C24: 20' | D24: OPO.20.12 | E24: FALSE | F24: FALSE | G24: FALSE | H24: FALSE | I24: FALSE | J24: FALSE | K24: FALSE | L24: FALSE | M24: FALSE | N24: FALSE | O24: FALSE | P24: No inspection
A25: Cabins | B25: OPO | C25: 20' | D25: OPO.20.17 | E25: FALSE | F25: FALSE | G25: FALSE | H25: FALSE | I25: FALSE | J25: FALSE | K25: FALSE | L25: FALSE | M25: FALSE | N25: FALSE | O25: FALSE | P25: No inspection
A26: Cabins | B26: OPO | C26: 20' | D26: OPO.20.13 | E26: FALSE | F26: FALSE | G26: FALSE | H26: FALSE | I26: FALSE | J26: FALSE | K26: FALSE | L26: FALSE | M26: FALSE | N26: FALSE | O26: FALSE | P26: No inspection
A27: Cabins | B27: OPO | C27: 20' | D27: OPO.20.18 | E27: FALSE | F27: FALSE | G27: FALSE | H27: FALSE | I27: FALSE | J27: FALSE | K27: FALSE | L27: FALSE | M27: FALSE | N27: FALSE | O27: FALSE | P27: No inspection
A28: Cabins | B28: OPO | C28: 20' | D28: OPO.20.02 | E28: FALSE | F28: FALSE | G28: FALSE | H28: FALSE | I28: FALSE | J28: FALSE | K28: FALSE | L28: FALSE | M28: FALSE | N28: FALSE | O28: FALSE | P28: No inspection
A29: Cabins | B29: OPO | C29: 20' | D29: OPO.20.23 | E29: FALSE | F29: FALSE | G29: FALSE | H29: FALSE | I29: FALSE | J29: FALSE | K29: FALSE | L29: FALSE | M29: FALSE | N29: FALSE | O29: FALSE | P29: No inspection
A30: Cabins | B30: OPO | C30: 20' | D30: OPO.20.24 | E30: FALSE | F30: FALSE | G30: FALSE | H30: FALSE | I30: FALSE | J30: FALSE | K30: FALSE | L30: FALSE | M30: FALSE | N30: FALSE | O30: FALSE | P30: No inspection
A31: Cabins | B31: OPO | C31: 20' | D31: OPO.20.25 | E31: TRUE | F31: TRUE | G31: TRUE | H31: FALSE | I31: FALSE | J31: TRUE | K31: TRUE | L31: TRUE | M31: TRUE | N31: TRUE | O31: TRUE | P31: [2026-06-05] By Calo | By: Calo | Defects: Interior paint, Exterior paint
... A41: Cabins | B41: OPO | C41: 20' | D41: OPO.20.06 | E41: FALSE | F41: FALSE | G41: FALSE | H41: FALSE | I41: FALSE | J41: FALSE | K41: FALSE | L41: FALSE | M41: FALSE | N41: FALSE | O41: FALSE | P41: No inspection
A42: Cabins | B42: OPO | C42: 20' | D42: OPO.20.07 | E42: TRUE | F42: TRUE | G42: TRUE | H42: FALSE | I42: FALSE | J42: FALSE | K42: TRUE | L42: N/A | M42: FALSE | N42: TRUE | O42: TRUE | P42: [2026-06-05] To clean, paint and do maintenance... 2 days work to 3 | By: calo.lategan@allaith.com | Defects: Interior paint, Exterior paint, AC, Lights
A43: Cabins | B43: OPO | C43: 24' | D43: OPO.24.1 | E43: FALSE | F43: FALSE | G43: FALSE | H43: FALSE | I43: FALSE | J43: FALSE | K43: FALSE | L43: FALSE | M43: FALSE | N43: FALSE | O43: FALSE | P43: No inspection
A44: Cabins | B44: OPO | C44: 30' | D44: OPO.30.1 | E44: FALSE | F44: FALSE | G44: FALSE | H44: FALSE | I44: FALSE | J44: FALSE | K44: FALSE | L44: FALSE | M44: FALSE | N44: FALSE | O44: FALSE | P44: No inspection
A45: Cabins | B45: OPO | C45: 30' | D45: OPO.30.3 | E45: FALSE | F45: FALSE | G45: FALSE | H45: FALSE | I45: FALSE | J45: FALSE | K45: FALSE | L45: FALSE | M45: FALSE | N45: FALSE | O45: FALSE | P45: No inspection
A46: Cabins | B46: OPO | C46: 30' | D46: OPO.30.4 | E46: FALSE | F46: FALSE | G46: FALSE | H46: FALSE | I46: FALSE | J46: FALSE | K46: FALSE | L46: FALSE | M46: FALSE | N46: FALSE | O46: FALSE | P46: No inspection
A47: Cabins | B47: OPO | C47: 30' | D47: OPO.30.5 | E47: FALSE | F47: FALSE | G47: FALSE | H47: FALSE | I47: FALSE | J47: FALSE | K47: FALSE | L47: FALSE | M47: FALSE | N47: FALSE | O47: FALSE | P47: No inspection
A48: Cabins | B48: OPO | C48: 30' | D48: OPO.30.6 | E48: FALSE | F48: FALSE | G48: FALSE | H48: FALSE | I48: FALSE | J48: FALSE | K48: FALSE | L48: FALSE | M48: FALSE | N48: FALSE | O48: FALSE | P48: No inspection
A49: Cabins | B49: OPO | C49: 32' | D49: OPO.32.1 | E49: FALSE | F49: FALSE | G49: FALSE | H49: FALSE | I49: FALSE | J49: FALSE | K49: FALSE | L49: FALSE | M49: FALSE | N49: FALSE | O49: FALSE | P49: No inspection
A50: Cabins | B50: OPO sound proof | C50: 40' | D50: OPO.40.4 | E50: TRUE | F50: TRUE | G50: TRUE | H50: TRUE | I50: TRUE | J50: TRUE | K50: N/A | L50: N/A | M50: TRUE | N50: TRUE | O50: TRUE | P50: [2026-05-20] Inspection Done By ANTO | By: ANTO
A51: Cabins | B51: OPO sound proof | C51: 40' | D51: OPO.40.7 | E51: FALSE | F51: FALSE | G51: FALSE | H51: FALSE | I51: FALSE | J51: FALSE | K51: FALSE | L51: FALSE | M51: FALSE | N51: FALSE | O51: FALSE | P51: No inspection
A52: Cabins | B52: OPO | C52: 40' | D52: OPO.40.1 | E52: FALSE | F52: FALSE | G52: FALSE | H52: FALSE | I52: FALSE | J52: FALSE | K52: FALSE | L52: FALSE | M52: FALSE | N52: FALSE | O52: FALSE | P52: No inspection
A53: Cabins | B53: OPO | C53: 40' | D53: OPO.40.2 | E53: TRUE | F53: TRUE | G53: TRUE | H53: TRUE | I53: TRUE | J53: TRUE | K53: TRUE | L53: N/A | M53: TRUE | N53: TRUE | O53: TRUE | P53: [2026-05-18] Inpection Done By ANTO | By: ANTO
A54: Cabins | B54: OPO | C54: 40' | D54: OPO.40.3 | E54: TRUE | F54: TRUE | G54: TRUE | H54: TRUE | I54: TRUE | J54: TRUE | K54: TRUE | L54: N/A | M54: TRUE | N54: TRUE | O54: TRUE | P54: [2026-05-18] Inpection Done By ANTO | By: ANTO
A55: Cabins | B55: OPO | C55: 40' | D55: OPO.40.5 | E55: TRUE | F55: TRUE | G55: TRUE | H55: TRUE | I55: TRUE | J55: TRUE | K55: TRUE | L55: N/A | M55: TRUE | N55: TRUE | O55: TRUE | P55: [2026-05-18] Inpection Done By ANTO | By: ANTO
A56: Cabins | B56: OPO | C56: 40' | D56: OPO.40.6 | E56: TRUE | F56: TRUE | G56: TRUE | H56: TRUE | I56: TRUE | J56: TRUE | K56: TRUE | L56: N/A | M56: TRUE | N56: TRUE | O56: TRUE | P56: [2026-05-18] Inpection Done By ANTO | By: ANTO
A57: Cabins | B57: Storage | C57: 40' | D57: STC.40.1 | E57: TRUE | F57: TRUE | G57: TRUE | H57: TRUE | I57: TRUE | J57: N/A | K57: N/A | L57: FALSE | M57: N/A | N57: TRUE | O57: N/A | P57: [2026-04-18] Inpection done by yadav | By: yadav
A58: Cabins | B58: Storage | C58: 40' | D58: STC.40.2 | E58: FALSE | F58: FALSE | G58: FALSE | H58: FALSE | I58: FALSE | J58: FALSE | K58: FALSE | L58: FALSE | M58: FALSE | N58: FALSE | O58: FALSE | P58: No inspection
A59: Cabins | B59: Storage | C59: 40' | D59: STC.40.3 | E59: FALSE | F59: FALSE | G59: FALSE | H59: FALSE | I59: FALSE | J59: FALSE | K59: FALSE | L59: FALSE | M59: FALSE | N59: FALSE | O59: FALSE | P59: No inspection
A60: Cabins | B60: Storage | C60: 40' | D60: STC.40.4 | E60: FALSE | F60: FALSE | G60: FALSE | H60: FALSE | I60: FALSE | J60: FALSE | K60: FALSE | L60: FALSE | M60: FALSE | N60: FALSE | O60: FALSE | P60: No inspection
A61: Cabins | B61: Storage | C61: 40' | D61: STC.40.5 | E61: TRUE | F61: TRUE | G61: TRUE | H61: TRUE | I61: TRUE | J61: N/A | K61: N/A | L61: FALSE | M61: N/A | N61: TRUE | O61: FALSE | P61: [2026-03-31] Inspection done by khaild | By: khaild
A62: Cabins | B62: Storage | C62: 40' | D62: STC.40.7 | E62: FALSE | F62: FALSE | G62: FALSE | H62: FALSE | I62: FALSE | J62: FALSE | K62: FALSE | L62: FALSE | M62: FALSE | N62: FALSE | O62: FALSE | P62: No inspection
A63: Cabins | B63: Storage | C63: 40' | D63: STC.40.8 | E63: TRUE | F63: TRUE | G63: TRUE | H63: TRUE | I63: TRUE | J63: N/A | K63: N/A | L63: FALSE | M63: N/A | N63: TRUE | O63: FALSE | P63: [2026-03-31] Inspection done by khaild | By: khaild
A64: Cabins | B64: Storage | C64: 40' | D64: STC.40.9 | E64: FALSE | F64: FALSE | G64: FALSE | H64: FALSE | I64: FALSE | J64: FALSE | K64: FALSE | L64: FALSE | M64: FALSE | N64: FALSE | O64: FALSE | P64: No inspection
A65: Cabins | B65: Storage | C65: 40' | D65: STC.40.10 | E65: FALSE | F65: FALSE | G65: FALSE | H65: FALSE | I65: FALSE | J65: FALSE | K65: FALSE | L65: FALSE | M65: FALSE | N65: FALSE | O65: FALSE | P65: No inspection
A66: Cabins | B66: Storage | C66: 40' | D66: STC.40.11 | E66: FALSE | F66: FALSE | G66: FALSE | H66: FALSE | I66: FALSE | J66: FALSE | K66: FALSE | L66: FALSE | M66: FALSE | N66: FALSE | O66: FALSE | P66: No inspection
A67: Cabins | B67: Storage | C67: 40' | D67: STC.40.12 | E67: FALSE | F67: FALSE | G67: FALSE | H67: FALSE | I67: FALSE | J67: FALSE | K67: FALSE | L67: FALSE | M67: FALSE | N67: FALSE | O67: FALSE | P67: No inspection
A68: Cabins | B68: Storage | C68: 40' | D68: STC.40.13 | E68: FALSE | F68: FALSE | G68: FALSE | H68: FALSE | I68: FALSE | J68: FALSE | K68: FALSE | L68: FALSE | M68: FALSE | N68: FALSE | O68: FALSE | P68: No inspection
A69: Cabins | B69: Ticket | C69: 40' | D69: TB.40.1 | E69: FALSE | F69: FALSE | G69: FALSE | H69: FALSE | I69: FALSE | J69: FALSE | K69: FALSE | L69: FALSE | M69: FALSE | N69: FALSE | O69: FALSE | P69: No inspection
A70: Cabins | B70: Ticket | C70: 40' | D70: TB.40.4 | E70: FALSE | F70: FALSE | G70: FALSE | H70: FALSE | I70: FALSE | J70: FALSE | K70: FALSE | L70: FALSE | M70: FALSE | N70: FALSE | O70: FALSE | P70: No inspection
A71: Cabins | B71: 3 Door Sound Proof | C71: 40' | D71: DR.3.40.1 | E71: TRUE | F71: TRUE | G71: TRUE | H71: TRUE | I71: FALSE | J71: TRUE | K71: TRUE | L71: TRUE | M71: TRUE | N71: TRUE | O71: TRUE | P71: [2026-05-15] Before sent we will paint work finished within a day Extrior painting work before we will finished Before sent we will paint within a day Extrior painting | By: calo.lategan@allaith.com | Defects: Exterior paint
A72: Cabins | B72: OPO | C72: 20' L | D72: OPO.L.20.01 | E72: FALSE | F72: FALSE | G72: FALSE | H72: FALSE | I72: FALSE | J72: FALSE | K72: FALSE | L72: FALSE | M72: FALSE | N72: FALSE | O72: FALSE | P72: JIZAN KSA
A73: Cabins | B73: OPO | C73: 20' L | D73: OPO.L.20.02 | E73: FALSE | F73: FALSE | G73: FALSE | H73: FALSE | I73: FALSE | J73: FALSE | K73: FALSE | L73: FALSE | M73: FALSE | N73: FALSE | O73: FALSE | P73: JIZAN KSA
A74: Cabins | B74: OPO | C74: 20' L | D74: OPO.L.20.03 | E74: FALSE | F74: FALSE | G74: FALSE | H74: FALSE | I74: FALSE | J74: FALSE | K74: FALSE | L74: FALSE | M74: FALSE | N74: FALSE | O74: FALSE | P74: JIZAN KSA
A75: Cabins | B75: OPO | C75: 20' L | D75: OPO.L.20.04 | E75: FALSE | F75: FALSE | G75: FALSE | H75: FALSE | I75: FALSE | J75: FALSE | K75: FALSE | L75: FALSE | M75: FALSE | N75: FALSE | O75: FALSE | P75: JIZAN KSA
... A81: Cabins | B81: OPO | C81: 20' L | D81: OPO.L.20.10 | E81: TRUE | F81: TRUE | G81: TRUE | H81: TRUE | I81: FALSE | J81: TRUE | K81: TRUE | L81: TRUE | M81: TRUE | N81: TRUE | O81: TRUE | P81: [2026-06-08] By Calo | By: Calo | Defects: Exterior paint
A82: Cabins | B82: OPO | C82: 20' L | D82: OPO.L.20.11 | E82: TRUE | F82: TRUE | G82: TRUE | H82: TRUE | I82: FALSE | J82: TRUE | K82: TRUE | L82: TRUE | M82: TRUE | N82: TRUE | O82: TRUE | P82: [2026-06-05] By Calo | By: Calo | Defects: Exterior paint | Q82: Booked for ADC 2026
A83: Cabins | B83: OPO | C83: 20' L | D83: OPO.L.20.12 | E83: FALSE | F83: FALSE | G83: FALSE | H83: FALSE | I83: FALSE | J83: FALSE | K83: FALSE | L83: FALSE | M83: FALSE | N83: FALSE | O83: FALSE | P83: No inspection | Q83: Booked for ADC 2026 | R83: No Plant Number
A84: Cabins | B84: OPO Ticket booth | C84: 20' L | D84: OPO.L.20.13 | E84: TRUE | F84: TRUE | G84: TRUE | H84: TRUE | I84: FALSE | J84: TRUE | K84: TRUE | L84: TRUE | M84: TRUE | N84: TRUE | O84: TRUE | P84: [2026-06-08] By Calo | By: Calo | Defects: Exterior paint | Q84: Booked for ADC 2026
A85: Cabins | B85: OPO Ticket booth | C85: 20' L | D85: OPO.L.20.14 | E85: TRUE | F85: TRUE | G85: TRUE | H85: TRUE | I85: FALSE | J85: TRUE | K85: TRUE | L85: TRUE | M85: TRUE | N85: TRUE | O85: TRUE | P85: [2026-06-05] By Calo | By: Calo | Defects: Exterior paint | Q85: Booked for ADC 2026
A86: Cabins | B86: OPO | C86: 20' L | D86: OPO.L.20.15 | E86: TRUE | F86: TRUE | G86: TRUE | H86: TRUE | I86: FALSE | J86: TRUE | K86: TRUE | L86: TRUE | M86: TRUE | N86: TRUE | O86: TRUE | P86: [2026-06-08] By Calo | By: Calo | Defects: Exterior paint
A87: Cabins | B87: OPO | C87: 20' L | D87: OPO.L.20.16 | E87: FALSE | F87: FALSE | G87: FALSE | H87: FALSE | I87: FALSE | J87: FALSE | K87: FALSE | L87: FALSE | M87: FALSE | N87: FALSE | O87: FALSE | P87: QIDDIYA KSA
A88: Cabins | B88: OPO | C88: 20' L | D88: OPO.L.20.17 | E88: FALSE | F88: FALSE | G88: FALSE | H88: FALSE | I88: FALSE | J88: FALSE | K88: FALSE | L88: FALSE | M88: FALSE | N88: FALSE | O88: FALSE | P88: On Hire for DUTCO MOE | R88: No Plant Number
A89: Cabins | B89: OPO | C89: 20' L | D89: OPO.L.20.18 | E89: TRUE | F89: TRUE | G89: TRUE | H89: TRUE | I89: FALSE | J89: TRUE | K89: TRUE | L89: TRUE | M89: TRUE | N89: TRUE | O89: TRUE | P89: [2026-06-05] By Calo | By: Calo | Defects: Exterior paint
A90: Cabins | B90: OPO | C90: 20' L | D90: OPO.L.20.19 | E90: FALSE | F90: FALSE | G90: FALSE | H90: FALSE | I90: FALSE | J90: FALSE | K90: FALSE | L90: FALSE | M90: FALSE | N90: FALSE | O90: FALSE | P90: QIDDIYA KSA
A91: Cabins | B91: OPO | C91: 20' L | D91: OPO.L.20.20 | E91: FALSE | F91: FALSE | G91: FALSE | H91: FALSE | I91: FALSE | J91: FALSE | K91: FALSE | L91: FALSE | M91: FALSE | N91: FALSE | O91: FALSE | P91: QIDDIYA KSA
A92: Cabins | B92: OPO | C92: 20' L | D92: OPO.L.20.21 | E92: FALSE | F92: FALSE | G92: FALSE | H92: FALSE | I92: FALSE | J92: FALSE | K92: FALSE | L92: FALSE | M92: FALSE | N92: FALSE | O92: FALSE | P92: QIDDIYA KSA
A93: Cabins | B93: OPO | C93: 20' L | D93: OPO.L.20.22 | E93: FALSE | F93: FALSE | G93: FALSE | H93: FALSE | I93: FALSE | J93: FALSE | K93: FALSE | L93: FALSE | M93: FALSE | N93: FALSE | O93: FALSE | P93: QIDDIYA KSA
A94: Cabins | B94: OPO | C94: 20' L | D94: OPO.L.20.23 | E94: TRUE | F94: TRUE | G94: TRUE | H94: TRUE | I94: FALSE | J94: TRUE | K94: TRUE | L94: TRUE | M94: TRUE | N94: TRUE | O94: TRUE | P94: [2026-06-05] By Calo | By: Calo | Defects: Exterior paint
A95: Cabins | B95: OPO | C95: 20' L | D95: OPO.L.20.24 | E95: FALSE | F95: FALSE | G95: FALSE | H95: FALSE | I95: FALSE | J95: FALSE | K95: FALSE | L95: FALSE | M95: FALSE | N95: FALSE | O95: FALSE | P95: No inspection
A96: Cabins | B96: OPO | C96: 20' L | D96: OPO.L.20.25 | E96: FALSE | F96: FALSE | G96: FALSE | H96: FALSE | I96: FALSE | J96: FALSE | K96: FALSE | L96: FALSE | M96: FALSE | N96: FALSE | O96: FALSE | P96: No inspection
A97: Cabins | B97: OPO | C97: 20' L | D97: OPO.L.20.26 | E97: TRUE | F97: TRUE | G97: TRUE | H97: TRUE | I97: FALSE | J97: TRUE | K97: TRUE | L97: TRUE | M97: TRUE | N97: TRUE | O97: TRUE | P97: [2026-06-08] By Calo | By: Calo | Defects: Exterior paint
A98: Cabins | B98: OPO | C98: 20' L | D98: OPO.L.20.27 | E98: TRUE | F98: TRUE | G98: TRUE | H98: TRUE | I98: FALSE | J98: TRUE | K98: TRUE | L98: TRUE | M98: TRUE | N98: TRUE | O98: TRUE | P98: [2026-06-05] by Calo | By: Calo | Defects: Exterior paint
A99: Cabins | B99: OPO | C99: 20' L | D99: OPO.L.20.28 | E99: FALSE | F99: FALSE | G99: FALSE | H99: FALSE | I99: FALSE | J99: FALSE | K99: FALSE | L99: FALSE | M99: FALSE | N99: FALSE | O99: FALSE | P99: No inspection
A100: Cabins | B100: OPO | C100: 20' L | D100: OPO.L.20.29 | E100: TRUE | F100: TRUE | G100: TRUE | H100: TRUE | I100: FALSE | J100: TRUE | K100: TRUE | L100: TRUE | M100: TRUE | N100: TRUE | O100: TRUE | P100: [2026-06-08] By Calo | By: Calo | Defects: Exterior paint
... A107: Cabins | B107: OPO | C107: 20' L | D107: OPO.L.20.36 | E107: FALSE | F107: FALSE | G107: FALSE | H107: FALSE | I107: FALSE | J107: FALSE | K107: FALSE | L107: FALSE | M107: FALSE | N107: FALSE | O107: FALSE | P107: Deliverd to Dubai Hayyat Hotel
A108: Cabins | B108: OPO | C108: 20' L | D108: OPO.L.20.37 | E108: TRUE | F108: TRUE | G108: TRUE | H108: TRUE | I108: FALSE | J108: TRUE | K108: TRUE | L108: TRUE | M108: TRUE | N108: TRUE | O108: TRUE | P108: [2026-06-05] by Calo | By: Calo | Defects: Exterior paint | R108: No Plant Number
A109: Cabins | B109: OPO | C109: 20' L | D109: OPO.L.20.38 | E109: TRUE | F109: TRUE | G109: TRUE | H109: TRUE | I109: FALSE | J109: TRUE | K109: TRUE | L109: TRUE | M109: TRUE | N109: TRUE | O109: TRUE | P109: [2026-06-05] By Calo | By: Calo | Defects: Exterior paint
A110: Cabins | B110: OPO | C110: 20' L | D110: OPO.L.20.39 | E110: FALSE | F110: FALSE | G110: FALSE | H110: FALSE | I110: FALSE | J110: FALSE | K110: FALSE | L110: FALSE | M110: FALSE | N110: FALSE | O110: FALSE | P110: No inspection
A111: Cabins | B111: OPO | C111: 20' L | D111: OPO.L.20.40 | E111: FALSE | F111: FALSE | G111: FALSE | H111: FALSE | I111: FALSE | J111: FALSE | K111: FALSE | L111: FALSE | M111: FALSE | N111: FALSE | O111: FALSE | P111: JIZZAN KSA
A112: Cabins | B112: OPO | C112: 20' L | D112: OPO.L.20.41 | E112: FALSE | F112: FALSE | G112: FALSE | H112: FALSE | I112: FALSE | J112: FALSE | K112: FALSE | L112: FALSE | M112: FALSE | N112: FALSE | O112: FALSE | P112: JIZZAN KSA
A113: Cabins | B113: OPO | C113: 20' L | D113: OPO.L.20.42 | E113: FALSE | F113: FALSE | G113: FALSE | H113: FALSE | I113: FALSE | J113: FALSE | K113: FALSE | L113: FALSE | M113: FALSE | N113: FALSE | O113: FALSE | P113: JIZZAN KSA
A114: Cabins | B114: OPO | C114: 20' L | D114: OPO.L.20.43 | E114: FALSE | F114: FALSE | G114: FALSE | H114: FALSE | I114: FALSE | J114: FALSE | K114: FALSE | L114: FALSE | M114: FALSE | N114: FALSE | O114: FALSE | P114: JIZZAN KSA
A115: Cabins | B115: OPO | C115: 20' L | D115: OPO.L.20.44 | E115: FALSE | F115: FALSE | G115: FALSE | H115: FALSE | I115: FALSE | J115: FALSE | K115: FALSE | L115: FALSE | M115: FALSE | N115: FALSE | O115: FALSE | P115: JIZZAN KSA
A116: Cabins | B116: OPO | C116: 20' L | D116: OPO.L.20.45 | E116: TRUE | F116: TRUE | G116: TRUE | H116: TRUE | I116: FALSE | J116: TRUE | K116: TRUE | L116: TRUE | M116: TRUE | N116: TRUE | O116: TRUE | P116: [2026-06-05] by Calo | By: Calo | Defects: Exterior paint | Q116: Booked for ADC 2026
A117: Cabins | B117: OPO | C117: 20' L | D117: OPO.L.20.46 | E117: FALSE | F117: FALSE | G117: FALSE | H117: FALSE | I117: FALSE | J117: FALSE | K117: FALSE | L117: FALSE | M117: FALSE | N117: FALSE | O117: FALSE | P117: Deliverd to Dubai Hayyat Hotel
A118: Cabins | B118: OPO | C118: 20' L | D118: OPO.L.20.47 | E118: TRUE | F118: TRUE | G118: TRUE | H118: TRUE | I118: FALSE | J118: TRUE | K118: TRUE | L118: TRUE | M118: TRUE | N118: TRUE | O118: TRUE | P118: [2026-06-08] By Calo | By: Calo | Defects: Exterior paint
A119: Cabins | B119: OPO | C119: 20' L | D119: OPO.L.20.48 | E119: FALSE | F119: FALSE | G119: FALSE | H119: FALSE | I119: FALSE | J119: FALSE | K119: FALSE | L119: FALSE | M119: FALSE | N119: FALSE | O119: FALSE | P119: Deliverd to Dubai Hayyat Hotel
A120: Cabins | B120: OPO | C120: 20' L | D120: OPO.L.20.49 | E120: TRUE | F120: TRUE | G120: TRUE | H120: TRUE | I120: TRUE | J120: TRUE | K120: TRUE | L120: TRUE | M120: TRUE | N120: TRUE | O120: TRUE | P120: [2026-06-05] By Calo | By: Calo
A121: Cabins | B121: OPO | C121: 20' L | D121: OPO.L.20.50 | E121: FALSE | F121: FALSE | G121: FALSE | H121: FALSE | I121: FALSE | J121: FALSE | K121: FALSE | L121: FALSE | M121: FALSE | N121: FALSE | O121: FALSE | P121: JIZZAN KSA
A122: Cabins | B122: OPO | C122: 20' L | D122: OPO.L.20.51 | E122: FALSE | F122: FALSE | G122: FALSE | H122: FALSE | I122: FALSE | J122: FALSE | K122: FALSE | L122: FALSE | M122: FALSE | N122: FALSE | O122: FALSE | P122: JIZZAN KSA
A123: Cabins | B123: OPO | C123: 20' L | D123: OPO.L.20.52 | E123: FALSE | F123: FALSE | G123: FALSE | H123: FALSE | I123: FALSE | J123: FALSE | K123: FALSE | L123: FALSE | M123: FALSE | N123: FALSE | O123: FALSE | P123: JIZZAN KSA
...

Sheet Flatpack
A1: Category | B1: Description | C1: Size | D1: Plant No. | E1: Flooring | F1: Walls | G1: Ceiling | H1: AC | I1: Lights | J1: Comments
A2: Containers | B2: Flatpack | C2: 16' flatpack | D2: F.P.O.20.1 | E2: FALSE | F2: FALSE | G2: FALSE | H2: FALSE | I2: FALSE | J2: No inspection
A3: Containers | B3: Flatpack | C3: 16' flatpack | D3: F.P.O.20.2 | E3: FALSE | F3: FALSE | G3: FALSE | H3: FALSE | I3: FALSE | J3: No inspection
A4: Containers | B4: Flatpack | C4: 16' flatpack | D4: F.P.O.20.3 | E4: FALSE | F4: FALSE | G4: FALSE | H4: FALSE | I4: FALSE | J4: No inspection
A5: Containers | B5: Flatpack | C5: 16' flatpack | D5: F.P.O.20.4 | E5: FALSE | F5: FALSE | G5: FALSE | H5: FALSE | I5: FALSE | J5: No inspection
A6: Containers | B6: Flatpack | C6: 16' flatpack | D6: F.P.O.20.5 | E6: FALSE | F6: FALSE | G6: FALSE | H6: FALSE | I6: FALSE | J6: No inspection

Sheet Flexiloo
A1: Category | B1: Description | C1: Size | D1: Plant No. | E1: Flooring | F1: Counter tops | G1: Lights | H1: Mirror | I1: Fittings | J1: Ceilings | K1: Walls | L1: Doors | M1: WC - urinal | N1: Basin | O1: Comments
A2: Sanitation | B2: Flexiloo EAWC | C2: EAWC | D2: FLX.EAWC.001 | E2: FALSE | F2: FALSE | G2: FALSE | H2: FALSE | I2: FALSE | J2: FALSE | K2: FALSE | L2: FALSE | M2: FALSE | N2: FALSE | O2: No inspection
A3: Sanitation | B3: Flexiloo EAWC | C3: EAWC | D3: FLX.EAWC.002 | E3: FALSE | F3: FALSE | G3: FALSE | H3: FALSE | I3: FALSE | J3: FALSE | K3: FALSE | L3: FALSE | M3: FALSE | N3: FALSE | O3: No inspection
A4: Sanitation | B4: Flexiloo EAWC | C4: EAWC | D4: FLX.EAWC.003 | E4: FALSE | F4: FALSE | G4: FALSE | H4: FALSE | I4: FALSE | J4: FALSE | K4: FALSE | L4: FALSE | M4: FALSE | N4: FALSE | O4: No inspection
A5: Sanitation | B5: Flexiloo EAWC | C5: EAWC | D5: FLX.EAWC.004 | E5: FALSE | F5: FALSE | G5: FALSE | H5: FALSE | I5: FALSE | J5: FALSE | K5: FALSE | L5: FALSE | M5: FALSE | N5: FALSE
A6: Sanitation | B6: Flexiloo Shower Cubicle | C6: Shower | D6: FLX.SHC.001 | E6: FALSE | F6: FALSE | G6: FALSE | H6: FALSE | I6: FALSE | J6: FALSE | K6: FALSE | L6: FALSE | M6: FALSE | N6: FALSE | O6: No inspection
A7: Sanitation | B7: Flexiloo Shower Cubicle | C7: Shower | D7: FLX.SHC.002 | E7: FALSE | F7: FALSE | G7: FALSE | H7: FALSE | I7: FALSE | J7: FALSE | K7: FALSE | L7: FALSE | M7: FALSE | N7: FALSE | O7: No inspection
A8: Sanitation | B8: Flexiloo Shower Cubicle | C8: Shower | D8: FLX.SHC.003 | E8: FALSE | F8: FALSE | G8: FALSE | H8: FALSE | I8: FALSE | J8: FALSE | K8: FALSE | L8: FALSE | M8: FALSE | N8: FALSE | O8: No inspection
A9: Sanitation | B9: Flexiloo Shower Cubicle | C9: Shower | D9: FLX.SHC.004 | E9: FALSE | F9: FALSE | G9: FALSE | H9: FALSE | I9: FALSE | J9: FALSE | K9: FALSE | L9: FALSE | M9: FALSE | N9: FALSE | O9: No inspection
A10: Sanitation | B10: Flexiloo Gent Urinal | C10: Urinal | D10: FLX.UR.004 | E10: FALSE | F10: FALSE | G10: FALSE | H10: FALSE | I10: FALSE | J10: FALSE | K10: FALSE | L10: FALSE | M10: FALSE | N10: FALSE | O10: No inspection
A11: Sanitation | B11: Flexiloo Gent Urinal | C11: Urinal | D11: FLX.UR.005 | E11: FALSE | F11: FALSE | G11: FALSE | H11: FALSE | I11: FALSE | J11: FALSE | K11: FALSE | L11: FALSE | M11: FALSE | N11: FALSE | O11: No inspection
A12: Sanitation | B12: Flexiloo Gent Urinal | C12: Urinal | D12: FLX.UR.006 | E12: FALSE | F12: FALSE | G12: FALSE | H12: FALSE | I12: FALSE | J12: FALSE | K12: FALSE | L12: FALSE | M12: FALSE | N12: FALSE | O12: No inspection
A13: Sanitation | B13: Flexiloo Gent Urinal | C13: Urinal | D13: FLX.UR.007 | E13: FALSE | F13: FALSE | G13: FALSE | H13: FALSE | I13: FALSE | J13: FALSE | K13: FALSE | L13: FALSE | M13: FALSE | N13: FALSE | O13: No inspection
A14: Sanitation | B14: Flexiloo Gent Urinal | C14: Urinal | D14: FLX.UR.008 | E14: FALSE | F14: FALSE | G14: FALSE | H14: FALSE | I14: FALSE | J14: FALSE | K14: FALSE | L14: FALSE | M14: FALSE | N14: FALSE | O14: No inspection
A15: Sanitation | B15: Flexiloo Gent Urinal | C15: Urinal | D15: FLX.UR.009 | E15: FALSE | F15: FALSE | G15: FALSE | H15: FALSE | I15: FALSE | J15: FALSE | K15: FALSE | L15: FALSE | M15: FALSE | N15: FALSE | O15: No inspection
A16: Sanitation | B16: Flexiloo Gent Urinal | C16: Urinal | D16: FLX.UR.010 | E16: FALSE | F16: FALSE | G16: FALSE | H16: FALSE | I16: FALSE | J16: FALSE | K16: FALSE | L16: FALSE | M16: FALSE | N16: FALSE | O16: No inspection
A17: Sanitation | B17: Flexiloo Gent Urinal | C17: Urinal | D17: FLX.UR.011 | E17: FALSE | F17: FALSE | G17: FALSE | H17: FALSE | I17: FALSE | J17: FALSE | K17: FALSE | L17: FALSE | M17: FALSE | N17: FALSE | O17: No inspection
... A166: Sanitation | B166: Flexiloo WC | C166: Toilet | D166: FLX.WC.32 | E166: FALSE | F166: FALSE | G166: FALSE | H166: FALSE | I166: FALSE | J166: FALSE | K166: FALSE | L166: FALSE | M166: FALSE | N166: FALSE | O166: No inspection
A167: Sanitation | B167: Flexiloo WC | C167: Toilet | D167: FLX.WC.33 | E167: TRUE | F167: N/A | G167: TRUE | H167: N/A | I167: TRUE | J167: TRUE | K167: TRUE | L167: TRUE | M167: TRUE | N167: N/A | O167: [2026-04-16] Inspection done by yadav | By: yadav
A168: Sanitation | B168: Flexiloo WC | C168: Toilet | D168: FLX.WC.34 | E168: FALSE | F168: FALSE | G168: FALSE | H168: FALSE | I168: FALSE | J168: FALSE | K168: FALSE | L168: FALSE | M168: FALSE | N168: FALSE | O168: No inspection
A169: Sanitation | B169: Flexiloo WC | C169: Toilet | D169: FLX.WC.35 | E169: FALSE | F169: FALSE | G169: FALSE | H169: FALSE | I169: FALSE | J169: FALSE | K169: FALSE | L169: FALSE | M169: FALSE | N169: FALSE | O169: No inspection
A170: Sanitation | B170: Flexiloo WC | C170: Toilet | D170: FLX.WC.36 | E170: FALSE | F170: FALSE | G170: FALSE | H170: FALSE | I170: FALSE | J170: FALSE | K170: FALSE | L170: FALSE | M170: FALSE | N170: FALSE | O170: No inspection
A171: Sanitation | B171: Flexiloo WC | C171: Toilet | D171: FLX.WC.37 | E171: FALSE | F171: FALSE | G171: FALSE | H171: FALSE | I171: FALSE | J171: FALSE | K171: FALSE | L171: FALSE | M171: FALSE | N171: FALSE | O171: No inspection
A172: Sanitation | B172: Flexiloo WC | C172: Toilet | D172: FLX.WC.38 | E172: FALSE | F172: FALSE | G172: FALSE | H172: FALSE | I172: FALSE | J172: FALSE | K172: FALSE | L172: FALSE | M172: FALSE | N172: FALSE | O172: No inspection
A173: Sanitation | B173: Flexiloo WC | C173: Toilet | D173: FLX.WC.39 | E173: FALSE | F173: FALSE | G173: FALSE | H173: FALSE | I173: FALSE | J173: FALSE | K173: FALSE | L173: FALSE | M173: FALSE | N173: FALSE | O173: No inspection
A174: Sanitation | B174: Flexiloo WC | C174: Toilet | D174: FLX.WC.40 | E174: FALSE | F174: FALSE | G174: FALSE | H174: FALSE | I174: FALSE | J174: FALSE | K174: FALSE | L174: FALSE | M174: FALSE | N174: FALSE | O174: No inspection
A175: Sanitation | B175: Flexiloo WC | C175: Toilet | D175: FLX.WC.41 | E175: FALSE | F175: FALSE | G175: FALSE | H175: FALSE | I175: FALSE | J175: FALSE | K175: FALSE | L175: FALSE | M175: FALSE | N175: FALSE | O175: No inspection
A176: Sanitation | B176: Flexiloo WC | C176: Toilet | D176: FLX.WC.42 | E176: FALSE | F176: FALSE | G176: FALSE | H176: FALSE | I176: FALSE | J176: FALSE | K176: FALSE | L176: FALSE | M176: FALSE | N176: FALSE | O176: No inspection
A177: Sanitation | B177: Flexiloo WC | C177: Toilet | D177: FLX.WC.43 | E177: FALSE | F177: FALSE | G177: FALSE | H177: FALSE | I177: FALSE | J177: FALSE | K177: FALSE | L177: FALSE | M177: FALSE | N177: FALSE | O177: No inspection
A178: Sanitation | B178: Flexiloo WC | C178: Toilet | D178: FLX.WC.44 | E178: FALSE | F178: FALSE | G178: FALSE | H178: FALSE | I178: FALSE | J178: FALSE | K178: FALSE | L178: FALSE | M178: FALSE | N178: FALSE | O178: No inspection
A179: Sanitation | B179: Flexiloo WC | C179: Toilet | D179: FLX.WC.45 | E179: FALSE | F179: FALSE | G179: FALSE | H179: FALSE | I179: FALSE | J179: FALSE | K179: FALSE | L179: FALSE | M179: FALSE | N179: FALSE | O179: No inspection
A180: Sanitation | B180: Flexiloo WC | C180: Toilet | D180: FLX.WC.46 | E180: TRUE | F180: FALSE | G180: TRUE | H180: N/A | I180: FALSE | J180: TRUE | K180: TRUE | L180: TRUE | M180: TRUE | N180: TRUE | O180: [2026-04-14] Inspection done yadav | By: calo.lategan@allaith.com
A181: Sanitation | B181: Flexiloo WC | C181: Toilet | D181: FLX.WC.47 | E181: TRUE | F181: FALSE | G181: TRUE | H181: N/A | I181: FALSE | J181: TRUE | K181: TRUE | L181: TRUE | M181: TRUE | N181: TRUE | O181: [2026-04-14] Inspection done by yadav | By: yadav
A182: Sanitation | B182: Flexiloo WC | C182: Toilet | D182: FLX.WC.48 | E182: FALSE | F182: FALSE | G182: FALSE | H182: FALSE | I182: FALSE | J182: FALSE | K182: FALSE | L182: FALSE | M182: FALSE | N182: FALSE | O182: No inspection
A183: Sanitation | B183: Flexiloo WC | C183: Toilet | D183: FLX.WC.49 | E183: FALSE | F183: FALSE | G183: FALSE | H183: FALSE | I183: FALSE | J183: FALSE | K183: FALSE | L183: FALSE | M183: FALSE | N183: FALSE | O183: No inspection
A184: Sanitation | B184: Flexiloo WC | C184: Toilet | D184: FLX.WC.50 | E184: FALSE | F184: FALSE | G184: FALSE | H184: FALSE | I184: FALSE | J184: FALSE | K184: FALSE | L184: FALSE | M184: FALSE | N184: FALSE | O184: No inspection
A185: Sanitation | B185: Flexiloo WC | C185: Toilet | D185: FLX.WC.51 | E185: FALSE | F185: FALSE | G185: FALSE | H185: FALSE | I185: FALSE | J185: FALSE | K185: FALSE | L185: FALSE | M185: FALSE | N185: FALSE | O185: No inspection
A186: Sanitation | B186: Flexiloo WC | C186: Toilet | D186: FLX.WC.52 | E186: FALSE | F186: FALSE | G186: FALSE | H186: FALSE | I186: FALSE | J186: FALSE | K186: FALSE | L186: FALSE | M186: FALSE | N186: FALSE | O186: No inspection
A187: Sanitation | B187: Flexiloo WC | C187: Toilet | D187: FLX.WC.53 | E187: FALSE | F187: FALSE | G187: FALSE | H187: FALSE | I187: FALSE | J187: FALSE | K187: FALSE | L187: FALSE | M187: FALSE | N187: FALSE | O187: No inspection
A188: Sanitation | B188: Flexiloo WC | C188: Toilet | D188: FLX.WC.54 | E188: FALSE | F188: FALSE | G188: FALSE | H188: FALSE | I188: FALSE | J188: FALSE | K188: FALSE | L188: FALSE | M188: FALSE | N188: FALSE | O188: No inspection
A189: Sanitation | B189: Flexiloo WC | C189: Toilet | D189: FLX.WC.55 | E189: FALSE | F189: FALSE | G189: FALSE | H189: FALSE | I189: FALSE | J189: FALSE | K189: FALSE | L189: FALSE | M189: FALSE | N189: FALSE | O189: No inspection
A190: Sanitation | B190: Flexiloo WC | C190: Toilet | D190: FLX.WC.56 | E190: FALSE | F190: FALSE | G190: FALSE | H190: FALSE | I190: FALSE | J190: FALSE | K190: FALSE | L190: FALSE | M190: FALSE | N190: FALSE | O190: No inspection
A191: Sanitation | B191: Flexiloo WC | C191: Toilet | D191: FLX.WC.57 | E191: TRUE | F191: FALSE | G191: TRUE | H191: N/A | I191: FALSE | J191: TRUE | K191: TRUE | L191: TRUE | M191: TRUE | N191: TRUE | O191: [2026-04-14] Inspection done by yadav | By: yadav
A192: Sanitation | B192: Flexiloo WC | C192: Toilet | D192: FLX.WC.58 | E192: FALSE | F192: FALSE | G192: FALSE | H192: FALSE | I192: FALSE | J192: FALSE | K192: FALSE | L192: FALSE | M192: FALSE | N192: FALSE | O192: No inspection
A193: Sanitation | B193: Flexiloo WC | C193: Toilet | D193: FLX.WC.59 | E193: TRUE | F193: FALSE | G193: TRUE | H193: N/A | I193: FALSE | J193: TRUE | K193: TRUE | L193: N/A | M193: TRUE | N193: TRUE | O193: [2026-04-14] Inspection done by yadav | By: yadav
A194: Sanitation | B194: Flexiloo WC | C194: Toilet | D194: FLX.WC.60 | E194: FALSE | F194: FALSE | G194: FALSE | H194: FALSE | I194: FALSE | J194: FALSE | K194: FALSE | L194: FALSE | M194: FALSE | N194: FALSE | O194: No inspection
A195: Sanitation | B195: Flexiloo WC | C195: Toilet | D195: FLX.WC.61 | E195: FALSE | F195: FALSE | G195: FALSE | H195: FALSE | I195: FALSE | J195: FALSE | K195: FALSE | L195: FALSE | M195: FALSE | N195: FALSE | O195: No inspection
A196: Sanitation | B196: Flexiloo WC | C196: Toilet | D196: FLX.WC.62 | E196: FALSE | F196: FALSE | G196: FALSE | H196: FALSE | I196: FALSE | J196: FALSE | K196: FALSE | L196: FALSE | M196: FALSE | N196: FALSE | O196: No inspection
A197: Sanitation | B197: Flexiloo WC | C197: Toilet | D197: FLX.WC.63 | E197: FALSE | F197: FALSE | G197: FALSE | H197: FALSE | I197: FALSE | J197: FALSE | K197: FALSE | L197: FALSE | M197: FALSE | N197: FALSE | O197: No inspection
A198: Sanitation | B198: Flexiloo WC | C198: Toilet | D198: FLX.WC.64 | E198: FALSE | F198: FALSE | G198: FALSE | H198: FALSE | I198: FALSE | J198: FALSE | K198: FALSE | L198: FALSE | M198: FALSE | N198: FALSE | O198: No inspection
A199: Sanitation | B199: Flexiloo WC | C199: Toilet | D199: FLX.WC.65 | E199: FALSE | F199: FALSE | G199: FALSE | H199: FALSE | I199: FALSE | J199: FALSE | K199: FALSE | L199: FALSE | M199: FALSE | N199: FALSE | O199: No inspection
A200: Sanitation | B200: Flexiloo WC | C200: Toilet | D200: FLX.WC.66 | E200: FALSE | F200: FALSE | G200: FALSE | H200: FALSE | I200: FALSE | J200: FALSE | K200: FALSE | L200: FALSE | M200: FALSE | N200: FALSE | O200: No inspection
A201: Sanitation | B201: Flexiloo WC | C201: Toilet | D201: FLX.WC.67 | E201: TRUE | F201: FALSE | G201: TRUE | H201: N/A | I201: FALSE | J201: TRUE | K201: TRUE | L201: TRUE | M201: TRUE | N201: TRUE | O201: [2026-04-14] Inspection done by yadav | By: yadav
A202: Sanitation | B202: Flexiloo WC | C202: Toilet | D202: FLX.WC.68 | E202: FALSE | F202: FALSE | G202: FALSE | H202: FALSE | I202: FALSE | J202: FALSE | K202: FALSE | L202: FALSE | M202: FALSE | N202: FALSE | O202: No inspection
A203: Sanitation | B203: Flexiloo WC | C203: Toilet | D203: FLX.WC.69 | E203: FALSE | F203: FALSE | G203: FALSE | H203: FALSE | I203: FALSE | J203: FALSE | K203: FALSE | L203: FALSE | M203: FALSE | N203: FALSE | O203: No inspection
A204: Sanitation | B204: Flexiloo WC | C204: Toilet | D204: FLX.WC.70 | E204: FALSE | F204: FALSE | G204: FALSE | H204: FALSE | I204: FALSE | J204: FALSE | K204: FALSE | L204: FALSE | M204: FALSE | N204: FALSE | O204: No inspection
A205: Sanitation | B205: Flexiloo WC | C205: Toilet | D205: FLX.WC.71 | E205: FALSE | F205: FALSE | G205: FALSE | H205: FALSE | I205: FALSE | J205: FALSE | K205: FALSE | L205: FALSE | M205: FALSE | N205: FALSE | O205: No inspection
A206: Sanitation | B206: Flexiloo WC | C206: Toilet | D206: FLX.WC.73 | E206: FALSE | F206: FALSE | G206: FALSE | H206: FALSE | I206: FALSE | J206: FALSE | K206: FALSE | L206: FALSE | M206: FALSE | N206: FALSE | O206: No inspection
A207: Sanitation | B207: Flexiloo WC | C207: Toilet | D207: FLX.WC.74 | E207: FALSE | F207: FALSE | G207: FALSE | H207: FALSE | I207: FALSE | J207: FALSE | K207: FALSE | L207: FALSE | M207: FALSE | N207: FALSE | O207: No inspection
A208: Sanitation | B208: Flexiloo WC | C208: Toilet | D208: FLX.WC.75 | E208: FALSE | F208: FALSE | G208: FALSE | H208: FALSE | I208: FALSE | J208: FALSE | K208: FALSE | L208: FALSE | M208: FALSE | N208: FALSE | O208: No inspection
A209: Sanitation | B209: Flexiloo WC | C209: Toilet | D209: FLX.WC.76 | E209: FALSE | F209: FALSE | G209: FALSE | H209: FALSE | I209: FALSE | J209: FALSE | K209: FALSE | L209: FALSE | M209: FALSE | N209: FALSE | O209: No inspection
A210: Sanitation | B210: Flexiloo WC (NEW) | C210: Toilet | D210: FLX.WC.77 | E210: FALSE | F210: FALSE | G210: FALSE | H210: FALSE | I210: FALSE | J210: FALSE | K210: FALSE | L210: FALSE | M210: FALSE | N210: FALSE | O210: No inspection
A211: Sanitation | B211: Flexiloo WC (NEW) | C211: Toilet | D211: FLX.WC.78 | E211: FALSE | F211: FALSE | G211: FALSE | H211: FALSE | I211: FALSE | J211: FALSE | K211: FALSE | L211: FALSE | M211: FALSE | N211: FALSE | O211: No inspection
A212: Sanitation | B212: Flexiloo WC (NEW) | C212: Toilet | D212: FLX.WC.79 | E212: FALSE | F212: FALSE | G212: FALSE | H212: FALSE | I212: FALSE | J212: FALSE | K212: FALSE | L212: FALSE | M212: FALSE | N212: FALSE | O212: No inspection
A213: Sanitation | B213: Flexiloo WC (NEW) | C213: Toilet | D213: FLX.WC.80 | E213: FALSE | F213: FALSE | G213: FALSE | H213: FALSE | I213: FALSE | J213: FALSE | K213: FALSE | L213: FALSE | M213: FALSE | N213: FALSE | O213: No inspection
... A230: Sanitation | B230: Flexiloo Pump | C230: Pump | D230: FLX.PU.023 | E230: FALSE | F230: FALSE | G230: FALSE | H230: FALSE | I230: FALSE | J230: FALSE | K230: FALSE | L230: FALSE | M230: FALSE | N230: FALSE | O230: No inspection

Sheet NEW Flexiloos
A1: Category | B1: Description | C1: Plant number | D1: Size | E1: Quantity | F1: Ply Cutting | G1: Cutting Sunmica | H1: Gluing Sunmica | I1: Groves for Hinges | J1: Ply frame assy | K1: Cutting Alu. Frame | L1: Assembly | M1: WC Fitting | N1: Vanity fitting | O1: Lighting | P1: Door frame | Q1: Door panel | R1: Snags | S1: TESTING | T1: Completion Date | U1: Comments
A2: Sanitation | B2: Flexiloo WC | C2: FLX.WC.87 | D2: Toilet | E2: 1 | F2: TRUE | G2: TRUE | H2: TRUE | I2: TRUE | J2: TRUE | K2: TRUE | L2: TRUE | M2: TRUE | N2: x | O2: TRUE | P2: TRUE | Q2: TRUE | R2: FALSE | S2: TRUE | T2: 45866
A3: Sanitation | B3: Flexiloo WC | C3: FLX.WC.88 | D3: Toilet | E3: 2 | F3: TRUE | G3: TRUE | H3: TRUE | I3: TRUE | J3: TRUE | K3: TRUE | L3: TRUE | M3: TRUE | N3: x | O3: TRUE | P3: TRUE | Q3: TRUE | R3: FALSE | S3: TRUE | T3: 45866
A4: Sanitation | B4: Flexiloo WC | C4: FLX.WC.89 | D4: Toilet | E4: 3 | F4: TRUE | G4: TRUE | H4: TRUE | I4: TRUE | J4: TRUE | K4: TRUE | L4: TRUE | M4: TRUE | N4: x | O4: TRUE | P4: TRUE | Q4: TRUE | R4: FALSE | S4: TRUE | T4: 45875
A5: Sanitation | B5: Flexiloo WC | C5: FLX.WC.90 | D5: Toilet | E5: 4 | F5: TRUE | G5: TRUE | H5: TRUE | I5: TRUE | J5: TRUE | K5: TRUE | L5: TRUE | M5: TRUE | N5: x | O5: TRUE | P5: TRUE | Q5: TRUE | R5: FALSE | S5: TRUE | T5: 45875
A6: Sanitation | B6: Flexiloo WC | C6: FLX.WC.91 | D6: Toilet | E6: 5 | F6: TRUE | G6: TRUE | H6: TRUE | I6: TRUE | J6: TRUE | K6: TRUE | L6: TRUE | M6: TRUE | N6: x | O6: TRUE | P6: TRUE | Q6: TRUE | R6: FALSE | S6: TRUE | T6: 45880
A7: Sanitation | B7: Flexiloo WC | C7: FLX.WC.92 | D7: Toilet | E7: 6 | F7: TRUE | G7: TRUE | H7: TRUE | I7: TRUE | J7: TRUE | K7: TRUE | L7: TRUE | M7: TRUE | N7: x | O7: TRUE | P7: TRUE | Q7: TRUE | R7: FALSE | S7: TRUE | T7: 45880
A8: Sanitation | B8: Flexiloo WC | C8: FLX.WC.93 | D8: Toilet | E8: 7 | F8: TRUE | G8: TRUE | H8: TRUE | I8: TRUE | J8: TRUE | K8: TRUE | L8: TRUE | M8: TRUE | N8: x | O8: TRUE | P8: TRUE | Q8: TRUE | R8: FALSE | S8: TRUE | T8: 45883
A9: Sanitation | B9: Flexiloo WC | C9: FLX.WC.94 | D9: Toilet | E9: 8 | F9: TRUE | G9: TRUE | H9: TRUE | I9: TRUE | J9: TRUE | K9: TRUE | L9: TRUE | M9: TRUE | N9: x | O9: TRUE | P9: TRUE | Q9: TRUE | R9: FALSE | S9: TRUE | T9: 45883
A10: Sanitation | B10: Flexiloo WC | C10: FLX.WC.95 | D10: Toilet | E10: 9 | F10: TRUE | G10: TRUE | H10: TRUE | I10: TRUE | J10: TRUE | K10: TRUE | L10: TRUE | M10: TRUE | N10: x | O10: TRUE | P10: TRUE | Q10: TRUE | R10: FALSE | S10: TRUE
A11: Sanitation | B11: Flexiloo WC | C11: FLX.WC.96 | D11: Toilet | E11: 10 | F11: TRUE | G11: TRUE | H11: TRUE | I11: TRUE | J11: TRUE | K11: TRUE | L11: TRUE | M11: TRUE | N11: x | O11: TRUE | P11: TRUE | Q11: TRUE | R11: FALSE | S11: TRUE
A12: Sanitation | B12: Flexiloo WC | C12: FLX.WC.97 | D12: Toilet | E12: 11 | F12: TRUE | G12: TRUE | H12: TRUE | I12: TRUE | J12: TRUE | K12: TRUE | L12: TRUE | M12: TRUE | N12: x | O12: TRUE | P12: TRUE | Q12: TRUE | R12: FALSE | S12: TRUE
A13: Sanitation | B13: Flexiloo WC | C13: FLX.WC.98 | D13: Toilet | E13: 12 | F13: TRUE | G13: TRUE | H13: TRUE | I13: TRUE | J13: TRUE | K13: TRUE | L13: TRUE | M13: TRUE | N13: x | O13: TRUE | P13: TRUE | Q13: TRUE | R13: FALSE | S13: TRUE
A14: Sanitation | B14: Flexiloo WC | C14: FLX.WC.99 | D14: Toilet | E14: 13 | F14: TRUE | G14: TRUE | H14: TRUE | I14: TRUE | J14: TRUE | K14: TRUE | L14: TRUE | M14: TRUE | N14: x | O14: TRUE | P14: TRUE | Q14: TRUE | R14: FALSE | S14: TRUE
A15: Sanitation | B15: Flexiloo WC | C15: FLX.WC.100 | D15: Toilet | E15: 14 | F15: TRUE | G15: TRUE | H15: TRUE | I15: TRUE | J15: TRUE | K15: TRUE | L15: TRUE | M15: TRUE | N15: x | O15: TRUE | P15: TRUE | Q15: TRUE | R15: FALSE | S15: TRUE
A16: Sanitation | B16: Flexiloo WC | C16: FLX.WC.101 | D16: Toilet | E16: 15 | F16: TRUE | G16: TRUE | H16: TRUE | I16: TRUE | J16: TRUE | K16: TRUE | L16: TRUE | M16: TRUE | N16: x | O16: TRUE | P16: TRUE | Q16: TRUE | R16: FALSE | S16: TRUE
A17: Sanitation | B17: Flexiloo WC | C17: FLX.WC.102 | D17: Toilet | E17: 16 | F17: TRUE | G17: TRUE | H17: TRUE | I17: TRUE | J17: TRUE | K17: TRUE | L17: TRUE | M17: TRUE | N17: x | O17: TRUE | P17: TRUE | Q17: TRUE | R17: FALSE | S17: TRUE
A18: Sanitation | B18: Flexiloo WC | C18: FLX.WC.103 | D18: Toilet | E18: 17 | F18: TRUE | G18: TRUE | H18: TRUE | I18: TRUE | J18: TRUE | K18: TRUE | L18: TRUE | M18: TRUE | N18: x | O18: TRUE | P18: TRUE | Q18: TRUE | R18: FALSE | S18: TRUE
A19: Sanitation | B19: Flexiloo WC | C19: FLX.WC.104 | D19: Toilet | E19: 18 | F19: TRUE | G19: TRUE | H19: TRUE | I19: TRUE | J19: TRUE | K19: TRUE | L19: TRUE | M19: TRUE | N19: x | O19: TRUE | P19: TRUE | Q19: TRUE | R19: FALSE | S19: TRUE
A20: Sanitation | B20: Flexiloo WC | C20: FLX.WC.105 | D20: Toilet | E20: 19 | F20: TRUE | G20: TRUE | H20: TRUE | I20: TRUE | J20: TRUE | K20: TRUE | L20: TRUE | M20: TRUE | N20: x | O20: TRUE | P20: TRUE | Q20: TRUE | R20: FALSE | S20: TRUE
A21: Sanitation | B21: Flexiloo WC | C21: FLX.WC.106 | D21: Toilet | E21: 20 | F21: TRUE | G21: TRUE | H21: TRUE | I21: TRUE | J21: TRUE | K21: TRUE | L21: TRUE | M21: TRUE | N21: x | O21: TRUE | P21: TRUE | Q21: TRUE | R21: FALSE | S21: TRUE
... A46: Sanitation | B46: Flexiloo WC | C46: FLX.WC.131 | D46: Toilet | E46: 45 | F46: FALSE | G46: FALSE | H46: FALSE | I46: FALSE | J46: FALSE | K46: FALSE | L46: FALSE | M46: FALSE | N46: x | O46: FALSE | P46: FALSE | Q46: FALSE | R46: FALSE | S46: FALSE
A47: Sanitation | B47: Flexiloo WC | C47: FLX.WC.132 | D47: Toilet | E47: 46 | F47: FALSE | G47: FALSE | H47: FALSE | I47: FALSE | J47: FALSE | K47: FALSE | L47: FALSE | M47: FALSE | N47: FALSE | O47: FALSE | P47: FALSE | Q47: FALSE | R47: FALSE | S47: FALSE
A48: Sanitation | B48: Flexiloo WC | C48: FLX.WC.133 | D48: Toilet | E48: 47 | F48: FALSE | G48: FALSE | H48: FALSE | I48: FALSE | J48: FALSE | K48: FALSE | L48: FALSE | M48: FALSE | N48: FALSE | O48: FALSE | P48: FALSE | Q48: FALSE | R48: FALSE | S48: FALSE
A49: Sanitation | B49: Flexiloo WC | C49: FLX.WC.134 | D49: Toilet | E49: 48 | F49: FALSE | G49: FALSE | H49: FALSE | I49: FALSE | J49: FALSE | K49: FALSE | L49: FALSE | M49: FALSE | N49: FALSE | O49: FALSE | P49: FALSE | Q49: FALSE | R49: FALSE | S49: FALSE
A50: Sanitation | B50: Flexiloo WC | C50: FLX.WC.135 | D50: Toilet | E50: 49 | F50: FALSE | G50: FALSE | H50: FALSE | I50: FALSE | J50: FALSE | K50: FALSE | L50: FALSE | M50: FALSE | N50: FALSE | O50: FALSE | P50: FALSE | Q50: FALSE | R50: FALSE | S50: FALSE
A51: Sanitation | B51: Flexiloo WC | C51: FLX.WC.136 | D51: Toilet | E51: 50 | F51: FALSE | G51: FALSE | H51: FALSE | I51: FALSE | J51: FALSE | K51: FALSE | L51: FALSE | M51: FALSE | N51: FALSE | O51: FALSE | P51: FALSE | Q51: FALSE | R51: FALSE | S51: FALSE
A52: Sanitation | B52: Flexiloo WC | C52: FLX.WC.137 | D52: Toilet | E52: 51 | F52: FALSE | G52: FALSE | H52: FALSE | I52: FALSE | J52: FALSE | K52: FALSE | L52: FALSE | M52: FALSE | N52: FALSE | O52: FALSE | P52: FALSE | Q52: FALSE | R52: FALSE | S52: FALSE
A53: Sanitation | B53: Flexiloo WC | C53: FLX.WC.138 | D53: Toilet | E53: FALSE | F53: FALSE | G53: FALSE | H53: FALSE | I53: FALSE | J53: FALSE | K53: FALSE | L53: FALSE | M53: FALSE | N53: FALSE | O53: FALSE | P53: FALSE | Q53: FALSE | R53: FALSE | S53: FALSE
A55: Sanitation | B55: Flexiloo Gent Urinal | C55: FLX.UR.054 | D55: Urinal | E55: 1 | F55: FALSE | G55: FALSE | H55: FALSE | I55: x | J55: FALSE | K55: FALSE | L55: FALSE | M55: x | N55: x | O55: FALSE | P55: x | Q55: x | R55: FALSE | S55: FALSE
A56: Sanitation | B56: Flexiloo Gent Urinal | C56: FLX.UR.055 | D56: Urinal | E56: 2 | F56: FALSE | G56: FALSE | H56: FALSE | I56: x | J56: FALSE | K56: FALSE | L56: FALSE | M56: x | N56: x | O56: FALSE | P56: x | Q56: x | R56: FALSE | S56: FALSE
A57: Sanitation | B57: Flexiloo Gent Urinal | C57: FLX.UR.056 | D57: Urinal | E57: 3 | F57: FALSE | G57: FALSE | H57: FALSE | I57: x | J57: FALSE | K57: FALSE | L57: FALSE | M57: x | N57: x | O57: FALSE | P57: x | Q57: x | R57: FALSE | S57: FALSE
A58: Sanitation | B58: Flexiloo Gent Urinal | C58: FLX.UR.057 | D58: Urinal | E58: 4 | F58: FALSE | G58: FALSE | H58: FALSE | I58: x | J58: FALSE | K58: FALSE | L58: FALSE | M58: x | N58: x | O58: FALSE | P58: x | Q58: x | R58: FALSE | S58: FALSE
A59: Sanitation | B59: Flexiloo Gent Urinal | C59: FLX.UR.058 | D59: Urinal | E59: 5 | F59: FALSE | G59: FALSE | H59: FALSE | I59: x | J59: FALSE | K59: FALSE | L59: FALSE | M59: x | N59: x | O59: FALSE | P59: x | Q59: x | R59: FALSE | S59: FALSE
A60: Sanitation | B60: Flexiloo Gent Urinal | C60: FLX.UR.059 | D60: Urinal | E60: 6 | F60: FALSE | G60: FALSE | H60: FALSE | I60: x | J60: FALSE | K60: FALSE | L60: FALSE | M60: x | N60: x | O60: FALSE | P60: x | Q60: x | R60: FALSE | S60: FALSE
A61: Sanitation | B61: Flexiloo Gent Urinal | C61: FLX.UR.060 | D61: Urinal | E61: 7 | F61: FALSE | G61: FALSE | H61: FALSE | I61: x | J61: FALSE | K61: FALSE | L61: FALSE | M61: x | N61: x | O61: FALSE | P61: x | Q61: x | R61: FALSE | S61: FALSE
A62: Sanitation | B62: Flexiloo Gent Urinal | C62: FLX.UR.061 | D62: Urinal | E62: 8 | F62: FALSE | G62: FALSE | H62: FALSE | I62: x | J62: FALSE | K62: FALSE | L62: FALSE | M62: x | N62: x | O62: FALSE | P62: x | Q62: x | R62: FALSE | S62: FALSE
A63: Sanitation | B63: Flexiloo Gent Urinal | C63: FLX.UR.062 | D63: Urinal | E63: 9 | F63: FALSE | G63: FALSE | H63: FALSE | I63: x | J63: FALSE | K63: FALSE | L63: FALSE | M63: x | N63: x | O63: FALSE | P63: x | Q63: x | R63: FALSE | S63: FALSE
A64: Sanitation | B64: Flexiloo Gent Urinal | C64: FLX.UR.063 | D64: Urinal | E64: 10 | F64: FALSE | G64: FALSE | H64: FALSE | I64: x | J64: FALSE | K64: FALSE | L64: FALSE | M64: x | N64: x | O64: FALSE | P64: x | Q64: x | R64: FALSE | S64: FALSE
A65: Sanitation | B65: Flexiloo Gent Urinal | C65: FLX.UR.064 | D65: Urinal | E65: 11 | F65: FALSE | G65: FALSE | H65: FALSE | I65: x | J65: FALSE | K65: FALSE | L65: FALSE | M65: x | N65: x | O65: FALSE | P65: x | Q65: x | R65: FALSE | S65: FALSE
A66: Sanitation | B66: Flexiloo Gent Urinal | C66: FLX.UR.065 | D66: Urinal | E66: 12 | F66: FALSE | G66: FALSE | H66: FALSE | I66: x | J66: FALSE | K66: FALSE | L66: FALSE | M66: x | N66: x | O66: FALSE | P66: x | Q66: x | R66: FALSE | S66: FALSE
... A73: Sanitation | B73: Flexiloo Gent Urinal | C73: FLX.UR.072 | D73: Urinal | E73: 19 | F73: FALSE | G73: FALSE | H73: FALSE | I73: x | J73: FALSE | K73: FALSE | L73: FALSE | M73: x | N73: x | O73: FALSE | P73: x | Q73: x | R73: FALSE | S73: FALSE
A74: Sanitation | B74: Flexiloo Gent Urinal | C74: FLX.UR.073 | D74: Urinal | E74: FALSE | F74: FALSE | G74: FALSE | H74: FALSE | I74: FALSE | J74: FALSE | K74: FALSE | L74: FALSE | M74: FALSE | N74: FALSE | O74: FALSE | P74: FALSE | Q74: FALSE | R74: FALSE | S74: FALSE
A76: Sanitation | B76: Flexiloo Vanity | C76: FLX.VA.087 | D76: Vanity | E76: 1 | F76: TRUE | G76: TRUE | H76: TRUE | I76: x | J76: TRUE | K76: TRUE | L76: TRUE | M76: x | N76: TRUE | O76: TRUE | P76: x | Q76: x | R76: FALSE | S76: TRUE | T76: 45879 | U76: Waiting for Wash basin and sensor tap
A77: Sanitation | B77: Flexiloo Vanity | C77: FLX.VA.088 | D77: Vanity | E77: 2 | F77: TRUE | G77: TRUE | H77: TRUE | I77: x | J77: TRUE | K77: TRUE | L77: TRUE | M77: x | N77: TRUE | O77: TRUE | P77: x | Q77: x | R77: FALSE | S77: TRUE | T77: 45880 | U77: Waiting for Wash basin and sensor tap
A78: Sanitation | B78: Flexiloo Vanity | C78: FLX.VA.089 | D78: Vanity | E78: 3 | F78: TRUE | G78: TRUE | H78: TRUE | I78: x | J78: TRUE | K78: TRUE | L78: TRUE | M78: x | N78: TRUE | O78: TRUE | P78: x | Q78: x | R78: FALSE | S78: TRUE | T78: 45881 | U78: Waiting for Wash basin and sensor tap
A79: Sanitation | B79: Flexiloo Vanity | C79: FLX.VA.090 | D79: Vanity | E79: 4 | F79: TRUE | G79: TRUE | H79: TRUE | I79: x | J79: TRUE | K79: TRUE | L79: TRUE | M79: x | N79: TRUE | O79: TRUE | P79: x | Q79: x | R79: FALSE | S79: TRUE | T79: 45882 | U79: Waiting for Wash basin and sensor tap
A80: Sanitation | B80: Flexiloo Vanity | C80: FLX.VA.091 | D80: Vanity | E80: 5 | F80: TRUE | G80: TRUE | H80: TRUE | I80: x | J80: TRUE | K80: TRUE | L80: TRUE | M80: x | N80: TRUE | O80: TRUE | P80: x | Q80: x | R80: FALSE | S80: TRUE | T80: 45883 | U80: Waiting for Wash basin and sensor tap
A81: Sanitation | B81: Flexiloo Vanity | C81: FLX.VA.092 | D81: Vanity | E81: 6 | F81: TRUE | G81: TRUE | H81: TRUE | I81: x | J81: TRUE | K81: TRUE | L81: TRUE | M81: x | N81: TRUE | O81: TRUE | P81: x | Q81: x | R81: FALSE | S81: TRUE | T81: 45884 | U81: Waiting for Wash basin and sensor tap
A82: Sanitation | B82: Flexiloo Vanity | C82: FLX.VA.093 | D82: Vanity | E82: 7 | F82: TRUE | G82: TRUE | H82: TRUE | I82: x | J82: TRUE | K82: TRUE | L82: TRUE | M82: x | N82: TRUE | O82: TRUE | P82: x | Q82: x | R82: FALSE | S82: TRUE | T82: 45885 | U82: Waiting for Wash basin and sensor tap
A83: Sanitation | B83: Flexiloo Vanity | C83: FLX.VA.094 | D83: Vanity | E83: 8 | F83: TRUE | G83: TRUE | H83: TRUE | I83: x | J83: TRUE | K83: TRUE | L83: TRUE | M83: x | N83: TRUE | O83: TRUE | P83: x | Q83: x | R83: FALSE | S83: TRUE | T83: 45886 | U83: Waiting for Wash basin and sensor tap
A84: Sanitation | B84: Flexiloo Vanity | C84: FLX.VA.095 | D84: Vanity | E84: 9 | F84: TRUE | G84: TRUE | H84: TRUE | I84: x | J84: TRUE | K84: TRUE | L84: TRUE | M84: x | N84: TRUE | O84: TRUE | P84: x | Q84: x | R84: FALSE | S84: TRUE | T84: 45887 | U84: Waiting for Wash basin and sensor tap
A85: Sanitation | B85: Flexiloo Vanity | C85: FLX.VA.096 | D85: Vanity | E85: 10 | F85: TRUE | G85: TRUE | H85: TRUE | I85: x | J85: TRUE | K85: TRUE | L85: TRUE | M85: x | N85: TRUE | O85: TRUE | P85: x | Q85: x | R85: FALSE | S85: TRUE
A86: Sanitation | B86: Flexiloo Vanity | C86: FLX.VA.097 | D86: Vanity | E86: 11 | F86: TRUE | G86: TRUE | H86: TRUE | I86: x | J86: TRUE | K86: TRUE | L86: TRUE | M86: x | N86: TRUE | O86: TRUE | P86: x | Q86: x | R86: FALSE | S86: TRUE
A87: Sanitation | B87: Flexiloo Vanity | C87: FLX.VA.098 | D87: Vanity | E87: 12 | F87: TRUE | G87: TRUE | H87: TRUE | I87: x | J87: TRUE | K87: TRUE | L87: TRUE | M87: x | N87: TRUE | O87: TRUE | P87: x | Q87: x | R87: FALSE | S87: TRUE
A88: Sanitation | B88: Flexiloo Vanity | C88: FLX.VA.099 | D88: Vanity | E88: 13 | F88: TRUE | G88: TRUE | H88: TRUE | I88: x | J88: TRUE | K88: TRUE | L88: TRUE | M88: x | N88: TRUE | O88: TRUE | P88: x | Q88: x | R88: FALSE | S88: TRUE
A89: Sanitation | B89: Flexiloo Vanity | C89: FLX.VA.100 | D89: Vanity | E89: 14 | F89: TRUE | G89: TRUE | H89: TRUE | I89: x | J89: TRUE | K89: TRUE | L89: TRUE | M89: x | N89: TRUE | O89: TRUE | P89: x | Q89: x | R89: FALSE | S89: TRUE
A90: Sanitation | B90: Flexiloo Vanity | C90: FLX.VA.101 | D90: Vanity | E90: 15 | F90: TRUE | G90: TRUE | H90: TRUE | I90: x | J90: TRUE | K90: TRUE | L90: TRUE | M90: x | N90: TRUE | O90: TRUE | P90: x | Q90: x | R90: FALSE | S90: TRUE
A91: Sanitation | B91: Flexiloo Vanity | C91: FLX.VA.102 | D91: Vanity | E91: 16 | F91: TRUE | G91: TRUE | H91: TRUE | I91: x | J91: TRUE | K91: TRUE | L91: TRUE | M91: x | N91: TRUE | O91: TRUE | P91: x | Q91: x | R91: FALSE | S91: TRUE
A92: Sanitation | B92: Flexiloo Vanity | C92: FLX.VA.103 | D92: Vanity | E92: 17 | F92: TRUE | G92: TRUE | H92: TRUE | I92: x | J92: TRUE | K92: TRUE | L92: TRUE | M92: x | N92: TRUE | O92: TRUE | P92: x | Q92: x | R92: FALSE | S92: TRUE
A93: Sanitation | B93: Flexiloo Vanity | C93: FLX.VA.104 | D93: Vanity | E93: 18 | F93: TRUE | G93: TRUE | H93: TRUE | I93: x | J93: TRUE | K93: TRUE | L93: TRUE | M93: x | N93: TRUE | O93: TRUE | P93: x | Q93: x | R93: FALSE | S93: TRUE
A94: Sanitation | B94: Flexiloo Vanity | C94: FLX.VA.105 | D94: Vanity | E94: 19 | F94: FALSE | G94: FALSE | H94: FALSE | I94: x | J94: FALSE | K94: FALSE | L94: FALSE | M94: x | N94: FALSE | O94: FALSE | P94: x | Q94: x | R94: FALSE | S94: FALSE
A95: Sanitation | B95: Flexiloo Vanity | C95: FLX.VA.106 | D95: Vanity | E95: FALSE | F95: FALSE | G95: FALSE | H95: FALSE | I95: FALSE | J95: FALSE | K95: FALSE | L95: FALSE | M95: FALSE | N95: FALSE | O95: FALSE | P95: FALSE | Q95: FALSE | R95: FALSE | S95: FALSE
A97: Sanitation | B97: Flexiloo POD | C97: FLX.EAWC.005 | D97: POD | E97: 1 | F97: TRUE | G97: FALSE | H97: FALSE | I97: x | J97: FALSE | K97: FALSE | L97: FALSE | M97: x | N97: FALSE | O97: FALSE | P97: x | Q97: x | R97: FALSE | S97: FALSE
A98: Sanitation | B98: Flexiloo POD | C98: FLX.EAWC.006 | D98: POD | E98: 2 | F98: TRUE | G98: FALSE | H98: FALSE | I98: x | J98: FALSE | K98: FALSE | L98: FALSE | M98: x | N98: FALSE | O98: FALSE | P98: x | Q98: x | R98: FALSE | S98: FALSE

Sheet Portaloo
A1: Category | B1: Spec | C1: Type | D1: Plant No. | E1: Interior fittings | F1: Flush lever | G1: Door lock | H1: Branding | I1: Comments
A2: Portaloo | B2: Disabled Portaloo | C2: Portaloo | D2: DA.PL.57 | E2: FALSE | F2: FALSE | G2: FALSE | H2: FALSE | I2: No inspection
A3: Portaloo | B3: Disabled Portaloo | C3: Portaloo | D3: DA.PL.58 | E3: FALSE | F3: FALSE | G3: FALSE | H3: FALSE | I3: No inspection
A4: Portaloo | B4: Portaloo | C4: Portaloo | D4: PL.03 | E4: TRUE | F4: TRUE | G4: TRUE | H4: FALSE | I4: [2026-03-30] Inpection done by Anto | By: Anto
A5: Portaloo | B5: Portaloo | C5: Portaloo | D5: PL.09 | E5: FALSE | F5: FALSE | G5: FALSE | H5: FALSE | I5: No inspection
A6: Portaloo | B6: Portaloo | C6: Portaloo | D6: PL.100 | E6: FALSE | F6: FALSE | G6: FALSE | H6: FALSE | I6: No inspection
A7: Portaloo | B7: Portaloo | C7: Portaloo | D7: PL.101 | E7: FALSE | F7: FALSE | G7: FALSE | H7: FALSE | I7: No inspection
A8: Portaloo | B8: Portaloo | C8: Portaloo | D8: PL.102 | E8: FALSE | F8: FALSE | G8: FALSE | H8: FALSE | I8: No inspection
A9: Portaloo | B9: Portaloo | C9: Portaloo | D9: PL.105 | E9: FALSE | F9: FALSE | G9: FALSE | H9: FALSE | I9: No inspection
A10: Portaloo | B10: Portaloo | C10: Portaloo | D10: PL.106 | E10: FALSE | F10: FALSE | G10: FALSE | H10: FALSE | I10: No inspection
A11: Portaloo | B11: Portaloo | C11: Portaloo | D11: PL.107 | E11: TRUE | F11: TRUE | G11: TRUE | H11: FALSE | I11: [2026-03-30] | By: calo.lategan@allaith.com
A12: Portaloo | B12: Portaloo | C12: Portaloo | D12: PL.108 | E12: FALSE | F12: FALSE | G12: FALSE | H12: FALSE | I12: No inspection
A13: Portaloo | B13: Portaloo | C13: Portaloo | D13: PL.109 | E13: FALSE | F13: FALSE | G13: FALSE | H13: FALSE | I13: No inspection
... A109: Portaloo | B109: Portaloo | C109: Portaloo | D109: PL.99 | E109: FALSE | F109: FALSE | G109: FALSE | H109: FALSE | I109: No inspection

Sheet Ezgo
A1: TYPE | B1: BRAND | C1: SPEC | D1: PLANT NO. | E1: PARTS ORDERED | F1: PARTS RECEIVED | G1: PARTS INSTALLED | H1: TYRES | I1: BATTERIES | J1: BRAKE CABLE ASSY | K1: BRAKE DRUM | L1: SPRING BUSH | M1: SPEED SENSOR | N1: HEAD LIGHT ASSY | O1: HORN SWITCH | P1: STEERING BOX ASSY | Q1: WINDSHIELD | R1: ACCELERATOR PEDAL ASSY | S1: FRONT BUMPER | T1: HORN | U1: KINGPIN | V1: FRONT ARM BUSH | W1: REAR AXLE | X1: TOW HITCH | Y1: MUD GUARD LH | Z1: FRONT BUMPER GUARD | AA1: CANOPY | AB1: BATTERY CABLE | AC1: TELEMATICS | AD1: POLISH | AE1: COMMENTS
A2: Golf Buggy | B2: EZGO - Abdullah | C2: 4 seater | D2: GB.4.112 | E2: FALSE | F2: FALSE | G2: FALSE | AC2: FALSE | AD2: FALSE
A3: Golf Buggy | B3: EZGO - Security | C3: 4 seater | D3: GB.4.118 | E3: FALSE | F3: FALSE | G3: FALSE | AC3: FALSE | AD3: FALSE
A4: Golf Buggy | B4: EZGO - Gold | C4: 4 seater | D4: GB.4.82 | E4: TRUE | F4: FALSE | G4: FALSE | O4: 1 | T4: 1 | AC4: FALSE | AD4: FALSE
A5: Golf Buggy | B5: Golf Buggy - Carryall 700 | C5: Van | D5: CAB.01 | E5: FALSE | F5: FALSE | G5: FALSE | AC5: FALSE | AD5: FALSE
A6: Golf Buggy | B6: Golf Buggy - Carryall 700 | C6: Van | D6: CAB.02 | E6: FALSE | F6: FALSE | G6: FALSE | AC6: FALSE | AD6: FALSE
A7: Golf Buggy | B7: EZGO | C7: 4 seater | D7: GB.4.10 | E7: TRUE | F7: FALSE | G7: FALSE | J7: 1 | L7: 4 | AC7: FALSE | AD7: FALSE
A8: Golf Buggy | B8: EZGO | C8: 4 seater | D8: GB.4.11 | E8: TRUE | F8: FALSE | G8: FALSE | K8: 2 | N8: 1 | AC8: FALSE | AD8: FALSE
A9: Golf Buggy | B9: EZGO | C9: 4 seater | D9: GB.4.113 | E9: TRUE | F9: FALSE | G9: FALSE | L9: 4 NO | Q9: 1 NO | S9: 1 NO | AC9: FALSE | AD9: FALSE
A10: Golf Buggy | B10: EZGO | C10: 4 seater | D10: GB.4.114 | E10: TRUE | F10: FALSE | G10: FALSE | M10: 1 NO | AC10: FALSE | AD10: FALSE
A11: Golf Buggy | B11: EZGO | C11: 4 seater | D11: GB.4.119 | E11: FALSE | F11: FALSE | G11: FALSE | AC11: FALSE | AD11: FALSE
A12: Golf Buggy | B12: EZGO | C12: 4 seater | D12: GB.4.12 | E12: TRUE | F12: FALSE | G12: FALSE | L12: 4 | O12: 1 | P12: 1 | Q12: 1 | AC12: FALSE | AD12: FALSE
A13: Golf Buggy | B13: EZGO | C13: 4 seater | D13: GB.4.122 | E13: FALSE | F13: FALSE | G13: FALSE | AC13: FALSE | AD13: FALSE
A14: Golf Buggy | B14: EZGO | C14: 4 seater | D14: GB.4.128 | E14: FALSE | F14: FALSE | G14: FALSE | AC14: FALSE | AD14: FALSE
A15: Golf Buggy | B15: EZGO | C15: 4 seater | D15: GB.4.129 | E15: FALSE | F15: FALSE | G15: FALSE | AC15: FALSE | AD15: FALSE
A16: Golf Buggy | B16: EZGO | C16: 4 seater | D16: GB.4.13 | E16: TRUE | F16: FALSE | G16: FALSE | Q16: 1 | R16: 1 | AC16: FALSE | AD16: FALSE
A17: Golf Buggy | B17: EZGO | C17: 4 seater | D17: GB.4.130 | E17: FALSE | F17: FALSE | G17: FALSE | AC17: FALSE | AD17: FALSE
A18: Golf Buggy | B18: EZGO | C18: 4 seater | D18: GB.4.132 | E18: FALSE | F18: FALSE | G18: FALSE | AC18: FALSE | AD18: FALSE
A19: Golf Buggy | B19: EZGO | C19: 4 seater | D19: GB.4.134 | E19: FALSE | F19: FALSE | G19: FALSE | AC19: FALSE | AD19: FALSE
A20: Golf Buggy | B20: EZGO | C20: 4 seater | D20: GB.4.139 | E20: FALSE | F20: FALSE | G20: FALSE | AC20: FALSE | AD20: FALSE
A21: Golf Buggy | B21: EZGO | C21: 4 seater | D21: GB.4.143 | E21: FALSE | F21: FALSE | G21: FALSE | AC21: FALSE | AD21: FALSE
A22: Golf Buggy | B22: EZGO | C22: 4 seater | D22: GB.4.144 | E22: FALSE | F22: FALSE | G22: FALSE | AC22: FALSE | AD22: FALSE
A23: Golf Buggy | B23: EZGO | C23: 4 seater | D23: GB.4.15 | E23: TRUE | F23: FALSE | G23: FALSE | L23: 4 | AC23: FALSE | AD23: FALSE
A24: Golf Buggy | B24: EZGO | C24: 4 seater | D24: GB.4.17 | E24: TRUE | F24: FALSE | G24: FALSE | L24: 4 | P24: 1 | Q24: 1 | S24: 1 | AC24: FALSE | AD24: FALSE
A25: Golf Buggy | B25: EZGO | C25: 4 seater | D25: GB.4.19 | E25: TRUE | F25: FALSE | G25: FALSE | Q25: 1 | AC25: FALSE | AD25: FALSE
A26: Golf Buggy | B26: EZGO | C26: 4 seater | D26: GB.4.27 | E26: FALSE | F26: FALSE | G26: FALSE | AC26: FALSE | AD26: FALSE
A27: Golf Buggy | B27: EZGO | C27: 4 seater | D27: GB.4.52 | E27: TRUE | F27: FALSE | G27: FALSE | L27: 4 | O27: 1 | Q27: 1 | S27: 1 | AC27: FALSE | AD27: FALSE
A28: Golf Buggy | B28: EZGO | C28: 4 seater | D28: GB.4.58 | E28: TRUE | F28: FALSE | G28: FALSE | L28: 4 | Q28: 1 | R28: 1 | AC28: FALSE | AD28: FALSE
A29: Golf Buggy | B29: EZGO | C29: 4 seater | D29: GB.4.59 | E29: TRUE | F29: FALSE | G29: FALSE | L29: 4 | O29: 1 | T29: 1 | AC29: FALSE | AD29: FALSE
A30: Golf Buggy | B30: EZGO | C30: 4 seater | D30: GB.4.60 | E30: TRUE | F30: FALSE | G30: FALSE | Q30: 1 | AC30: FALSE | AD30: FALSE
A31: Golf Buggy | B31: EZGO | C31: 4 seater | D31: GB.4.61 | E31: TRUE | F31: FALSE | G31: FALSE | S31: 1 | U31: 8 | AC31: FALSE | AD31: FALSE
A32: Golf Buggy | B32: EZGO | C32: 4 seater | D32: GB.4.62 | E32: TRUE | F32: FALSE | G32: FALSE | L32: 4 | O32: 1 | P32: 1 | T32: 1 | AC32: FALSE | AD32: FALSE
A33: Golf Buggy | B33: EZGO | C33: 4 seater | D33: GB.4.63 | E33: FALSE | F33: FALSE | G33: FALSE | AC33: FALSE | AD33: FALSE
A34: Golf Buggy | B34: EZGO | C34: 4 seater | D34: GB.4.64 | E34: TRUE | F34: FALSE | G34: FALSE | L34: 4 | O34: 1 | T34: 1 | AC34: FALSE | AD34: FALSE
A35: Golf Buggy | B35: EZGO | C35: 4 seater | D35: GB.4.65 | E35: TRUE | F35: FALSE | G35: FALSE | L35: 4 | O35: 1 | T35: 1 | U35: 8 | AB35: 5 | AC35: FALSE | AD35: FALSE
A36: Golf Buggy | B36: EZGO | C36: 4 seater | D36: GB.4.66 | E36: FALSE | F36: FALSE | G36: FALSE | AC36: FALSE | AD36: FALSE
A37: Golf Buggy | B37: EZGO | C37: 4 seater | D37: GB.4.67 | E37: TRUE | F37: FALSE | G37: FALSE | Q37: 1 | AA37: 1 | AC37: FALSE | AD37: FALSE
A38: Golf Buggy | B38: EZGO | C38: 4 seater | D38: GB.4.68 | E38: TRUE | F38: FALSE | G38: FALSE | L38: 4 | AC38: FALSE | AD38: FALSE
A39: Golf Buggy | B39: EZGO | C39: 4 seater | D39: GB.4.69 | E39: TRUE | F39: FALSE | G39: FALSE | L39: 4 | Q39: 1 | AC39: FALSE | AD39: FALSE
A40: Golf Buggy | B40: EZGO | C40: 4 seater | D40: GB.4.70 | E40: FALSE | F40: FALSE | G40: FALSE | AC40: FALSE | AD40: FALSE | AE40: Only labour charge on PO
A41: Golf Buggy | B41: EZGO | C41: 4 seater | D41: GB.4.71 | E41: TRUE | F41: FALSE | G41: FALSE | L41: 4 | AC41: FALSE | AD41: FALSE
A42: Golf Buggy | B42: EZGO | C42: 4 seater | D42: GB.4.72 | E42: TRUE | F42: FALSE | G42: FALSE | L42: 4 | Q42: 1 | V42: 4 | AC42: FALSE | AD42: FALSE
A43: Golf Buggy | B43: EZGO | C43: 4 seater | D43: GB.4.73 | E43: TRUE | F43: FALSE | G43: FALSE | L43: 4 | O43: 1 | T43: 1 | AC43: FALSE | AD43: FALSE
A44: Golf Buggy | B44: EZGO | C44: 4 seater | D44: GB.4.74 | E44: TRUE | F44: FALSE | G44: FALSE | O44: 1 | P44: 1 | T44: 1 | AA44: 1 | AC44: FALSE | AD44: FALSE
A45: Golf Buggy | B45: EZGO | C45: 4 seater | D45: GB.4.75 | E45: TRUE | F45: FALSE | G45: FALSE | L45: 4 | O45: 1 | T45: 1 | AC45: FALSE | AD45: FALSE
A46: Golf Buggy | B46: EZGO | C46: 4 seater | D46: GB.4.76 | E46: TRUE | F46: FALSE | G46: FALSE | L46: 4 | Q46: 1 | AC46: FALSE | AD46: FALSE
A47: Golf Buggy | B47: EZGO | C47: 4 seater | D47: GB.4.77 | E47: TRUE | F47: FALSE | G47: FALSE | L47: 4 | Q47: 1 | AC47: FALSE | AD47: FALSE
A48: Golf Buggy | B48: EZGO | C48: 4 seater | D48: GB.4.78 | E48: TRUE | F48: FALSE | G48: FALSE | L48: 4 | O48: 1 | T48: 1 | AC48: FALSE | AD48: FALSE
A49: Golf Buggy | B49: EZGO | C49: 4 seater | D49: GB.4.79 | E49: TRUE | F49: FALSE | G49: FALSE | L49: 4 | O49: 1 | S49: 1 | T49: 1 | AC49: FALSE | AD49: FALSE
A50: Golf Buggy | B50: EZGO | C50: 4 seater | D50: GB.4.80 | E50: TRUE | F50: FALSE | G50: FALSE | O50: 1 | Q50: 1 | T50: 1 | AC50: FALSE | AD50: FALSE
A51: Golf Buggy | B51: EZGO | C51: 4 seater | D51: GB.4.81 | E51: TRUE | F51: FALSE | G51: FALSE | L51: 4 | O51: 1 | T51: 1 | AC51: FALSE | AD51: FALSE
A52: Golf Buggy | B52: EZGO | C52: 4 seater | D52: GB.4.83 | E52: TRUE | F52: FALSE | G52: FALSE | P52: 1 | Q52: 1 | AC52: FALSE | AD52: FALSE
A53: Golf Buggy | B53: EZGO | C53: 4 seater | D53: GB.4.84 | E53: TRUE | F53: FALSE | G53: FALSE | O53: 1 | P53: 1 | T53: 1 | U53: 8 | AC53: FALSE | AD53: FALSE
A54: Golf Buggy | B54: EZGO | C54: 4 seater | D54: GB.4.85 | E54: TRUE | F54: FALSE | G54: FALSE | L54: 4 | O54: 1 | P54: 1 | Q54: 1 | T54: 1 | AC54: FALSE | AD54: FALSE
A55: Golf Buggy | B55: EZGO | C55: 4 seater | D55: GB.4.86 | E55: TRUE | F55: FALSE | G55: FALSE | L55: 4 | O55: 1 | T55: 1 | AC55: FALSE | AD55: FALSE
A56: Golf Buggy | B56: EZGO | C56: 4 seater | D56: GB.4.87 | E56: TRUE | F56: FALSE | G56: FALSE | L56: 4 | AC56: FALSE | AD56: FALSE
A57: Golf Buggy | B57: EZGO | C57: 4 seater | D57: GB.4.88 | E57: TRUE | F57: FALSE | G57: FALSE | L57: 4 | O57: 1 | P57: 1 | T57: 1 | AC57: FALSE | AD57: FALSE
A58: Golf Buggy | B58: EZGO | C58: 4 seater | D58: GB.4.89 | E58: TRUE | F58: FALSE | G58: FALSE | L58: 4 | AC58: FALSE | AD58: FALSE
A59: Golf Buggy | B59: EZGO | C59: 4 seater | D59: GB.4.90 | E59: TRUE | F59: FALSE | G59: FALSE | O59: 1 | T59: 1 | AC59: FALSE | AD59: FALSE
A60: Golf Buggy | B60: EZGO | C60: 4 seater | D60: GB.4.91 | E60: TRUE | F60: FALSE | G60: FALSE | O60: 1 | P60: 1 | T60: 1 | AC60: FALSE | AD60: FALSE
A61: Golf Buggy | B61: EZGO | C61: 4 seater | D61: GB.4.92 | E61: TRUE | F61: FALSE | G61: FALSE | O61: 1 | Q61: 1 | T61: 1 | AC61: FALSE | AD61: FALSE
A62: Golf Buggy | B62: EZGO | C62: 6 seater | D62: GB.6.98 | E62: FALSE | F62: FALSE | G62: FALSE | AC62: FALSE | AD62: FALSE
A63: Golf Buggy | B63: EZGO | C63: 6 seater | D63: GB.6.100 | E63: TRUE | F63: FALSE | G63: FALSE | L63: 4 | Y63: 1 | Z63: 1 | AC63: FALSE | AD63: FALSE
A64: Golf Buggy | B64: EZGO | C64: 6 seater | D64: GB.6.102 | E64: FALSE | F64: FALSE | G64: FALSE | AC64: FALSE | AD64: FALSE
A65: Golf Buggy | B65: EZGO | C65: 6 seater | D65: GB.6.101 | E65: TRUE | F65: FALSE | G65: FALSE | J65: 1 | AC65: FALSE | AD65: FALSE
A66: Golf Buggy | B66: EZGO | C66: 6 seater | D66: GB.6.103 | E66: FALSE | F66: FALSE | G66: FALSE | AC66: FALSE | AD66: FALSE
A67: Golf Buggy | B67: EZGO | C67: 6 seater | D67: GB.6.104 | E67: FALSE | F67: FALSE | G67: FALSE | AC67: FALSE | AD67: FALSE
A68: Golf Buggy | B68: EZGO | C68: 6 seater | D68: GB.6.105 | E68: TRUE | F68: FALSE | G68: FALSE | J68: 1 | L68: 4 | N68: 2 | AC68: FALSE | AD68: FALSE
A69: Golf Buggy | B69: EZGO | C69: 6 seater | D69: GB.6.106 | E69: TRUE | F69: FALSE | G69: FALSE | L69: 4 | Q69: 1 | W69: 1 | AC69: FALSE | AD69: FALSE
A70: Golf Buggy | B70: EZGO | C70: 6 seater | D70: GB.6.107 | E70: FALSE | F70: FALSE | G70: FALSE | AC70: FALSE | AD70: FALSE
A71: Golf Buggy | B71: EZGO | C71: 6 seater | D71: GB.6.108 | E71: TRUE | F71: FALSE | G71: FALSE | L71: 4 | AC71: FALSE | AD71: FALSE
A72: Golf Buggy | B72: EZGO | C72: 6 seater | D72: GB.6.109 | E72: TRUE | F72: FALSE | G72: FALSE | L72: 4 | AC72: FALSE | AD72: FALSE
A73: Golf Buggy | B73: EZGO | C73: 6 seater | D73: GB.6.110 | E73: TRUE | F73: FALSE | G73: FALSE | L73: 4 | AC73: FALSE | AD73: FALSE
A74: Golf Buggy | B74: EZGO | C74: 6 seater | D74: GB.6.111 | E74: FALSE | F74: FALSE | G74: FALSE | AC74: FALSE | AD74: FALSE
A75: Golf Buggy | B75: EZGO | C75: 6 seater | D75: GB.6.172 | E75: FALSE | F75: FALSE | G75: FALSE | AC75: FALSE | AD75: FALSE
A76: Golf Buggy | B76: EZGO | C76: 6 seater | D76: GB.6.180 | E76: FALSE | F76: FALSE | G76: FALSE | AC76: FALSE | AD76: FALSE
A77: Golf Buggy | B77: EZGO | C77: 6 seater | D77: GB.6.20 | E77: FALSE | F77: FALSE | G77: FALSE | AC77: FALSE | AD77: FALSE
A78: Golf Buggy | B78: EZGO | C78: 6 seater | D78: GB.6.21 | E78: FALSE | F78: FALSE | G78: FALSE | AC78: FALSE | AD78: FALSE
A79: Golf Buggy | B79: EZGO | C79: 6 seater | D79: GB.6.22 | E79: FALSE | F79: FALSE | G79: FALSE | AC79: FALSE | AD79: FALSE
A80: Golf Buggy | B80: EZGO | C80: 6 seater | D80: GB.6.23 | E80: TRUE | F80: FALSE | G80: FALSE | L80: 4 | AC80: FALSE | AD80: FALSE
A81: Golf Buggy | B81: EZGO | C81: 6 seater | D81: GB.6.24 | E81: FALSE | F81: FALSE | G81: FALSE | AC81: FALSE | AD81: FALSE
A82: Golf Buggy | B82: EZGO | C82: 6 seater | D82: GB.6.25 | E82: FALSE | F82: FALSE | G82: FALSE | AC82: FALSE | AD82: FALSE
A83: Golf Buggy | B83: EZGO | C83: 6 seater | D83: GB.6.93 | E83: TRUE | F83: FALSE | G83: FALSE | S83: 1 | Z83: 1 | AC83: FALSE | AD83: FALSE
A84: Golf Buggy | B84: EZGO | C84: 6 seater | D84: GB.6.95 | E84: FALSE | F84: FALSE | G84: FALSE | AC84: FALSE | AD84: FALSE
A85: Golf Buggy | B85: EZGO | C85: 6 seater | D85: GB.6.96 | E85: FALSE | F85: FALSE | G85: FALSE | AC85: FALSE | AD85: FALSE
A86: Golf Buggy | B86: EZGO | C86: 6 seater | D86: GB.6.97 | E86: TRUE | F86: FALSE | G86: FALSE | O86: 1 | P86: 1 | AC86: FALSE | AD86: FALSE
A87: Golf Buggy | B87: EZGO | C87: 6 seater | D87: GB.6.99 | E87: TRUE | F87: FALSE | G87: FALSE | Z87: 1 | AC87: FALSE | AD87: FALSE
A88: Golf Buggy | B88: EZGO - Ambulance | C88: 6 seater | D88: GB.6.56 | E88: TRUE | F88: FALSE | G88: FALSE | W88: 1 | X88: 4 | AC88: FALSE | AD88: FALSE
A89: Golf Buggy | B89: EZGO - Ambulance | C89: 6 seater | D89: GB.6.57 | E89: TRUE | F89: FALSE | G89: FALSE | L89: 4 | Y89: 1 | AC89: FALSE | AD89: FALSE
A90: Golf Buggy | B90: EZGO - Ambulance | C90: 6 seater | D90: GB.6.94 | E90: FALSE | F90: FALSE | G90: FALSE | AC90: FALSE | AD90: FALSE

Sheet Clubcar
A1: TYPE | B1: BRAND | C1: SPEC | D1: PLANT NO. | E1: INSPECTION June '23 | F1: PARTS ORDERED | G1: PARTS RECEIVED | H1: PARTS INSTALLED | I1: TYRES | J1: BATTERIES | K1: TELEMATICS | L1: POLISH | M1: COMMENTS
A2: Golf Buggy | B2: Club Car | C2: 4 seater | D2: GBC.4.145 | E2: TRUE | F2: FALSE | G2: FALSE | H2: FALSE | I2: FALSE | J2: FALSE | K2: FALSE | L2: FALSE
A3: Golf Buggy | B3: Club Car | C3: 4 seater | D3: GBC.4.146 | E3: TRUE | F3: FALSE | G3: FALSE | H3: FALSE | I3: FALSE | J3: FALSE | K3: FALSE | L3: FALSE
A4: Golf Buggy | B4: Club Car | C4: 4 seater | D4: GBC.4.147 | E4: TRUE | F4: FALSE | G4: FALSE | H4: FALSE | I4: FALSE | J4: FALSE | K4: FALSE | L4: FALSE
A5: Golf Buggy | B5: Club Car | C5: 4 seater | D5: GBC.4.148 | E5: TRUE | F5: FALSE | G5: FALSE | H5: FALSE | I5: FALSE | J5: FALSE | K5: FALSE | L5: FALSE
A6: Golf Buggy | B6: Club Car | C6: 4 seater | D6: GBC.4.149 | E6: TRUE | F6: FALSE | G6: FALSE | H6: FALSE | I6: FALSE | J6: FALSE | K6: FALSE | L6: FALSE
A7: Golf Buggy | B7: Club Car | C7: 4 seater | D7: GBC.4.150 | E7: TRUE | F7: FALSE | G7: FALSE | H7: FALSE | I7: FALSE | J7: FALSE | K7: FALSE | L7: FALSE
A8: Golf Buggy | B8: Club Car | C8: 4 seater | D8: GBC.4.151 | E8: TRUE | F8: FALSE | G8: FALSE | H8: FALSE | I8: FALSE | J8: FALSE | K8: FALSE | L8: FALSE
A9: Golf Buggy | B9: Club Car | C9: 4 seater | D9: GBC.4.152 | E9: TRUE | F9: FALSE | G9: FALSE | H9: FALSE | I9: FALSE | J9: FALSE | K9: FALSE | L9: FALSE
A10: Golf Buggy | B10: Club Car | C10: 4 seater | D10: GBC.4.153 | E10: TRUE | F10: FALSE | G10: FALSE | H10: FALSE | I10: FALSE | J10: FALSE | K10: FALSE | L10: FALSE
A11: Golf Buggy | B11: Club Car | C11: 4 seater | D11: GBC.4.154 | E11: TRUE | F11: FALSE | G11: FALSE | H11: FALSE | I11: FALSE | J11: FALSE | K11: FALSE | L11: FALSE
A12: Golf Buggy | B12: Club Car | C12: 4 seater | D12: GBC.4.155 | E12: TRUE | F12: FALSE | G12: FALSE | H12: FALSE | I12: FALSE | J12: FALSE | K12: FALSE | L12: FALSE
A13: Golf Buggy | B13: Club Car | C13: 4 seater | D13: GBC.4.156 | E13: TRUE | F13: FALSE | G13: FALSE | H13: FALSE | I13: FALSE | J13: FALSE | K13: FALSE | L13: FALSE
... A95: Golf Buggy | B95: Club Car | C95: 6 seater | D95: GBC.6.180 | E95: TRUE | F95: FALSE | G95: FALSE | H95: FALSE | I95: FALSE | J95: FALSE | K95: FALSE | L95: FALSE

Sheet Polaris
A1: Make | B1: Type | C1: Plant no. | D1: Problems | E1: Work to be done | F1: Cost
A2: Polaris | B2: Gator | C2: IRL.13
A3: Polaris | B3: Gator | C3: IRL.14
A4: Polaris | B4: Mule-ranger Crew M.s | C4: IRL.18
A5: Polaris | B5: Mule-ranger Crew F.s. | C5: IRL.20
A6: Polaris | B6: Mule-ranger Crew F.s. | C6: IRL.23
A7: Polaris | B7: Mule-ranger Crew M.s | C7: IRL.25
A8: Polaris | B8: Mule-ranger Crew M.s | C8: IRL.29
A9: Polaris | B9: Mule-ranger Crew M.s | C9: IRL.31
A10: Polaris | B10: Mule-ranger Crew M.s | C10: IRL.34
A11: Polaris | B11: Mule-ranger Crew M.s | C11: IRL.35
A12: Polaris | B12: Mule-ranger Crew M.s | C12: IRL.36
A13: Polaris | B13: Petrol Mule 2 Seater | C13: IRL.40
... A22: Polaris | B22: Electric Mule 2 Seater | C22: IRL.49

Sheet Kawasaki
A1: Kawasaki | B1: Gator | D1: IRL.01
A2: Kawasaki | B2: Gator | D2: IRL.02
A3: Kawasaki | B3: Gator | D3: IRL.03
A4: Kawasaki | B4: Gator | D4: IRL.04
A5: Kawasaki | B5: Gator | D5: IRL.05
A6: Kawasaki | B6: Gator | D6: IRL.06
A7: Kawasaki | B7: Gator | D7: IRL.07
A8: Kawasaki | B8: Gator | D8: IRL.08
A9: Kawasaki | B9: Gator | D9: IRL.09
A10: Kawasaki | B10: Gator | D10: IRL.10
A11: Kawasaki | B11: Gator | D11: IRL.11
A12: Kawasaki | B12: Gator | D12: IRL.12

Sheet New Flatpack
A1: Category | B1: Description | C1: Plant number | D1: Size | E1: Quantity | F1: Floor | G1: Column | H1: Roof | I1: Plan panel | J1: window panel | K1: Window curtain | L1: Door Panel | M1: Electric DB | N1: Socket | O1: Lighting | P1: Assembly
A2: Cabin | B2: Flat pack | C2: OPO.L.20.107 | D2: 20x8 | E2: 1 | F2: FALSE | G2: FALSE | H2: FALSE | I2: FALSE | J2: FALSE | K2: FALSE | L2: FALSE | M2: FALSE | N2: FALSE | O2: FALSE | P2: FALSE
A3: Cabin | B3: Flat pack | C3: OPO.L.20.108 | D3: 20x8 | E3: 2 | F3: FALSE | G3: FALSE | H3: FALSE | I3: FALSE | J3: FALSE | K3: FALSE | L3: FALSE | M3: FALSE | N3: FALSE | O3: FALSE | P3: FALSE
A4: Cabin | B4: Flat pack | C4: OPO.L.20.109 | D4: 20x8 | E4: 3 | F4: FALSE | G4: FALSE | H4: FALSE | I4: FALSE | J4: FALSE | K4: FALSE | L4: FALSE | M4: FALSE | N4: FALSE | O4: FALSE | P4: FALSE
A5: Cabin | B5: Flat pack | C5: OPO.L.20.110 | D5: 20x8 | E5: 4 | F5: FALSE | G5: FALSE | H5: FALSE | I5: FALSE | J5: FALSE | K5: FALSE | L5: FALSE | M5: FALSE | N5: FALSE | O5: FALSE | P5: FALSE
A6: Cabin | B6: Flat pack | C6: OPO.L.20.111 | D6: 20x8 | E6: 5 | F6: FALSE | G6: FALSE | H6: FALSE | I6: FALSE | J6: FALSE | K6: FALSE | L6: FALSE | M6: FALSE | N6: FALSE | O6: FALSE | P6: FALSE
A7: Cabin | B7: Flat pack | C7: OPO.L.20.112 | D7: 20x8 | E7: 6 | F7: FALSE | G7: FALSE | H7: FALSE | I7: FALSE | J7: FALSE | K7: FALSE | L7: FALSE | M7: FALSE | N7: FALSE | O7: FALSE | P7: FALSE
A8: Cabin | B8: Flat pack | C8: OPO.L.20.113 | D8: 20x8 | E8: 7 | F8: FALSE | G8: FALSE | H8: FALSE | I8: FALSE | J8: FALSE | K8: FALSE | L8: FALSE | M8: FALSE | N8: FALSE | O8: FALSE | P8: FALSE
A9: Cabin | B9: Flat pack | C9: OPO.L.20.114 | D9: 20x8 | E9: 8 | F9: FALSE | G9: FALSE | H9: FALSE | I9: FALSE | J9: FALSE | K9: FALSE | L9: FALSE | M9: FALSE | N9: FALSE | O9: FALSE | P9: FALSE
A10: Cabin | B10: Flat pack | C10: OPO.L.20.115 | D10: 20x8 | E10: 9 | F10: FALSE | G10: FALSE | H10: FALSE | I10: FALSE | J10: FALSE | K10: FALSE | L10: FALSE | M10: FALSE | N10: FALSE | O10: FALSE | P10: FALSE
A11: Cabin | B11: Flat pack | C11: OPO.L.20.116 | D11: 20x8 | E11: 10 | F11: FALSE | G11: FALSE | H11: FALSE | I11: FALSE | J11: FALSE | K11: FALSE | L11: FALSE | M11: FALSE | N11: FALSE | O11: FALSE | P11: FALSE
A12: Cabin | B12: Flat pack | C12: OPO.L.20.117 | D12: 20x8 | E12: 11 | F12: FALSE | G12: FALSE | H12: FALSE | I12: FALSE | J12: FALSE | K12: FALSE | L12: FALSE | M12: FALSE | N12: FALSE | O12: FALSE | P12: FALSE
A13: Cabin | B13: Flat pack | C13: OPO.L.20.118 | D13: 20x8 | E13: 12 | F13: FALSE | G13: FALSE | H13: FALSE | I13: FALSE | J13: FALSE | K13: FALSE | L13: FALSE | M13: FALSE | N13: FALSE | O13: FALSE | P13: FALSE
... A103: Cabin | B103: Flat pack | C103: OPO.L.20.208 | D103: 20x9 | E103: 102 | F103: FALSE | G103: FALSE | H103: FALSE | I103: FALSE | J103: FALSE | K103: FALSE | L103: FALSE | M103: FALSE | N103: FALSE | O103: FALSE | P103: FALSE

Sheet Summary
A1: Activities | B1: Status | C1: Progress | D1: Comments
A2: Maintenance sheets for equipment category | B2: 0.75 | C2: =IFERROR(__xludf.DUMMYFUNCTION("IF(B2="""", """", SPARKLINE(B2, {""charttype"", ""bar""; ""max"", 1; ""color"", ""#434343""}))"),"") | D2: need to add progress %
A3: Lift permit for yard ops | B3: 0.1 | C3: =IFERROR(__xludf.DUMMYFUNCTION("IF(B3="""", """", SPARKLINE(B3, {""charttype"", ""bar""; ""max"", 1; ""color"", ""#009000""}))"),"") | D3: request made to HSE
A4: Vendor yard visits | B4: 0.5 | C4: =IFERROR(__xludf.DUMMYFUNCTION("IF(B4="""", """", SPARKLINE(B4, {""charttype"", ""bar""; ""max"", 1; ""color"", ""#009000""}))"),"") | D4: waiting for vendor to visit Battery testing-Clubcar-Logo lazer cut Duscaff-Counter tops flexiloo-(Seat embroidery-Checker plate floor buggy VIP)
A5: Ablution trailers - registration, branding, marketing | B5: 0.1 | C5: =IFERROR(__xludf.DUMMYFUNCTION("IF(B5="""", """", SPARKLINE(B5, {""charttype"", ""bar""; ""max"", 1; ""color"", ""#009000""}))"),"") | D5: , registration end April, branding, tow hitch, test load, commission, plant no.s (Waas & Hire Desk)
A6: Solar Lights | B6: 0 | C6: =IFERROR(__xludf.DUMMYFUNCTION("IF(B6="""", """", SPARKLINE(B6, {""charttype"", ""bar""; ""max"", 1; ""color"", ""#009000""}))"),"") | D6: , registration end April, branding, tow hitch, test load, commission, plant no.s (Waas & Hire Desk)
A7: 6 Seater Buggies | B7: 0 | C7: =IFERROR(__xludf.DUMMYFUNCTION("IF(B7="""", """", SPARKLINE(B7, {""charttype"", ""bar""; ""max"", 1; ""color"", ""#009000""}))"),"") | D7: , registration end April, branding, tow hitch, test load, commission, plant no.s (Waas & Hire Desk)
A8: Cabins-Ablutions - roofing | B8: 0.25 | C8: =IFERROR(__xludf.DUMMYFUNCTION("IF(B8="""", """", SPARKLINE(B8, {""charttype"", ""bar""; ""max"", 1; ""color"", ""#009000""}))"),"") | D8: Vendor came to inspect waiting on a quote for Roof repair or replace - look into seal between fibreglass and roof
A9: VIP Ablutions - refit | B9: 0.1 | C9: =IFERROR(__xludf.DUMMYFUNCTION("IF(B9="""", """", SPARKLINE(B9, {""charttype"", ""bar""; ""max"", 1; ""color"", ""#009000""}))"),"") | D9: Ablution stripped need to deside on final desighn-Get vendor for Marble wall panels , Marble floor vinyle ,Oak venior for the doors and wash basin panels.( same as the Photo.)
A10: Cabins-Ablutions - flooring | B10: 0.25 | C10: =IFERROR(__xludf.DUMMYFUNCTION("IF(B10="""", """", SPARKLINE(B10, {""charttype"", ""bar""; ""max"", 1; ""color"", ""#009000""}))"),"") | D10: started with mess halls
A11: Cabins-Ablutions - wall interiors | B11: 0.1 | C11: =IFERROR(__xludf.DUMMYFUNCTION("IF(B11="""", """", SPARKLINE(B11, {""charttype"", ""bar""; ""max"", 1; ""color"", ""#009000""}))"),"") | D11: supplier to provide options on panel finish
A12: Flexiloo - countertop corian refits and mirrors | B12: 0.1 | C12: =IFERROR(__xludf.DUMMYFUNCTION("IF(B12="""", """", SPARKLINE(B12, {""charttype"", ""bar""; ""max"", 1; ""color"", ""#009000""}))"),"") | D12: waiting for vendor for price on the corian we have recevide the price on plastic +-560 per squere
A13: EZGO - inspections, cost analysis, repairs, refit | B13: 0 | C13: =IFERROR(__xludf.DUMMYFUNCTION("IF(B13="""", """", SPARKLINE(B13, {""charttype"", ""bar""; ""max"", 1; ""color"", ""#009000""}))"),"")
A14: Buggy - telematics, fleet management | B14: 0 | C14: =IFERROR(__xludf.DUMMYFUNCTION("IF(B14="""", """", SPARKLINE(B14, {""charttype"", ""bar""; ""max"", 1; ""color"", ""#009000""}))"),"")
A15: Buggy Workshop refit - painting, workbench, QC, spares, battery management, record keeping | B15: 0.5 | C15: =IFERROR(__xludf.DUMMYFUNCTION("IF(B15="""", """", SPARKLINE(B15, {""charttype"", ""bar""; ""max"", 1; ""color"", ""#009000""}))"),"") | D15: work shop near complete
A16: Cabins-Ablutions - lighting | B16: 0 | C16: =IFERROR(__xludf.DUMMYFUNCTION("IF(B16="""", """", SPARKLINE(B16, {""charttype"", ""bar""; ""max"", 1; ""color"", ""#009000""}))"),"")
A17: Cabins-Ablutions - fixtures & fittings | B17: 0 | C17: =IFERROR(__xludf.DUMMYFUNCTION("IF(B17="""", """", SPARKLINE(B17, {""charttype"", ""bar""; ""max"", 1; ""color"", ""#009000""}))"),"")
A18: Cabins-Ablutions - fabrication & assembly | B18: 0 | C18: =IFERROR(__xludf.DUMMYFUNCTION("IF(B18="""", """", SPARKLINE(B18, {""charttype"", ""bar""; ""max"", 1; ""color"", ""#009000""}))"),"")
A19: QC checklists - Virtulab app | B19: 0 | C19: =IFERROR(__xludf.DUMMYFUNCTION("IF(B19="""", """", SPARKLINE(B19, {""charttype"", ""bar""; ""max"", 1; ""color"", ""#009000""}))"),"")
A20: Delivery-Collect Exit-Entry stock management | B20: 0 | C20: =IFERROR(__xludf.DUMMYFUNCTION("IF(B20="""", """", SPARKLINE(B20, {""charttype"", ""bar""; ""max"", 1; ""color"", ""#009000""}))"),"")
A21: Buggy Boxes | B21: 0 | C21: =IFERROR(__xludf.DUMMYFUNCTION("IF(B21="""", """", SPARKLINE(B21, {""charttype"", ""bar""; ""max"", 1; ""color"", ""#009000""}))"),"")
A22: Buggy Upholstery | B22: 0 | C22: =IFERROR(__xludf.DUMMYFUNCTION("IF(B22="""", """", SPARKLINE(B22, {""charttype"", ""bar""; ""max"", 1; ""color"", ""#009000""}))"),"")
A23: Random power points in golf cabins | B23: 0 | C23: =IFERROR(__xludf.DUMMYFUNCTION("IF(B23="""", """", SPARKLINE(B23, {""charttype"", ""bar""; ""max"", 1; ""color"", ""#009000""}))"),"")
A24: Light switches at exit for all lights when mess halls combined | B24: 0 | C24: =IFERROR(__xludf.DUMMYFUNCTION("IF(B24="""", """", SPARKLINE(B24, {""charttype"", ""bar""; ""max"", 1; ""color"", ""#009000""}))"),"")
A25: Flexiloo transport covers | B25: 0 | C25: =IFERROR(__xludf.DUMMYFUNCTION("IF(B25="""", """", SPARKLINE(B25, {""charttype"", ""bar""; ""max"", 1; ""color"", ""#009000""}))"),"")
A26: KAWASAKI - inspections, cost analysis, repairs, refit | B26: 0 | C26: =IFERROR(__xludf.DUMMYFUNCTION("IF(B26="""", """", SPARKLINE(B26, {""charttype"", ""bar""; ""max"", 1; ""color"", ""#009000""}))"),"")
A27: Buggy - spare parts and inventory management | B27: 0 | C27: =IFERROR(__xludf.DUMMYFUNCTION("IF(B27="""", """", SPARKLINE(B27, {""charttype"", ""bar""; ""max"", 1; ""color"", ""#009000""}))"),"")
A28: CLUB CARS - inspections, cost analysis, repairs, refit | B28: 0 | C28: =IFERROR(__xludf.DUMMYFUNCTION("IF(B28="""", """", SPARKLINE(B28, {""charttype"", ""bar""; ""max"", 1; ""color"", ""#009000""}))"),"")
A29: POLARIS - inspections, cost analysis, repairs, refit | B29: 0 | C29: =IFERROR(__xludf.DUMMYFUNCTION("IF(B29="""", """", SPARKLINE(B29, {""charttype"", ""bar""; ""max"", 1; ""color"", ""#009000""}))"),"")
A30: Cabins-Ablutions - acoustic panels | B30: 0 | C30: =IFERROR(__xludf.DUMMYFUNCTION("IF(B30="""", """", SPARKLINE(B30, {""charttype"", ""bar""; ""max"", 1; ""color"", ""#009000""}))"),"")
A31: Cabins-Ablutions - exterior & branding | B31: 0 | C31: =IFERROR(__xludf.DUMMYFUNCTION("IF(B31="""", """", SPARKLINE(B31, {""charttype"", ""bar""; ""max"", 1; ""color"", ""#009000""}))"),"")
A32: Picnic Bench branding | B32: 0 | C32: =IFERROR(__xludf.DUMMYFUNCTION("IF(B32="""", """", SPARKLINE(B32, {""charttype"", ""bar""; ""max"", 1; ""color"", ""#009000""}))"),"")
A33: Cabin trim see portakabin | B33: 0 | C33: =IFERROR(__xludf.DUMMYFUNCTION("IF(B33="""", """", SPARKLINE(B33, {""charttype"", ""bar""; ""max"", 1; ""color"", ""#009000""}))"),"")
A34: Buggy Garage - overhead charging and housekeeping | B34: 0 | C34: =IFERROR(__xludf.DUMMYFUNCTION("IF(B34="""", """", SPARKLINE(B34, {""charttype"", ""bar""; ""max"", 1; ""color"", ""#009000""}))"),"")
A35: SS Warehouse - housekeeping, shelving, stacking | B35: 0 | C35: =IFERROR(__xludf.DUMMYFUNCTION("IF(B35="""", """", SPARKLINE(B35, {""charttype"", ""bar""; ""max"", 1; ""color"", ""#009000""}))"),"")
A36: Flatpack Ass’y | B36: 0 | C36: =IFERROR(__xludf.DUMMYFUNCTION("IF(B36="""", """", SPARKLINE(B36, {""charttype"", ""bar""; ""max"", 1; ""color"", ""#009000""}))"),"")
A37: Cabins-Ablutions - window tinting | B37: 0 | C37: =IFERROR(__xludf.DUMMYFUNCTION("IF(B37="""", """", SPARKLINE(B37, {""charttype"", ""bar""; ""max"", 1; ""color"", ""#009000""}))"),"")
A38: Cabins-Ablutions - ac | B38: 0 | C38: =IFERROR(__xludf.DUMMYFUNCTION("IF(B38="""", """", SPARKLINE(B38, {""charttype"", ""bar""; ""max"", 1; ""color"", ""#009000""}))"),"")
A39: Buggy - pilot project body redesign | B39: 0 | C39: =IFERROR(__xludf.DUMMYFUNCTION("IF(B39="""", """", SPARKLINE(B39, {""charttype"", ""bar""; ""max"", 1; ""color"", ""#009000""}))"),"")
A40: Security Cabins Buggy repaint | B40: 0.1 | C40: =IFERROR(__xludf.DUMMYFUNCTION("IF(B40="""", """", SPARKLINE(B40, {""charttype"", ""bar""; ""max"", 1; ""color"", ""#009000""}))"),"") | D40: desighn recevide need to deside if happy
A41: Road Cone branding | B41: 0 | C41: =IFERROR(__xludf.DUMMYFUNCTION("IF(B41="""", """", SPARKLINE(B41, {""charttype"", ""bar""; ""max"", 1; ""color"", ""#009000""}))"),"")
A42: Flexi protective covers for transport | B42: 0 | C42: =IFERROR(__xludf.DUMMYFUNCTION("IF(B42="""", """", SPARKLINE(B42, {""charttype"", ""bar""; ""max"", 1; ""color"", ""#009000""}))"),"")
C43: =IFERROR(__xludf.DUMMYFUNCTION("IF(B43="""", """", SPARKLINE(B43, {""charttype"", ""bar""; ""max"", 1; ""color"", ""#009000""}))"),"")
C44: =IFERROR(__xludf.DUMMYFUNCTION("IF(B44="""", """", SPARKLINE(B44, {""charttype"", ""bar""; ""max"", 1; ""color"", ""#009000""}))"),"")
C45: =IFERROR(__xludf.DUMMYFUNCTION("IF(B45="""", """", SPARKLINE(B45, {""charttype"", ""bar""; ""max"", 1; ""color"", ""#009000""}))"),"")
C46: =IFERROR(__xludf.DUMMYFUNCTION("IF(B46="""", """", SPARKLINE(B46, {""charttype"", ""bar""; ""max"", 1; ""color"", ""#009000""}))"),"")
C47: =IFERROR(__xludf.DUMMYFUNCTION("IF(B47="""", """", SPARKLINE(B47, {""charttype"", ""bar""; ""max"", 1; ""color"", ""#009000""}))"),"")
C48: =IFERROR(__xludf.DUMMYFUNCTION("IF(B48="""", """", SPARKLINE(B48, {""charttype"", ""bar""; ""max"", 1; ""color"", ""#009000""}))"),"")
C49: =IFERROR(__xludf.DUMMYFUNCTION("IF(B49="""", """", SPARKLINE(B49, {""charttype"", ""bar""; ""max"", 1; ""color"", ""#009000""}))"),"")
C50: =IFERROR(__xludf.DUMMYFUNCTION("IF(B50="""", """", SPARKLINE(B50, {""charttype"", ""bar""; ""max"", 1; ""color"", ""#009000""}))"),"")
C51: =IFERROR(__xludf.DUMMYFUNCTION("IF(B51="""", """", SPARKLINE(B51, {""charttype"", ""bar""; ""max"", 1; ""color"", ""#009000""}))"),"")
C52: =IFERROR(__xludf.DUMMYFUNCTION("IF(B52="""", """", SPARKLINE(B52, {""charttype"", ""bar""; ""max"", 1; ""color"", ""#009000""}))"),"")
C53: =IFERROR(__xludf.DUMMYFUNCTION("IF(B53="""", """", SPARKLINE(B53, {""charttype"", ""bar""; ""max"", 1; ""color"", ""#009000""}))"),"")
C54: =IFERROR(__xludf.DUMMYFUNCTION("IF(B54="""", """", SPARKLINE(B54, {""charttype"", ""bar""; ""max"", 1; ""color"", ""#009000""}))"),"")
C55: =IFERROR(__xludf.DUMMYFUNCTION("IF(B55="""", """", SPARKLINE(B55, {""charttype"", ""bar""; ""max"", 1; ""color"", ""#009000""}))"),"")
C56: =IFERROR(__xludf.DUMMYFUNCTION("IF(B56="""", """", SPARKLINE(B56, {""charttype"", ""bar""; ""max"", 1; ""color"", ""#009000""}))"),"")
C57: =IFERROR(__xludf.DUMMYFUNCTION("IF(B57="""", """", SPARKLINE(B57, {""charttype"", ""bar""; ""max"", 1; ""color"", ""#009000""}))"),"")
C58: =IFERROR(__xludf.DUMMYFUNCTION("IF(B58="""", """", SPARKLINE(B58, {""charttype"", ""bar""; ""max"", 1; ""color"", ""#009000""}))"),"")
C59: =IFERROR(__xludf.DUMMYFUNCTION("IF(B59="""", """", SPARKLINE(B59, {""charttype"", ""bar""; ""max"", 1; ""color"", ""#009000""}))"),"")
C60: =IFERROR(__xludf.DUMMYFUNCTION("IF(B60="""", """", SPARKLINE(B60, {""charttype"", ""bar""; ""max"", 1; ""color"", ""#009000""}))"),"")
C61: =IFERROR(__xludf.DUMMYFUNCTION("IF(B61="""", """", SPARKLINE(B61, {""charttype"", ""bar""; ""max"", 1; ""color"", ""#009000""}))"),"")
C62: =IFERROR(__xludf.DUMMYFUNCTION("IF(B62="""", """", SPARKLINE(B62, {""charttype"", ""bar""; ""max"", 1; ""color"", ""#009000""}))"),"")
C63: =IFERROR(__xludf.DUMMYFUNCTION("IF(B63="""", """", SPARKLINE(B63, {""charttype"", ""bar""; ""max"", 1; ""color"", ""#009000""}))"),"")
C64: =IFERROR(__xludf.DUMMYFUNCTION("IF(B64="""", """", SPARKLINE(B64, {""charttype"", ""bar""; ""max"", 1; ""color"", ""#009000""}))"),"")
C65: =IFERROR(__xludf.DUMMYFUNCTION("IF(B65="""", """", SPARKLINE(B65, {""charttype"", ""bar""; ""max"", 1; ""color"", ""#009000""}))"),"")
C66: =IFERROR(__xludf.DUMMYFUNCTION("IF(B66="""", """", SPARKLINE(B66, {""charttype"", ""bar""; ""max"", 1; ""color"", ""#009000""}))"),"")
C67: =IFERROR(__xludf.DUMMYFUNCTION("IF(B67="""", """", SPARKLINE(B67, {""charttype"", ""bar""; ""max"", 1; ""color"", ""#009000""}))"),"")

Sheet Dashboard
B2: SS - MAINTENANCE OVERVIEW
B3: Total Progress | C3: =SUM(C5:C14) -> 1963 | D3: =SUM(D5:D14) -> 7882 | E3: =IFERROR(C3/D3, 0) -> 0.24904846 | F3: =IFERROR(__xludf.DUMMYFUNCTION("SPARKLINE(E3, {""charttype"", ""bar""; ""max"", 1; ""color1"", IF(E3>=0.8, ""#0F9D58"", IF(E3>=0.5, ""#F4B400"", ""#DB4437""))})"),"")
B4: PLANT NO | C4: Completed Tasks | D4: Total Tasks | E4: Progress % | F4: Dynamic Progress Bar
B5: Portaloo | C5: =IFERROR(COUNTIF(Portaloo!E2:H109, TRUE), 0) -> 36 | D5: =IFERROR(COUNTIF(Portaloo!E2:H109, TRUE)+COUNTIF(Portaloo!E2:H109, FALSE), 0) -> 432 | E5: =IFERROR(C5/D5, 0) -> 0.083333333 | F5: =IFERROR(__xludf.DUMMYFUNCTION("SPARKLINE(E5, {""charttype"", ""bar""; ""max"", 1; ""color1"", IF(E5>=0.8, ""#0F9D58"", IF(E5>=0.5, ""#F4B400"", ""#DB4437""))})"),"")
B6: NEW Flexiloos | C6: =IFERROR(COUNTIF('NEW Flexiloos'!F2:S98, TRUE), 0) -> 536 | D6: =IFERROR(COUNTIF('NEW Flexiloos'!F2:S98, TRUE)+COUNTIF('NEW Flexiloos'!A5:Z998, FALSE), 0) -> 1092 | E6: =IFERROR(C6/D6, 0) -> 0.49084249 | F6: =IFERROR(__xludf.DUMMYFUNCTION("SPARKLINE(E6, {""charttype"", ""bar""; ""max"", 1; ""color1"", IF(E6>=0.8, ""#0F9D58"", IF(E6>=0.5, ""#F4B400"", ""#DB4437""))})"),"")
B7: Flexiloo | C7: =IFERROR(COUNTIF(Flexiloo!E2:N230, TRUE), 0) -> 41 | D7: =IFERROR(COUNTIF(Flexiloo!E2:N230, TRUE)+COUNTIF(Flexiloo!E2:N230, FALSE), 0) -> 2281 | E7: =IFERROR(C7/D7, 0) -> 0.017974573 | F7: =IFERROR(__xludf.DUMMYFUNCTION("SPARKLINE(E7, {""charttype"", ""bar""; ""max"", 1; ""color1"", IF(E7>=0.8, ""#0F9D58"", IF(E7>=0.5, ""#F4B400"", ""#DB4437""))})"),"")
B8: Flatpack | C8: =IFERROR(COUNTIF(Flatpack!E2:I6, TRUE), 0) -> 0 | D8: =IFERROR(COUNTIF(Flatpack!E2:I6, TRUE)+COUNTIF(Flatpack!E2:I6, FALSE), 0) -> 25 | E8: =IFERROR(C8/D8, 0) -> 0 | F8: =IFERROR(__xludf.DUMMYFUNCTION("SPARKLINE(E8, {""charttype"", ""bar""; ""max"", 1; ""color1"", IF(E8>=0.8, ""#0F9D58"", IF(E8>=0.5, ""#F4B400"", ""#DB4437""))})"),"")
B9: New Flatpack | C9: =IFERROR(COUNTIF('New Flatpack'!F2:P56, TRUE), 0) -> 0 | D9: =IFERROR(COUNTIF('New Flatpack'!F2:P56, TRUE)+COUNTIF('New Flatpack'!F2:P56, FALSE), 0) -> 605 | E9: =IFERROR(C9/D9, 0) -> 0 | F9: =IFERROR(__xludf.DUMMYFUNCTION("SPARKLINE(E9, {""charttype"", ""bar""; ""max"", 1; ""color1"", IF(E9>=0.8, ""#0F9D58"", IF(E9>=0.5, ""#F4B400"", ""#DB4437""))})"),"")
B10: Cabins | C10: =IFERROR(COUNTIF(Cabins!E2:O274, TRUE), 0) -> 993 | D10: =IFERROR(SUMPRODUCT(((Cabins!E2:O274=TRUE) + (Cabins!E2:O274=FALSE)) * (Cabins!P2:P274<>"QIDDIYA KSA") * (Cabins!P2:P274<>"JIZZAN KSA") * (Cabins!P2:P274<>"On Hire for DUTCO MOE")), 0) -> 2221 | E10: =IFERROR(C10/D10, 0) -> 0.4470959 | F10: =IFERROR(__xludf.DUMMYFUNCTION("SPARKLINE(E10, {""charttype"", ""bar""; ""max"", 1; ""color1"", IF(E10>=0.8, ""#0F9D58"", IF(E10>=0.5, ""#F4B400"", ""#DB4437""))})"),"")
B11: Messhall | C11: =IFERROR(COUNTIF(Messhall!E2:M11, TRUE), 0) -> 0 | D11: =IFERROR(COUNTIF(Messhall!E2:M11, TRUE)+COUNTIF(Messhall!E2:M11, FALSE), 0) -> 90 | E11: =IFERROR(C11/D11, 0) -> 0 | F11: =IFERROR(__xludf.DUMMYFUNCTION("SPARKLINE(E11, {""charttype"", ""bar""; ""max"", 1; ""color1"", IF(E11>=0.8, ""#0F9D58"", IF(E11>=0.5, ""#F4B400"", ""#DB4437""))})"),"")
B12: Ablution | C12: =IFERROR(COUNTIF(Ablution!E2:R66, TRUE), 0) -> 203 | D12: =IFERROR(COUNTIF(Ablution!E2:R66, TRUE)+COUNTIF(Ablution!E2:R66, FALSE), 0) -> 888 | E12: =IFERROR(C12/D12, 0) -> 0.2286036 | F12: =IFERROR(__xludf.DUMMYFUNCTION("SPARKLINE(E12, {""charttype"", ""bar""; ""max"", 1; ""color1"", IF(E12>=0.8, ""#0F9D58"", IF(E12>=0.5, ""#F4B400"", ""#DB4437""))})"),"")
B13: Shower unit | C13: =IFERROR(COUNTIF('Shower unit'!E2:S6, TRUE), 0) -> 0 | D13: =IFERROR(COUNTIF('Shower unit'!E2:S6, TRUE)+COUNTIF('Shower unit'!E2:S6, FALSE), 0) -> 75 | E13: =IFERROR(C13/D13, 0) -> 0 | F13: =IFERROR(__xludf.DUMMYFUNCTION("SPARKLINE(E13, {""charttype"", ""bar""; ""max"", 1; ""color1"", IF(E13>=0.8, ""#0F9D58"", IF(E13>=0.5, ""#F4B400"", ""#DB4437""))})"),"")
B14: DRS | C14: =IFERROR(COUNTIF(DRS!E2:S13, TRUE), 0) -> 154 | D14: =IFERROR(COUNTIF(DRS!E2:S13, TRUE)+COUNTIF(DRS!E2:S13, FALSE), 0) -> 173 | E14: =IFERROR(C14/D14, 0) -> 0.89017341 | F14: =IFERROR(__xludf.DUMMYFUNCTION("SPARKLINE(E14, {""charttype"", ""bar""; ""max"", 1; ""color1"", IF(E14>=0.8, ""#0F9D58"", IF(E14>=0.5, ""#F4B400"", ""#DB4437""))})"),"")

Sheet VIP unit status
A2: VIP | B2: 10' | C2: D.ABL.10.3 | D2: Done
A3: 4 Door VIP | B3: 16' | C3: 4DR.ABL.16.1 | D3: Done | E3: new VIP
A4: 4 Door VIP | B4: 16' | C4: 4DR.ABL.16.2 | D4: Done | E4: new VIP
A5: 4 Door VIP | B5: 16' | C5: 4DR.ABL.16.3 | D5: Done | E5: new VIP
A6: Mixed VIP | B6: 20' | C6: ABL.M-F.20.16 | D6: Unconfirmed stacked 2 high
A7: Mixed VIP | B7: 20' | C7: ABL.M-F.20.14 | D7: Unconfirmed stacked 2 high
A8: Mixed VIP | B8: 40' | C8: ABL.M-F.40.2 | D8: major cracks new standard | E8: new VIP
A9: Mixed VIP | B9: 40' | C9: ABL.M-F.40.4 | D9: old standard whole redo | F9: Priority
A10: Mixed VIP | B10: 40' | C10: ABL.M-F.40.5 | D10: minor cracks new standard/ slightly different panles/sheets to standard but similar | E10: new VIP
A11: Mixed VIP | B11: 40' | C11: ABL.M-F.40.8 | D11: old standard whole redo | F11: Priority
A12: VIP | B12: 32' | C12: VIPABLM-F.32.1 | D12: minor cracks new standard | E12: new VIP
A13: VIP | B13: 32' | C13: VIPABLM-F.32.2 | D13: new standard | E13: new VIP

Sheet _Diagnostic
A1: [STC.20.6] dumped Fri Apr 10 2026 14:59:30 GMT+0400 (Gulf Standard Time)
A2: ---- HEADER FIELDS ----
A3: plantNo | B3: STC.20.6
A4: checkDate | B4: 46112
A5: checkType | B5: STORAGE
A6: inspector | B6: khalid
A7: note | B7: Inspection done by khalid
A8: ---- ITEMS (24) ----
A9: bullet | B9: label | C9: state
A10: a | B10: structural damage | C10: TRUE
A11: a | B11: exterior damage | C11: TRUE
A12: b | B12: plumbing | C12: NA
A13: b | B13: exterior paint | C13: TRUE
A14: c | B14: ac | C14: NA
A15: c | B15: water pump motor | C15: NA
A16: d | B16: cleaning | C16: TRUE
A17: a | B17: wash besin | C17: NA
A18: a | B18: interior damage | C18: TRUE
A19: b | B19: water taps | C19: NA
A20: b | B20: interior paint | C20: TRUE
A21: c | B21: hand soap dispenser | C21: NA
A22: c | B22: light | C22: NA
A23: d | B23: urinal | C23: NA
A24: d | B24: floor | C24: TRUE
A25: e | B25: wc | C25: NA
A26: e | B26: electrical | C26: NA
A27: f | B27: wc seat cover | C27: NA
A28: f | B28: exhaust fan | C28: NA
A29: g | B29: tissue holder | C29: NA
A30: g | B30: door | C30: TRUE
A31: h | B31: mirror | C31: NA
A32: h | B32: window | C32: NA
A33: i | B33: fire extinguisher | C33: NA
A34: ---- RAW TEXT ----
A35: AL LAITH PROJECTS SERVICES LLC
A36: P.O. Box 27349, Saih Shuaib 3, DIC, Dubai, U.A.E.
A37: Tel: +971 04 443 6360, Fax: 04-2448680
A38: Website: www.alaith.com
A39: SITE SERVICES
A40: (QC)
A41: Inspection ID: 76c59266 Inspection Date: 31-03-2026 18:38:32 Type: STORAGE Plant Number: STC.20.6
A42: 6M X 2.5M)Inspector Name: calo.lategan@allaith.com Description: STORAGE CONTAINER (20FT X 8FT -
A43: 1
A44: GENERAL
A45: 2
A46: EXTERNAL
A47: a
A48: Structural Damage
A49: ✅
A50: a
A51: Exterior Damage
A52: ✅
A53: b
A54: Plumbing
A55: N-A
A56: b
A57: Exterior Paint
... A67: ✅
A68: 4
A69: RESTROOM
A70: 3
A71: INTERNAL
A72: a
A73: Wash Besin
A74: N-A
A75: a
A76: Interior Damage
A77: ✅
A78: b
A79: Water Taps
A80: N-A
A81: b
A82: Interior Paint
... A129: Disclaimer: This Pre - Post -Delivery Inspection (PDI) report reflects the observable condition of the equipment at the time of inspection. It does not constitute a warranty, express or implied, regarding the future performance or reliability of the equipment. The inspection is limited to accessible components; no assessment has been made of concealed or non-visible defects. The company assumes no liability for any issues arising after the inspection or delivery.

Sheet _Logs
A1: Timestamp | B1: Function | C1: Message | D1: Stack
A2: 46120.668 | B2: _syncCore_ | C2: Done in 58.9s | written 1 | idempotent 0 | highlighted 0 | no-tab 0 | parse-fail 0
A3: 46120.669 | B3: _syncCore_ | C3: Done in 6.1s | written 1 | idempotent 0 | highlighted 0 | no-tab 0 | parse-fail 0
A4: 46120.672 | B4: _syncCore_ | C4: Done in 5.8s | written 1 | idempotent 0 | highlighted 0 | no-tab 0 | parse-fail 0
A5: 46120.683 | B5: _syncCore_ | C5: Done in 9.0s | written 1 | idempotent 0 | highlighted 0 | no-tab 0 | parse-fail 0
A6: 46120.686 | B6: _syncCore_ | C6: Done in 9.7s | written 1 | idempotent 0 | highlighted 0 | no-tab 0 | parse-fail 0
A7: 46120.691 | B7: _syncCore_ | C7: Done in 9.9s | written 1 | idempotent 0 | highlighted 0 | no-tab 0 | parse-fail 0
A8: 46121.523 | B8: _syncCore_ | C8: Done in 8.8s | written 1 | idempotent 0 | highlighted 0 | no-tab 0 | parse-fail 0
A9: 46121.532 | B9: reorganizeDrive | C9: Done: 0 plant folders, 0 latest PDFs, 0 archived, 22 unmatched
A10: 46121.532 | B10: reorganizeDrive | C10: Unmatched files: Copy of STC.20.6-260331 POST PDI.pdf, Copy of STC.40.5-260331 POST PDI.pdf, Copy of PL.15-260330 POST PDI.pdf, Copy of PL.30-260330 POST PDI.pdf, Copy of PL.116-260330 POST PDI.pdf, Copy of PL.59-260330 POST PDI.pdf, Copy of PL.86-260330 POST PDI.pdf, Copy of PL.145-260330 POST PDI.pdf, Copy of PL.03-260330 POST PDI.pdf, Copy of PL.161-260330 POST PDI.pdf, Copy of PL.107-260330 POST PDI.pdf, Copy of STC.20.5-260331 POST PDI.pdf, Copy of STC.40.8-260331 POST PDI.pdf, Copy of ABL.F.40.02-260404 POST PDI.pdf, Copy of DR.2.TS.32.6-260404 POST PDI.pdf, Copy of ABL.F.40.01-260404 POST PDI.pdf, Copy of DR.2T.40.01-260407 POST PDI.pdf, Copy of DR.2.T.32.9-260407 POST PDI.pdf, Copy of DR.2.T.32.3-260404 POST PDI.pdf, Copy of DR.2.TS.32.5-260404 POST PDI.pdf, Copy of DR.2.T.32.8-260404 POST PDI.pdf, Copy of PB-260403 POST PDI.pdf
A11: 46121.542 | B11: reorganizeDrive | C11: Done: 22 plant folders, 22 latest PDFs, 0 archived, 0 unmatched
A12: 46121.609 | B12: parse:DR.2.TS.32.5 | C12: API call to drive.files.copy failed with error: User rate limit exceeded. | D12: GoogleJsonResponseException: API call to drive.files.copy failed with error: User rate limit exceeded. at extractPdfTextByFileId_ (Code:607:30) at syncAllFromCopy (Code:2274:22) at __GS_INTERNAL_top_function_call__.gs:1:8
A13: 46121.609 | B13: parse:ABL.F.40.02 | C13: API call to drive.files.copy failed with error: User rate limit exceeded. | D13: GoogleJsonResponseException: API call to drive.files.copy failed with error: User rate limit exceeded. at extractPdfTextByFileId_ (Code:607:30) at syncAllFromCopy (Code:2274:22) at __GS_INTERNAL_top_function_call__.gs:1:8
A14: 46121.611 | B14: syncAllFromCopy | C14: COPY sync done in 141.6s | written 19 | idempotent 0 | highlighted 0 | no-tab 1 | parse-fail 2
A15: 46121.688 | B15: parse:ABL.F.40.02 | C15: API call to drive.files.copy failed with error: User rate limit exceeded. | D15: GoogleJsonResponseException: API call to drive.files.copy failed with error: User rate limit exceeded. at extractPdfTextByFileId_ (Code:607:30) at _syncCore_ (Code:1365:20) at syncAll (Code:1224:5) at __GS_INTERNAL_top_function_call__.gs:1:8
A16: 46121.688 | B16: _syncCore_ | C16: Done in 282.7s | written 20 | idempotent 0 | highlighted 0 | no-tab 1 | parse-fail 1
A17: 46122.357 | B17: parse:PL.107 | C17: API call to drive.files.copy failed with error: User rate limit exceeded. | D17: GoogleJsonResponseException: API call to drive.files.copy failed with error: User rate limit exceeded. at extractPdfTextByFileId_ (Code:607:30) at syncAllFromCopy (Code:2291:22) at forceSyncAllFromCopy (Code:2326:3) at __GS_INTERNAL_top_function_call__.gs:1:8
A18: 46122.358 | B18: parse:PL.15 | C18: API call to drive.files.copy failed with error: User rate limit exceeded. | D18: GoogleJsonResponseException: API call to drive.files.copy failed with error: User rate limit exceeded. at extractPdfTextByFileId_ (Code:607:30) at syncAllFromCopy (Code:2291:22) at forceSyncAllFromCopy (Code:2326:3) at __GS_INTERNAL_top_function_call__.gs:1:8
A19: 46122.358 | B19: syncAllFromCopy | C19: COPY sync done in 120.1s | written 19 | idempotent 0 | highlighted 0 | no-tab 1 | parse-fail 2
A20: 46122.363 | B20: parse:PL.145 | C20: API call to drive.files.copy failed with error: User rate limit exceeded. | D20: GoogleJsonResponseException: API call to drive.files.copy failed with error: User rate limit exceeded. at extractPdfTextByFileId_ (Code:607:30) at _syncCore_ (Code:1365:20) at syncAll (Code:1224:5) at __GS_INTERNAL_top_function_call__.gs:1:8
A21: 46122.364 | B21: parse:DR.2.T.32.3 | C21: API call to drive.files.copy failed with error: User rate limit exceeded. | D21: GoogleJsonResponseException: API call to drive.files.copy failed with error: User rate limit exceeded. at extractPdfTextByFileId_ (Code:607:30) at _syncCore_ (Code:1365:20) at syncAll (Code:1224:5) at __GS_INTERNAL_top_function_call__.gs:1:8
A22: 46122.364 | B22: _syncCore_ | C22: Done in 145.4s | written 19 | idempotent 0 | highlighted 0 | no-tab 1 | parse-fail 2
A23: 46122.37 | B23: _syncCore_ | C23: Done in 52.6s | written 2 | idempotent 19 | highlighted 0 | no-tab 1 | parse-fail 0
A24: 46122.377 | B24: _syncCore_ | C24: Done in 96.8s | written 0 | idempotent 21 | highlighted 0 | no-tab 1 | parse-fail 0
A25: 46122.383 | B25: _syncCore_ | C25: Done in 36.2s | written 0 | idempotent 21 | highlighted 0 | no-tab 1 | parse-fail 0
A26: 46122.39 | B26: _syncCore_ | C26: Done in 39.7s | written 0 | idempotent 21 | highlighted 0 | no-tab 1 | parse-fail 0
A27: 46122.397 | B27: _syncCore_ | C27: Done in 45.7s | written 0 | idempotent 21 | highlighted 0 | no-tab 1 | parse-fail 0
A28: 46122.404 | B28: _syncCore_ | C28: Done in 37.5s | written 0 | idempotent 21 | highlighted 0 | no-tab 1 | parse-fail 0
A29: 46122.411 | B29: _syncCore_ | C29: Done in 57.0s | written 0 | idempotent 21 | highlighted 0 | no-tab 1 | parse-fail 0
A30: 46122.418 | B30: _syncCore_ | C30: Done in 46.5s | written 0 | idempotent 21 | highlighted 0 | no-tab 1 | parse-fail 0
A31: 46122.425 | B31: _syncCore_ | C31: Done in 41.6s | written 0 | idempotent 21 | highlighted 0 | no-tab 1 | parse-fail 0
A32: 46122.432 | B32: _syncCore_ | C32: Done in 48.1s | written 0 | idempotent 21 | highlighted 0 | no-tab 1 | parse-fail 0
A33: 46122.438 | B33: _syncCore_ | C33: Done in 2.6s | written 0 | idempotent 0 | highlighted 0 | no-tab 0 | parse-fail 0
... A40: 46122.444 | B40: _syncCore_ | C40: Done in 24.0s | written 3 | idempotent 0 | highlighted 0 | no-tab 0 | parse-fail 0
A41: 46122.446 | B41: parse:PL.107 | C41: API call to drive.files.copy failed with error: User rate limit exceeded. | D41: GoogleJsonResponseException: API call to drive.files.copy failed with error: User rate limit exceeded. at extractPdfTextByFileId_ (Code:607:30) at _syncCore_ (Code:1365:20) at pollSync (Code:1701:5) at __GS_INTERNAL_top_function_call__.gs:1:8
A42: 46122.446 | B42: parse:PL.86 | C42: API call to drive.files.copy failed with error: User rate limit exceeded. | D42: GoogleJsonResponseException: API call to drive.files.copy failed with error: User rate limit exceeded. at extractPdfTextByFileId_ (Code:607:30) at _syncCore_ (Code:1365:20) at pollSync (Code:1701:5) at __GS_INTERNAL_top_function_call__.gs:1:8
A43: 46122.446 | B43: parse:PL.03 | C43: API call to drive.files.copy failed with error: User rate limit exceeded. | D43: GoogleJsonResponseException: API call to drive.files.copy failed with error: User rate limit exceeded. at extractPdfTextByFileId_ (Code:607:30) at _syncCore_ (Code:1365:20) at pollSync (Code:1701:5) at __GS_INTERNAL_top_function_call__.gs:1:8
A44: 46122.446 | B44: parse:STC.20.5 | C44: API call to drive.files.copy failed with error: User rate limit exceeded. | D44: GoogleJsonResponseException: API call to drive.files.copy failed with error: User rate limit exceeded. at extractPdfTextByFileId_ (Code:607:30) at _syncCore_ (Code:1365:20) at pollSync (Code:1701:5) at __GS_INTERNAL_top_function_call__.gs:1:8
A45: 46122.447 | B45: _syncCore_ | C45: Done in 135.0s | written 17 | idempotent 0 | highlighted 0 | no-tab 1 | parse-fail 4
A47: 46122.452 | B47: _syncCore_ | C47: Done in 7.9s | written 0 | idempotent 0 | highlighted 0 | no-tab 0 | parse-fail 0 | dl-fail 0
A48: 46122.46 | B48: _syncCore_ | C48: Done in 19.4s | written 0 | idempotent 0 | highlighted 0 | no-tab 0 | parse-fail 0 | dl-fail 0
A49: 46122.467 | B49: _syncCore_ | C49: Done in 63.8s | written 21 | idempotent 0 | highlighted 0 | no-tab 1 | parse-fail 0 | dl-fail 0
A50: 46122.474 | B50: _syncCore_ | C50: Done in 80.7s | written 13 | idempotent 8 | highlighted 0 | no-tab 1 | parse-fail 0 | dl-fail 0
A51: 46122.481 | B51: _syncCore_ | C51: Done in 58.6s | written 0 | idempotent 21 | highlighted 0 | no-tab 1 | parse-fail 0 | dl-fail 0
A52: 46122.488 | B52: _syncCore_ | C52: Done in 63.0s | written 0 | idempotent 21 | highlighted 0 | no-tab 1 | parse-fail 0 | dl-fail 0
A53: 46122.495 | B53: _syncCore_ | C53: Done in 53.2s | written 1 | idempotent 20 | highlighted 0 | no-tab 1 | parse-fail 0
A54: 46122.502 | B54: _syncCore_ | C54: Done in 95.4s | written 0 | idempotent 21 | highlighted 0 | no-tab 1 | parse-fail 0
A55: 46122.508 | B55: _syncCore_ | C55: Done in 47.2s | written 0 | idempotent 21 | highlighted 0 | no-tab 1 | parse-fail 0
A56: 46122.516 | B56: _syncCore_ | C56: Done in 115.7s | written 0 | idempotent 21 | highlighted 0 | no-tab 1 | parse-fail 0
A57: 46122.522 | B57: _syncCore_ | C57: Done in 56.6s | written 0 | idempotent 21 | highlighted 0 | no-tab 1 | parse-fail 0
... A1176: 46137.108 | B1176: _syncCore_ | C1176: Done in 17.9s | written 84 | cached 44 | idempotent 0 | highlighted 0 | override 0 | no-tab 2 | parse-fail 0 | dl-fail 0
A1177: 46137.114 | B1177: pollSync | C1177: We're sorry, a server error occurred. Please wait a bit and try again. | D1177: Exception: We're sorry, a server error occurred. Please wait a bit and try again. at cleanupTriggers_ (Continuation:80:59) at clearResumeState_ (Continuation:42:3) at _syncCore_ (SyncEngine:340:3) at pollSync (DrivePush:98:5) at __GS_INTERNAL_top_function_call__.gs:1:8
A1178: 46137.121 | B1178: _syncCore_ | C1178: Done in 23.6s | written 84 | cached 44 | idempotent 0 | highlighted 0 | override 0 | no-tab 2 | parse-fail 0 | dl-fail 0
A1179: 46137.128 | B1179: _syncCore_ | C1179: Done in 25.7s | written 84 | cached 44 | idempotent 0 | highlighted 0 | override 0 | no-tab 2 | parse-fail 0 | dl-fail 0
A1180: 46137.135 | B1180: _syncCore_ | C1180: Done in 16.0s | written 84 | cached 44 | idempotent 0 | highlighted 0 | override 0 | no-tab 2 | parse-fail 0 | dl-fail 0
A1181: 46137.142 | B1181: _syncCore_ | C1181: Done in 12.0s | written 84 | cached 44 | idempotent 0 | highlighted 0 | override 0 | no-tab 2 | parse-fail 0 | dl-fail 0
A1182: 46137.149 | B1182: _syncCore_ | C1182: Done in 13.1s | written 84 | cached 44 | idempotent 0 | highlighted 0 | override 0 | no-tab 2 | parse-fail 0 | dl-fail 0
A1183: 46137.156 | B1183: _syncCore_ | C1183: Done in 24.8s | written 84 | cached 44 | idempotent 0 | highlighted 0 | override 0 | no-tab 2 | parse-fail 0 | dl-fail 0
A1184: 46137.163 | B1184: _syncCore_ | C1184: Done in 18.2s | written 84 | cached 44 | idempotent 0 | highlighted 0 | override 0 | no-tab 2 | parse-fail 0 | dl-fail 0
A1185: 46137.17 | B1185: _syncCore_ | C1185: Done in 15.5s | written 84 | cached 44 | idempotent 0 | highlighted 0 | override 0 | no-tab 2 | parse-fail 0 | dl-fail 0
A1186: 46137.177 | B1186: _syncCore_ | C1186: Done in 14.3s | written 84 | cached 44 | idempotent 0 | highlighted 0 | override 0 | no-tab 2 | parse-fail 0 | dl-fail 0
A1187: 46137.184 | B1187: _syncCore_ | C1187: Done in 29.3s | written 84 | cached 44 | idempotent 0 | highlighted 0 | override 0 | no-tab 2 | parse-fail 0 | dl-fail 0
A1188: 46137.191 | B1188: _syncCore_ | C1188: Done in 15.4s | written 84 | cached 44 | idempotent 0 | highlighted 0 | override 0 | no-tab 2 | parse-fail 0 | dl-fail 0
A1189: 46137.198 | B1189: _syncCore_ | C1189: Done in 13.7s | written 84 | cached 44 | idempotent 0 | highlighted 0 | override 0 | no-tab 2 | parse-fail 0 | dl-fail 0
... A2493: 46146.267 | B2493: _syncCore_ | C2493: Done in 10.8s | written 84 | cached 44 | idempotent 0 | highlighted 0 | override 0 | no-tab 2 | parse-fail 0 | dl-fail 0
A2494: 46146.274 | B2494: pollSync | C2494: Service Spreadsheets failed while accessing document with ID 1G1mP78mIpVpddiWkut-d2Br04RaXTf5PW-VnIS3ayOA. | D2494: Exception: Service Spreadsheets failed while accessing document with ID 1G1mP78mIpVpddiWkut-d2Br04RaXTf5PW-VnIS3ayOA. at plantNoColIdx_ (SheetContext:15:25) at buildTabContext_ (SheetContext:78:20) at _syncCore_ (SyncEngine:163:35) at pollSync (DrivePush:98:5) at __GS_INTERNAL_top_function_call__.gs:1:8
A2495: 46146.281 | B2495: _syncCore_ | C2495: Done in 21.0s | written 84 | cached 44 | idempotent 0 | highlighted 0 | override 0 | no-tab 2 | parse-fail 0 | dl-fail 0
A2496: 46146.288 | B2496: _syncCore_ | C2496: Done in 15.5s | written 84 | cached 44 | idempotent 0 | highlighted 0 | override 0 | no-tab 2 | parse-fail 0 | dl-fail 0
A2497: 46146.295 | B2497: _syncCore_ | C2497: Done in 13.8s | written 84 | cached 44 | idempotent 0 | highlighted 0 | override 0 | no-tab 2 | parse-fail 0 | dl-fail 0
A2498: 46146.302 | B2498: _syncCore_ | C2498: Done in 13.6s | written 84 | cached 44 | idempotent 0 | highlighted 0 | override 0 | no-tab 2 | parse-fail 0 | dl-fail 0
A2499: 46146.309 | B2499: _syncCore_ | C2499: Done in 25.9s | written 84 | cached 44 | idempotent 0 | highlighted 0 | override 0 | no-tab 2 | parse-fail 0 | dl-fail 0
A2500: 46146.316 | B2500: _syncCore_ | C2500: Done in 13.3s | written 84 | cached 44 | idempotent 0 | highlighted 0 | override 0 | no-tab 2 | parse-fail 0 | dl-fail 0
A2501: 46146.323 | B2501: _syncCore_ | C2501: Done in 16.3s | written 84 | cached 44 | idempotent 0 | highlighted 0 | override 0 | no-tab 2 | parse-fail 0 | dl-fail 0
A2502: 46146.33 | B2502: _syncCore_ | C2502: Done in 17.4s | written 84 | cached 44 | idempotent 0 | highlighted 0 | override 0 | no-tab 2 | parse-fail 0 | dl-fail 0
A2503: 46146.337 | B2503: _syncCore_ | C2503: Done in 10.1s | written 84 | cached 44 | idempotent 0 | highlighted 0 | override 0 | no-tab 2 | parse-fail 0 | dl-fail 0
A2504: 46146.344 | B2504: _syncCore_ | C2504: Done in 15.0s | written 84 | cached 44 | idempotent 0 | highlighted 0 | override 0 | no-tab 2 | parse-fail 0 | dl-fail 0
A2505: 46146.351 | B2505: _syncCore_ | C2505: Done in 13.0s | written 84 | cached 44 | idempotent 0 | highlighted 0 | override 0 | no-tab 2 | parse-fail 0 | dl-fail 0
A2506: 46146.357 | B2506: _syncCore_ | C2506: Done in 12.2s | written 84 | cached 44 | idempotent 0 | highlighted 0 | override 0 | no-tab 2 | parse-fail 0 | dl-fail 0
... A6434: 46173.433 | B6434: _syncCore_ | C6434: Done in 22.6s | written 108 | cached 60 | idempotent 0 | highlighted 6 | override 0 | no-tab 2 | parse-fail 0 | dl-fail 0
A6435: 46173.44 | B6435: pollSync | C6435: Unable to talk to trigger service | D6435: Exception: Unable to talk to trigger service at cleanupTriggers_ (Continuation:78:30) at queueInsuranceTrigger_ (Continuation:50:3) at _syncCore_ (SyncEngine:114:3) at pollSync (DrivePush:98:5) at __GS_INTERNAL_top_function_call__.gs:1:8
A6436: 46173.447 | B6436: pollSync | C6436: Unable to talk to trigger service | D6436: Exception: Unable to talk to trigger service at cleanupTriggers_ (Continuation:78:30) at queueInsuranceTrigger_ (Continuation:50:3) at _syncCore_ (SyncEngine:114:3) at pollSync (DrivePush:98:5) at __GS_INTERNAL_top_function_call__.gs:1:8
A6437: 46173.454 | B6437: _syncCore_ | C6437: Done in 18.8s | written 108 | cached 60 | idempotent 0 | highlighted 6 | override 0 | no-tab 2 | parse-fail 0 | dl-fail 0
A6438: 46173.461 | B6438: _syncCore_ | C6438: Done in 24.8s | written 108 | cached 60 | idempotent 0 | highlighted 6 | override 0 | no-tab 2 | parse-fail 0 | dl-fail 0
A6439: 46173.468 | B6439: _syncCore_ | C6439: Done in 22.6s | written 108 | cached 60 | idempotent 0 | highlighted 6 | override 0 | no-tab 2 | parse-fail 0 | dl-fail 0
A6440: 46173.475 | B6440: _syncCore_ | C6440: Done in 22.2s | written 108 | cached 60 | idempotent 0 | highlighted 6 | override 0 | no-tab 2 | parse-fail 0 | dl-fail 0
A6441: 46173.482 | B6441: _syncCore_ | C6441: Done in 43.7s | written 108 | cached 60 | idempotent 0 | highlighted 6 | override 0 | no-tab 2 | parse-fail 0 | dl-fail 0
A6442: 46173.489 | B6442: _syncCore_ | C6442: Done in 18.1s | written 108 | cached 60 | idempotent 0 | highlighted 6 | override 0 | no-tab 2 | parse-fail 0 | dl-fail 0
A6443: 46173.496 | B6443: _syncCore_ | C6443: Done in 19.1s | written 108 | cached 60 | idempotent 0 | highlighted 6 | override 0 | no-tab 2 | parse-fail 0 | dl-fail 0
A6444: 46173.503 | B6444: _syncCore_ | C6444: Done in 34.9s | written 108 | cached 60 | idempotent 0 | highlighted 6 | override 0 | no-tab 2 | parse-fail 0 | dl-fail 0
A6445: 46173.51 | B6445: _syncCore_ | C6445: Done in 17.6s | written 108 | cached 60 | idempotent 0 | highlighted 6 | override 0 | no-tab 2 | parse-fail 0 | dl-fail 0
A6446: 46173.516 | B6446: _syncCore_ | C6446: Done in 15.3s | written 108 | cached 60 | idempotent 0 | highlighted 6 | override 0 | no-tab 2 | parse-fail 0 | dl-fail 0
A6447: 46173.524 | B6447: _syncCore_ | C6447: Done in 24.8s | written 108 | cached 60 | idempotent 0 | highlighted 6 | override 0 | no-tab 2 | parse-fail 0 | dl-fail 0
A6448: 46173.53 | B6448: _syncCore_ | C6448: Done in 25.7s | written 108 | cached 60 | idempotent 0 | highlighted 6 | override 0 | no-tab 2 | parse-fail 0 | dl-fail 0
... A7935: 46183.697 | B7935: _syncCore_ | C7935: Done in 35.0s | written 112 | cached 159 | idempotent 0 | highlighted 189 | override 0 | no-tab 2 | parse-fail 0 | dl-fail 0
